Workbook
Name ___ST1: #N/A
Name ___YO1: #N/A
Name __A100000: #REF!
Name __A66000: #REF!
Name __A67000: #REF!
Name __A68000: #REF!
Name __A80000: #REF!
Name __DCN1: #REF!
Name __IntlFixup: TRUE
Name __mac03: [1]장비!$M$125
Name __mac10: [1]장비!$M$133
Name __mbh07: [1]장비!$M$21
Name __mdt02: [1]장비!$M$241
Name __mdt15: [1]장비!$M$17
Name __mgn05: [1]장비!$M$177
Name __mgp45: [1]장비!$M$237
Name __mlm10: [1]장비!$M$165
Name __mlt17: [1]장비!$M$33
Name __mmd36: [1]장비!$M$37
Name __mmr08: [1]장비!$M$45
Name __mmr10: [1]장비!$M$41
Name __mmx02: [1]장비!$M$221
Name __mtc30: [1]장비!$M$85
Name __mtd10: [1]장비!$M$49
Name __mtr08: [1]장비!$M$57
Name __mvr10: [1]장비!$M$53
Name __mwt55: [1]장비!$M$161
Name __R69496: '[2]입출재고현황 (2)'!$R$62503
Name __R70000: '[2]입출재고현황 (2)'!$R$60007
Name __R80000: '[2]입출재고현황 (2)'!$R$20007
Name __R90000: '[2]입출재고현황 (2)'!$R$20007
Name __R99000: '[2]입출재고현황 (2)'!$R$11947
Name __ST1: #N/A
Name __YO1: #N/A
Name __zz1: #REF!
Name _\Z: [3]결과조달!$GU$5658:$IV$7860
Name _1_5___공용전열공사: #REF!
Name _1_9___전산설비공사: #REF!
Name _10A_61: #N/A
Name _10A_62: #N/A
Name _10A_63: #N/A
Name _10A_64: #N/A
Name _10A_65: #N/A
Name _10A_66: #N/A
Name _10A_67: #N/A
Name _10A_68: #N/A
Name _10A_69: #N/A
Name _10A_70: #N/A
Name _10A_71: #N/A
Name _10A_72: #N/A
Name _10A_73: #N/A
Name _10A_74: #N/A
Name _10A_75: #N/A
Name _10A_76: #N/A
Name _10A_77: #N/A
Name _10A_78: #N/A
Name _10A_79: #N/A
Name _10A_80: #N/A
Name _10A_81: #N/A
Name _10A_82: #N/A

Sheet 1) Rooms
A1: ＃ WHR Monthly Closing | R1: ='[86]1. Summary'!$P$1 -> Business Performance in 2026 | S1: =$A$1 -> ＃ WHR Monthly Closing | AJ1: =$R$1 -> Business Performance in 2026 | AK1: =$A$1 -> ＃ WHR Monthly Closing | BB1: =$R$1 -> Business Performance in 2026 | BC1: =$A$1 -> ＃ WHR Monthly Closing | BT1: =$R$1 -> Business Performance in 2026 | BU1: =$A$1 -> ＃ WHR Monthly Closing | CM1: =$R$1 -> Business Performance in 2026 | CN1: =$A$1 -> ＃ WHR Monthly Closing | DE1: =$R$1 -> Business Performance in 2026 | DF1: =$A$1 -> ＃ WHR Monthly Closing | DW1: =$R$1 -> Business Performance in 2026
A3: 1. 2026년 실적 | S3: 2. 2026년 목표 | AK3: 3. 2025년 실적 | BC3: 4. 2024년 실적 | BU3: 5. 분기별 | CN3: 6. 목표 대비 증감 | DF3: 7. 목표 대비 달성률
A4: 1) ROOM | R4: * Unit : USD / Rooms | S4: =$A$4 -> 1) ROOM | AJ4: =$R$4 -> * Unit : USD / Rooms | AK4: =$S4 -> 1) ROOM | BB4: =$AJ4 -> * Unit : USD / Rooms | BC4: =$S4 -> 1) ROOM | BT4: =$AJ4 -> * Unit : USD / Rooms | BU4: =$S4 -> 1) ROOM | CM4: =$AJ4 -> * Unit : USD / Rooms | CN4: =$S4 -> 1) ROOM | DE4: =$AJ4 -> * Unit : USD / Rooms | DF4: =$S4 -> 1) ROOM
E5: Total | F5: Actual 2026 | W5: Total | X5: Budget 2026 | AO5: Total | AP5: Actual 2025 | BG5: Total | BH5: Actual 2024 | BY5: Actual 2026 | CD5: Budget 2026 | CI5: Actual 2025 | CR5: Total | CS5: Actual VS. Budget 2026 | DJ5: Total | DK5: Actual VS. Budget 2026(%)
F6: ='[86]1. Summary'!$C$6 -> 3 | G6: 1 | H6: 2 | I6: 3 | J6: 4 | K6: 5 | L6: 6 | M6: 7 | N6: 8 | O6: 9 | P6: 10 | Q6: 11 | R6: 12 | X6: =$F$6 -> 3 | Y6: =$G$6 -> 1 | Z6: =$H$6 -> 2 | AA6: =$I$6 -> 3 | AB6: =$J$6 -> 4 | AC6: =$K$6 -> 5 | AD6: =$L$6 -> 6 | AE6: =$M$6 -> 7 | AF6: =$N$6 -> 8 | AG6: =$O$6 -> 9 | AH6: =$P$6 -> 10 | AI6: =$Q$6 -> 11 | AJ6: =$R$6 -> 12 | AP6: =$F$6 -> 3 | AQ6: =$G$6 -> 1 | AR6: =$H$6 -> 2 | AS6: =$I$6 -> 3 | AT6: =$J$6 -> 4 | AU6: =$K$6 -> 5 | AV6: =$L$6 -> 6 | AW6: =$M$6 -> 7 | AX6: =$N$6 -> 8 | AY6: =$O$6 -> 9 | AZ6: =$P$6 -> 10 | BA6: =$Q$6 -> 11 | BB6: =$R$6 -> 12 | BH6: =$F$6 -> 3 | BI6: =$G$6 -> 1 | BJ6: =$H$6 -> 2 | BK6: =$I$6 -> 3 | BL6: =$J$6 -> 4 | BM6: =$K$6 -> 5 | BN6: =$L$6 -> 6 | BO6: =$M$6 -> 7 | BP6: =$N$6 -> 8 | BQ6: =$O$6 -> 9 | BR6: =$P$6 -> 10 | BS6: =$Q$6 -> 11 | BT6: =$R$6 -> 12 | BY6: Total | BZ6: 1 | CA6: 2 | CB6: 3 | CC6: 4 | CD6: Total | CE6: 1 | CF6: 2 | CG6: 3 | CH6: 4 | CI6: Total | CJ6: 1 | CK6: 2 | CL6: 3 | CM6: 4 | CS6: =$F$6 -> 3 | CT6: =$G$6 -> 1 | CU6: =$H$6 -> 2 | CV6: =$I$6 -> 3 | CW6: =$J$6 -> 4 | CX6: =$K$6 -> 5 | CY6: =$L$6 -> 6 | CZ6: =$M$6 -> 7 | DA6: =$N$6 -> 8 | DB6: =$O$6 -> 9 | DC6: =$P$6 -> 10 | DD6: =$Q$6 -> 11 | DE6: =$R$6 -> 12 | DK6: =$F$6 -> 3 | DL6: =$G$6 -> 1 | DM6: =$H$6 -> 2 | DN6: =$I$6 -> 3 | DO6: =$J$6 -> 4 | DP6: =$K$6 -> 5 | DQ6: =$L$6 -> 6 | DR6: =$M$6 -> 7 | DS6: =$N$6 -> 8 | DT6: =$O$6 -> 9 | DU6: =$P$6 -> 10 | DV6: =$Q$6 -> 11 | DW6: =$R$6 -> 12
B7: OCC | E7: =IFERROR(E9/E8,0) -> 0.8300202 | F7: =IFERROR(F9/F8,0) -> 0.8300202 | G7: =IFERROR(G9/G8,0) -> 0.85231672 | H7: =IFERROR(H9/H8,0) -> 0.84792208 | I7: =IFERROR(I9/I8,0) -> 0.79155425 | J7: =IFERROR(J9/J8,0) -> 0 | K7: =IFERROR(K9/K8,0) -> 0 | L7: =IFERROR(L9/L8,0) -> 0 | ... R7: =IFERROR(R9/R8,0) -> 0 | T7: OCC | W7: =IFERROR(W9/W8,0) -> 0.88900623 | X7: =IFERROR(X9/X8,0) -> 0.8760404 | Y7: =IFERROR(Y9/Y8,0) -> 0.87120235 | Z7: =IFERROR(Z9/Z8,0) -> 0.89285714 | AA7: =IFERROR(AA9/AA8,0) -> 0.86568915 | AB7: =IFERROR(AB9/AB8,0) -> 0.89527273 | AC7: =IFERROR(AC9/AC8,0) -> 0.90017595 | AD7: =IFERROR(AD9/AD8,0) -> 0.91818182 | ... AJ7: =IFERROR(AJ9/AJ8,0) -> 0.87343109 | AL7: =$T7 -> OCC | AO7: =IFERROR(AO9/AO8,0) -> 0.88022914 | AP7: =IFERROR(AP9/AP8,0) -> 0.88767677 | AQ7: =IFERROR(AQ9/AQ8,0) -> 0.8914956 | AR7: =IFERROR(AR9/AR8,0) -> 0.89155844 | AS7: =IFERROR(AS9/AS8,0) -> 0.88035191 | AT7: =IFERROR(AT9/AT8,0) -> 0.89418182 | AU7: =IFERROR(AU9/AU8,0) -> 0.90181818 | AV7: =IFERROR(AV9/AV8,0) -> 0.91030303 | ... BB7: =IFERROR(BB9/BB8,0) -> 0.87695015 | BD7: =$T7 -> OCC | BG7: =IFERROR(BG9/BG8,0) -> 0.87852956 | BH7: =IFERROR(BH9/BH8,0) -> 0.89230769 | BI7: =IFERROR(BI9/BI8,0) -> 0.90510264 | BJ7: =IFERROR(BJ9/BJ8,0) -> 0.91210031 | BK7: =IFERROR(BK9/BK8,0) -> 0.86099707 | BL7: =IFERROR(BL9/BL8,0) -> 0.88387879 | BM7: =IFERROR(BM9/BM8,0) -> 0.88504399 | BN7: =IFERROR(BN9/BN8,0) -> 0.924 | ... BT7: =IFERROR(BT9/BT8,0) -> 0.91495601 | BV7: =$T7 -> OCC | BY7: =IFERROR(BY9/BY8,0) -> 0.8300202 | BZ7: =IFERROR(BZ9/BZ8,0) -> 0.8300202 | CA7: =IFERROR(CA9/CA8,0) -> 0 | CB7: =IFERROR(CB9/CB8,0) -> 0 | CC7: =IFERROR(CC9/CC8,0) -> 0 | CD7: =IFERROR(CD9/CD8,0) -> 0.88900623 | CE7: =IFERROR(CE9/CE8,0) -> 0.8760404 | CF7: =IFERROR(CF9/CF8,0) -> 0.9044955 | ... CM7: =IFERROR(CM9/CM8,0) -> 0.82703557 | CO7: =$T7 -> OCC | CR7: =E7-W7 -> -0.058986025 | CS7: =F7-X7 -> -0.046020202 | CT7: =G7-Y7 -> -0.01888563 | CU7: =H7-Z7 -> -0.044935065 | CV7: =I7-AA7 -> -0.074134897 | CW7: =J7-AB7 -> -0.89527273 | CX7: =K7-AC7 -> -0.90017595 | CY7: =L7-AD7 -> -0.91818182 | ... DE7: =R7-AJ7 -> -0.87343109 | DG7: =$T7 -> OCC | DJ7: =IFERROR(((E7-W7)/ABS(W7))+1,0) -> 0.93364948 | DK7: =IFERROR(((F7-X7)/ABS(X7))+1,0) -> 0.94746795 | DL7: =IFERROR(((G7-Y7)/ABS(Y7))+1,0) -> 0.97832234 | DM7: =IFERROR(((H7-Z7)/ABS(Z7))+1,0) -> 0.94967273 | DN7: =IFERROR(((I7-AA7)/ABS(AA7))+1,0) -> 0.91436314 | DO7: =IFERROR(((J7-AB7)/ABS(AB7))+1,0) -> 0 | DP7: =IFERROR(((K7-AC7)/ABS(AC7))+1,0) -> 0 | DQ7: =IFERROR(((L7-AD7)/ABS(AD7))+1,0) -> 0 | ... DW7: =IFERROR(((R7-AJ7)/ABS(AJ7))+1,0) -> 0
C8: Available Rooms | E8: =SUM(G8:R8) -> 24750 | F8: =SUMPRODUCT((G$6:R$6<=F$6)*(G8:R8)) -> 24750 | G8: 8525 | H8: 7700 | I8: 8525 | U8: Available Rooms | W8: =SUM(Y8:AJ8) -> 100375 | X8: =SUMPRODUCT((Y$6:AJ$6<=X$6)*(Y8:AJ8)) -> 24750 | Y8: 8525 | Z8: 7700 | AA8: 8525 | AB8: 8250 | AC8: 8525 | AD8: 8250 | AE8: 8525 | AF8: 8525 | AG8: 8250 | AH8: 8525 | AI8: 8250 | AJ8: 8525 | AM8: =$U8 -> Available Rooms | AO8: =SUM(AQ8:BB8) -> 100375 | AP8: =SUMPRODUCT((AQ$6:BB$6<=AP$6)*(AQ8:BB8)) -> 24750 | AQ8: 8525 | AR8: 7700 | AS8: 8525 | AT8: 8250 | AU8: 8525 | AV8: 8250 | AW8: 8525 | AX8: 8525 | AY8: 8250 | AZ8: 8525 | BA8: 8250 | BB8: 8525 | BE8: =$U8 -> Available Rooms | BG8: =SUM(BI8:BT8) -> 100650 | BH8: =SUMPRODUCT((BI$6:BT$6<=BH$6)*(BI8:BT8)) -> 25025 | BI8: 8525 | BJ8: 7975 | BK8: 8525 | BL8: 8250 | BM8: 8525 | BN8: 8250 | BO8: 8525 | BP8: 8525 | BQ8: 8250 | BR8: 8525 | BS8: 8250 | BT8: 8525 | BW8: =$U8 -> Available Rooms | BY8: =SUM(BZ8:CC8) -> 24750 | BZ8: =SUM(G8:I8) -> 24750 | CA8: =SUM(J8:L8) -> 0 | CB8: =SUM(M8:O8) -> 0 | CC8: =SUM(P8:R8) -> 0 | CD8: =SUM(CE8:CH8) -> 100375 | CE8: =SUM(Y8:AA8) -> 24750 | CF8: =SUM(AB8:AD8) -> 25025 | CG8: =SUM(AE8:AG8) -> 25300 | CH8: =SUM(AH8:AJ8) -> 25300 | CI8: =SUM(CJ8:CM8) -> 100375 | CJ8: =SUM(AQ8:AS8) -> 24750 | CK8: =SUM(AT8:AV8) -> 25025 | CL8: =SUM(AW8:AY8) -> 25300 | CM8: =SUM(AZ8:BB8) -> 25300 | CP8: =$U8 -> Available Rooms | CR8: =E8-W8 -> -75625 | CS8: =F8-X8 -> 0 | CT8: =G8-Y8 -> 0 | CU8: =H8-Z8 -> 0 | CV8: =I8-AA8 -> 0 | CW8: =J8-AB8 -> -8250 | CX8: =K8-AC8 -> -8525 | CY8: =L8-AD8 -> -8250 | ... DE8: =R8-AJ8 -> -8525 | DH8: =$U8 -> Available Rooms | DJ8: =IFERROR(((E8-W8)/ABS(W8))+1,"") -> 0.24657534 | DK8: =IFERROR(((F8-X8)/ABS(X8))+1,"") -> 1 | DL8: =IFERROR(((G8-Y8)/ABS(Y8))+1,"") -> 1 | DM8: =IFERROR(((H8-Z8)/ABS(Z8))+1,"") -> 1 | DN8: =IFERROR(((I8-AA8)/ABS(AA8))+1,"") -> 1 | DO8: =IFERROR(((J8-AB8)/ABS(AB8))+1,"") -> 0 | DP8: =IFERROR(((K8-AC8)/ABS(AC8))+1,"") -> 0 | DQ8: =IFERROR(((L8-AD8)/ABS(AD8))+1,"") -> 0 | ... DW8: =IFERROR(((R8-AJ8)/ABS(AJ8))+1,"") -> 0
C9: RN | E9: =SUM(G9:R9) -> 20543 | F9: =F12 -> 20543 | G9: =G12 -> 7266 | H9: =H12 -> 6529 | I9: =I12 -> 6748 | J9: =J12 -> 0 | K9: =K12 -> 0 | L9: =L12 -> 0 | M9: =M12 -> 0 | ... R9: =R12 -> 0 | U9: RN | W9: =SUM(Y9:AJ9) -> 89234 | X9: =X12 -> 21682 | Y9: =Y12 -> 7427 | Z9: =Z12 -> 6875 | AA9: =AA12 -> 7380 | AB9: =AB12 -> 7386 | AC9: =AC12 -> 7674 | AD9: =AD12 -> 7575 | AE9: =AE12 -> 7375 | ... AJ9: =AJ12 -> 7446 | AM9: =$U9 -> RN | AO9: =SUM(AQ9:BB9) -> 88353 | AP9: =AP12 -> 21970 | AQ9: =AQ12 -> 7600 | AR9: =AR12 -> 6865 | AS9: =AS12 -> 7505 | AT9: =AT12 -> 7377 | AU9: =AU12 -> 7688 | AV9: =AV12 -> 7510 | AW9: =AW12 -> 7746 | ... BB9: =BB12 -> 7476 | BE9: =$U9 -> RN | BG9: =SUM(BI9:BT9) -> 88424 | BH9: =BH12 -> 22330 | BI9: =BI12 -> 7716 | BJ9: =BJ12 -> 7274 | BK9: =BK12 -> 7340 | BL9: =BL12 -> 7292 | BM9: =BM12 -> 7545 | BN9: =BN12 -> 7623 | BO9: =BO12 -> 7703 | ... BT9: =BT12 -> 7800 | BW9: =$U9 -> RN | BY9: =BY12 -> 20543 | BZ9: =SUM(G9:I9) -> 20543 | CA9: =SUM(J9:L9) -> 0 | CB9: =SUM(M9:O9) -> 0 | CC9: =SUM(P9:R9) -> 0 | CD9: =CD12 -> 89234 | CE9: =SUM(Y9:AA9) -> 21682 | CF9: =SUM(AB9:AD9) -> 22635 | CG9: =SUM(AE9:AG9) -> 22096 | CH9: =SUM(AH9:AJ9) -> 22821 | CI9: =CI12 -> 88353 | CJ9: =SUM(AQ9:AS9) -> 21970 | CK9: =SUM(AT9:AV9) -> 22575 | CL9: =SUM(AW9:AY9) -> 22884 | CM9: =SUM(AZ9:BB9) -> 20924 | CP9: =$U9 -> RN | CR9: =E9-W9 -> -68691 | CS9: =F9-X9 -> -1139 | CT9: =G9-Y9 -> -161 | CU9: =H9-Z9 -> -346 | CV9: =I9-AA9 -> -632 | CW9: =J9-AB9 -> -7386 | CX9: =K9-AC9 -> -7674 | CY9: =L9-AD9 -> -7575 | ... DE9: =R9-AJ9 -> -7446 | DH9: =$U9 -> RN | DJ9: =IFERROR(((E9-W9)/ABS(W9))+1,"") -> 0.23021494 | DK9: =IFERROR(((F9-X9)/ABS(X9))+1,"") -> 0.94746795 | DL9: =IFERROR(((G9-Y9)/ABS(Y9))+1,"") -> 0.97832234 | DM9: =IFERROR(((H9-Z9)/ABS(Z9))+1,"") -> 0.94967273 | DN9: =IFERROR(((I9-AA9)/ABS(AA9))+1,"") -> 0.91436314 | DO9: =IFERROR(((J9-AB9)/ABS(AB9))+1,"") -> 0 | DP9: =IFERROR(((K9-AC9)/ABS(AC9))+1,"") -> 0 | DQ9: =IFERROR(((L9-AD9)/ABS(AD9))+1,"") -> 0 | ... DW9: =IFERROR(((R9-AJ9)/ABS(AJ9))+1,"") -> 0
C10: ADR | E10: =E23 -> 147.09369 | F10: =F23 -> 147.09369 | G10: =G23 -> 150.37861 | H10: =H23 -> 146.29547 | I10: =I23 -> 144.32892 | J10: =J23 -> 0 | K10: =K23 -> 0 | L10: =L23 -> 0 | ... R10: =R23 -> 0 | U10: ADR | W10: =W23 -> 168.76007 | X10: =X23 -> 160.72203 | Y10: =Y23 -> 150.46452 | Z10: =Z23 -> 165.84 | AA10: =AA23 -> 166.2771 | AB10: =AB23 -> 154.30382 | AC10: =AC23 -> 164.78369 | AD10: =AD23 -> 171.26799 | ... AJ10: =AJ23 -> 187.73838 | AM10: =$U10 -> ADR | AO10: =AO23 -> 157.13402 | AP10: =AP23 -> 161.96208 | AQ10: =AQ23 -> 159.57733 | AR10: =AR23 -> 165.18753 | AS10: =AS23 -> 161.42661 | AT10: =AT23 -> 156.82902 | AU10: =AU23 -> 153.43926 | AV10: =AV23 -> 161.77295 | ... BB10: =BB23 -> 163.3739 | BE10: =$U10 -> ADR | BG10: =BG23 -> 164.71118 | BH10: =BH23 -> 165.45275 | BI10: =BI23 -> 166.98885 | BJ10: =BJ23 -> 168.73013 | BK10: =BK23 -> 160.59005 | BL10: =BL23 -> 150.47916 | BM10: =BM23 -> 156.04016 | BN10: =BN23 -> 169.46399 | ... BT10: =BT23 -> 170.62753 | BW10: =$U10 -> ADR | BY10: =BY23 -> 147.09369 | BZ10: =BZ23 -> 147.09369 | CA10: =CA23 -> 0 | CB10: =CB23 -> 0 | CC10: =CC23 -> 0 | CD10: =CD23 -> 168.76007 | CE10: =CE23 -> 160.72203 | CF10: =CF23 -> 163.53404 | ... CM10: =CM23 -> 148.28176 | CP10: =$U10 -> ADR | CR10: =E10-W10 -> -21.66638 | CS10: =F10-X10 -> -13.628339 | CT10: =G10-Y10 -> -0.085908624 | CU10: =H10-Z10 -> -19.544531 | CV10: =I10-AA10 -> -21.948184 | CW10: =J10-AB10 -> -154.30382 | CX10: =K10-AC10 -> -164.78369 | CY10: =L10-AD10 -> -171.26799 | ... DE10: =R10-AJ10 -> -187.73838 | DH10: =$U10 -> ADR | DJ10: =IFERROR(((E10-W10)/ABS(W10))+1,"") -> 0.8716143 | DK10: =IFERROR(((F10-X10)/ABS(X10))+1,"") -> 0.91520553 | DL10: =IFERROR(((G10-Y10)/ABS(Y10))+1,"") -> 0.99942904 | DM10: =IFERROR(((H10-Z10)/ABS(Z10))+1,"") -> 0.88214827 | DN10: =IFERROR(((I10-AA10)/ABS(AA10))+1,"") -> 0.86800237 | DO10: =IFERROR(((J10-AB10)/ABS(AB10))+1,"") -> 0 | DP10: =IFERROR(((K10-AC10)/ABS(AC10))+1,"") -> 0 | DQ10: =IFERROR(((L10-AD10)/ABS(AD10))+1,"") -> 0 | ... DW10: =IFERROR(((R10-AJ10)/ABS(AJ10))+1,"") -> 0
C11: Revpar | E11: =IFERROR(E17/E8,0) -> 122.09073 | F11: =IFERROR(F17/F8,0) -> 122.09073 | G11: =IFERROR(G17/G8,0) -> 128.17021 | H11: =IFERROR(H17/H8,0) -> 124.04716 | I11: =IFERROR(I17/I8,0) -> 114.24417 | J11: =IFERROR(J17/J8,0) -> 0 | K11: =IFERROR(K17/K8,0) -> 0 | L11: =IFERROR(L17/L8,0) -> 0 | ... R11: =IFERROR(R17/R8,0) -> 0 | U11: Revpar | W11: =IFERROR(W17/W8,0) -> 150.02875 | X11: =IFERROR(X17/X8,0) -> 140.79899 | Y11: =IFERROR(Y17/Y8,0) -> 131.08504 | Z11: =IFERROR(Z17/Z8,0) -> 148.07143 | AA11: =IFERROR(AA17/AA8,0) -> 143.94428 | AB11: =IFERROR(AB17/AB8,0) -> 138.144 | AC11: =IFERROR(AC17/AC8,0) -> 148.33431 | AD11: =IFERROR(AD17/AD8,0) -> 157.25515 | ... AJ11: =IFERROR(AJ17/AJ8,0) -> 163.97654 | AM11: =$U11 -> Revpar | AO11: =IFERROR(AO17/AO8,0) -> 138.31394 | AP11: =IFERROR(AP17/AP8,0) -> 143.76997 | AQ11: =IFERROR(AQ17/AQ8,0) -> 142.26249 | AR11: =IFERROR(AR17/AR8,0) -> 147.27434 | AS11: =IFERROR(AS17/AS8,0) -> 142.11223 | AT11: =IFERROR(AT17/AT8,0) -> 140.23366 | AU11: =IFERROR(AU17/AU8,0) -> 138.37432 | AV11: =IFERROR(AV17/AV8,0) -> 147.26241 | ... BB11: =IFERROR(BB17/BB8,0) -> 143.27077 | BE11: =$U11 -> Revpar | BG11: =IFERROR(BG17/BG8,0) -> 144.70364 | BH11: =IFERROR(BH17/BH8,0) -> 147.63477 | BI11: =IFERROR(BI17/BI8,0) -> 151.14205 | BJ11: =IFERROR(BJ17/BJ8,0) -> 153.89881 | BK11: =IFERROR(BK17/BK8,0) -> 138.26757 | BL11: =IFERROR(BL17/BL8,0) -> 133.00533 | BM11: =IFERROR(BM17/BM8,0) -> 138.1024 | BN11: =IFERROR(BN17/BN8,0) -> 156.58473 | ... BT11: =IFERROR(BT17/BT8,0) -> 156.11668 | BW11: =$U11 -> Revpar | BY11: =IFERROR(BY17/BY8,0) -> 122.09073 | BZ11: =IFERROR(BZ17/BZ8,0) -> 122.09073 | CA11: =IFERROR(CA17/CA8,0) -> 0 | CB11: =IFERROR(CB17/CB8,0) -> 0 | CC11: =IFERROR(CC17/CC8,0) -> 0 | CD11: =IFERROR(CD17/CD8,0) -> 150.02875 | CE11: =IFERROR(CE17/CE8,0) -> 140.79899 | CF11: =IFERROR(CF17/CF8,0) -> 147.9158 | ... CM11: =IFERROR(CM17/CM8,0) -> 122.63429 | CP11: =$U11 -> Revpar | CR11: =E11-W11 -> -27.938019 | CS11: =F11-X11 -> -18.708257 | CT11: =G11-Y11 -> -2.9148387 | CU11: =H11-Z11 -> -24.02427 | CV11: =I11-AA11 -> -29.700114 | CW11: =J11-AB11 -> -138.144 | CX11: =K11-AC11 -> -148.33431 | CY11: =L11-AD11 -> -157.25515 | ... DE11: =R11-AJ11 -> -163.97654 | DH11: =$U11 -> Revpar | DJ11: =IFERROR(((E11-W11)/ABS(W11))+1,0) -> 0.81378224 | DK11: =IFERROR(((F11-X11)/ABS(X11))+1,0) -> 0.86712791 | DL11: =IFERROR(((G11-Y11)/ABS(Y11))+1,0) -> 0.97776376 | DM11: =IFERROR(((H11-Z11)/ABS(Z11))+1,0) -> 0.83775216 | DN11: =IFERROR(((I11-AA11)/ABS(AA11))+1,0) -> 0.79366937 | DO11: =IFERROR(((J11-AB11)/ABS(AB11))+1,0) -> 0 | DP11: =IFERROR(((K11-AC11)/ABS(AC11))+1,0) -> 0 | DQ11: =IFERROR(((L11-AD11)/ABS(AD11))+1,0) -> 0 | ... DW11: =IFERROR(((R11-AJ11)/ABS(AJ11))+1,0) -> 0
B12: RN | E12: =SUM(G12:R12) -> 20543 | F12: =SUM(F13:F16) -> 20543 | G12: =SUM(G13:G16) -> 7266 | H12: =SUM(H13:H16) -> 6529 | I12: =SUM(I13:I16) -> 6748 | J12: =SUM(J13:J16) -> 0 | K12: =SUM(K13:K16) -> 0 | L12: =SUM(L13:L16) -> 0 | M12: =SUM(M13:M16) -> 0 | ... R12: =SUM(R13:R16) -> 0 | T12: RN | W12: =SUM(Y12:AJ12) -> 89234 | X12: =SUM(X13:X16) -> 21682 | Y12: =SUM(Y13:Y16) -> 7427 | Z12: =SUM(Z13:Z16) -> 6875 | AA12: =SUM(AA13:AA16) -> 7380 | AB12: =SUM(AB13:AB16) -> 7386 | AC12: =SUM(AC13:AC16) -> 7674 | AD12: =SUM(AD13:AD16) -> 7575 | AE12: =SUM(AE13:AE16) -> 7375 | ... AJ12: =SUM(AJ13:AJ16) -> 7446 | AL12: =$T12 -> RN | AO12: =SUM(AQ12:BB12) -> 88353 | AP12: =SUM(AP13:AP16) -> 21970 | AQ12: =SUM(AQ13:AQ16) -> 7600 | AR12: =SUM(AR13:AR16) -> 6865 | AS12: =SUM(AS13:AS16) -> 7505 | AT12: =SUM(AT13:AT16) -> 7377 | AU12: =SUM(AU13:AU16) -> 7688 | AV12: =SUM(AV13:AV16) -> 7510 | AW12: =SUM(AW13:AW16) -> 7746 | ... BB12: =SUM(BB13:BB16) -> 7476 | BD12: =$T12 -> RN | BG12: =SUM(BI12:BT12) -> 88424 | BH12: =SUM(BH13:BH16) -> 22330 | BI12: =SUM(BI13:BI16) -> 7716 | BJ12: =SUM(BJ13:BJ16) -> 7274 | BK12: =SUM(BK13:BK16) -> 7340 | BL12: =SUM(BL13:BL16) -> 7292 | BM12: =SUM(BM13:BM16) -> 7545 | BN12: =SUM(BN13:BN16) -> 7623 | BO12: =SUM(BO13:BO16) -> 7703 | ... BT12: =SUM(BT13:BT16) -> 7800 | BV12: =$T12 -> RN | BY12: =SUM(BY13:BY16) -> 20543 | BZ12: =SUM(BZ13:BZ16) -> 20543 | CA12: =SUM(CA13:CA16) -> 0 | CB12: =SUM(CB13:CB16) -> 0 | CC12: =SUM(CC13:CC16) -> 0 | CD12: =SUM(CD13:CD16) -> 89234 | CE12: =SUM(CE13:CE16) -> 21682 | CF12: =SUM(CF13:CF16) -> 22635 | ... CM12: =SUM(CM13:CM16) -> 20924 | CO12: =$T12 -> RN | CR12: =E12-W12 -> -68691 | CS12: =F12-X12 -> -1139 | CT12: =G12-Y12 -> -161 | CU12: =H12-Z12 -> -346 | CV12: =I12-AA12 -> -632 | CW12: =J12-AB12 -> -7386 | CX12: =K12-AC12 -> -7674 | CY12: =L12-AD12 -> -7575 | ... DE12: =R12-AJ12 -> -7446 | DG12: =$T12 -> RN | DJ12: =IFERROR(((E12-W12)/ABS(W12))+1,"") -> 0.23021494 | DK12: =IFERROR(((F12-X12)/ABS(X12))+1,"") -> 0.94746795 | DL12: =IFERROR(((G12-Y12)/ABS(Y12))+1,"") -> 0.97832234 | DM12: =IFERROR(((H12-Z12)/ABS(Z12))+1,"") -> 0.94967273 | DN12: =IFERROR(((I12-AA12)/ABS(AA12))+1,"") -> 0.91436314 | DO12: =IFERROR(((J12-AB12)/ABS(AB12))+1,"") -> 0 | DP12: =IFERROR(((K12-AC12)/ABS(AC12))+1,"") -> 0 | DQ12: =IFERROR(((L12-AD12)/ABS(AD12))+1,"") -> 0 | ... DW12: =IFERROR(((R12-AJ12)/ABS(AJ12))+1,"") -> 0
C13: Crew | E13: =SUM(G13:R13) -> 0 | F13: =SUMPRODUCT((G$6:R$6<=F$6)*(G13:R13)) -> 0 | G13: 0 | H13: 0 | I13: 0 | U13: Crew | W13: =SUM(Y13:AJ13) -> 0 | X13: =SUMPRODUCT((Y$6:AJ$6<=X$6)*(Y13:AJ13)) -> 0 | Y13: 0 | Z13: 0 | AA13: 0 | AB13: 0 | AC13: 0 | AD13: 0 | AE13: 0 | AF13: 0 | AG13: 0 | AH13: 0 | AI13: 0 | AJ13: 0 | AM13: =$U13 -> Crew | AO13: =SUM(AQ13:BB13) -> 7905 | AP13: =SUMPRODUCT((AQ$6:BB$6<=AP$6)*(AQ13:BB13)) -> 2792 | AQ13: 956 | AR13: 874 | AS13: 962 | AT13: 902 | AU13: 954 | AV13: 911 | AW13: 960 | AX13: 964 | AY13: 422 | AZ13: 0 | BA13: 0 | BB13: 0 | BE13: =$U13 -> Crew | BG13: =SUM(BI13:BT13) -> 10512 | BH13: =SUMPRODUCT((BI$6:BT$6<=BH$6)*(BI13:BT13)) -> 1721 | BI13: 596 | BJ13: 555 | BK13: 570 | BL13: 948 | BM13: 1045 | BN13: 1022 | BO13: 1064 | BP13: 1053 | BQ13: 1001 | BR13: 918 | BS13: 781 | BT13: 959 | BW13: =$U13 -> Crew | BY13: =SUM(BZ13:CC13) -> 0 | BZ13: =SUM(G13:I13) -> 0 | CA13: =SUM(J13:L13) -> 0 | CB13: =SUM(M13:O13) -> 0 | CC13: =SUM(P13:R13) -> 0 | CD13: =SUM(CE13:CH13) -> 0 | CE13: =SUM(Y13:AA13) -> 0 | CF13: =SUM(AB13:AD13) -> 0 | CG13: =SUM(AE13:AG13) -> 0 | CH13: =SUM(AH13:AJ13) -> 0 | CI13: =SUM(CJ13:CM13) -> 7905 | CJ13: =SUM(AQ13:AS13) -> 2792 | CK13: =SUM(AT13:AV13) -> 2767 | CL13: =SUM(AW13:AY13) -> 2346 | CM13: =SUM(AZ13:BB13) -> 0 | CP13: =$U13 -> Crew | CR13: =E13-W13 -> 0 | CS13: =F13-X13 -> 0 | CT13: =G13-Y13 -> 0 | CU13: =H13-Z13 -> 0 | CV13: =I13-AA13 -> 0 | CW13: =J13-AB13 -> 0 | CX13: =K13-AC13 -> 0 | CY13: =L13-AD13 -> 0 | ... DE13: =R13-AJ13 -> 0 | DH13: =$U13 -> Crew | DJ13: =IFERROR(((E13-W13)/ABS(W13))+1,"") | DK13: =IFERROR(((F13-X13)/ABS(X13))+1,"") | DL13: =IFERROR(((G13-Y13)/ABS(Y13))+1,"") | DM13: =IFERROR(((H13-Z13)/ABS(Z13))+1,"") | DN13: =IFERROR(((I13-AA13)/ABS(AA13))+1,"") | DO13: =IFERROR(((J13-AB13)/ABS(AB13))+1,"") | DP13: =IFERROR(((K13-AC13)/ABS(AC13))+1,"") | DQ13: =IFERROR(((L13-AD13)/ABS(AD13))+1,"") | ... DW13: =IFERROR(((R13-AJ13)/ABS(AJ13))+1,"")
C14: Group | E14: =SUM(G14:R14) -> 1179 | F14: =SUMPRODUCT((G$6:R$6<=F$6)*(G14:R14)) -> 1179 | G14: 221 | H14: 279 | I14: 679 | U14: Group | W14: =SUM(Y14:AJ14) -> 6550 | X14: =SUMPRODUCT((Y$6:AJ$6<=X$6)*(Y14:AJ14)) -> 1415 | Y14: 305 | Z14: 570 | AA14: 540 | AB14: 540 | AC14: 410 | AD14: 630 | AE14: 255 | AF14: 435 | AG14: 500 | AH14: 890 | AI14: 870 | AJ14: 605 | AM14: =$U14 -> Group | AO14: =SUM(AQ14:BB14) -> 5913 | AP14: =SUMPRODUCT((AQ$6:BB$6<=AP$6)*(AQ14:BB14)) -> 851 | AQ14: 125 | AR14: 148 | AS14: 578 | AT14: 721 | AU14: 241 | AV14: 569 | AW14: 237 | AX14: 710 | AY14: 272 | AZ14: 984 | BA14: 723 | BB14: 605 | BE14: =$U14 -> Group | BG14: =SUM(BI14:BT14) -> 6073 | BH14: =SUMPRODUCT((BI$6:BT$6<=BH$6)*(BI14:BT14)) -> 1564 | BI14: 372 | BJ14: 540 | BK14: 652 | BL14: 390 | BM14: 246 | BN14: 497 | BO14: 416 | BP14: 643 | BQ14: 330 | BR14: 972 | BS14: 671 | BT14: 344 | BW14: =$U14 -> Group | BY14: =SUM(BZ14:CC14) -> 1179 | BZ14: =SUM(G14:I14) -> 1179 | CA14: =SUM(J14:L14) -> 0 | CB14: =SUM(M14:O14) -> 0 | CC14: =SUM(P14:R14) -> 0 | CD14: =SUM(CE14:CH14) -> 6550 | CE14: =SUM(Y14:AA14) -> 1415 | CF14: =SUM(AB14:AD14) -> 1580 | CG14: =SUM(AE14:AG14) -> 1190 | CH14: =SUM(AH14:AJ14) -> 2365 | CI14: =SUM(CJ14:CM14) -> 5913 | CJ14: =SUM(AQ14:AS14) -> 851 | CK14: =SUM(AT14:AV14) -> 1531 | CL14: =SUM(AW14:AY14) -> 1219 | CM14: =SUM(AZ14:BB14) -> 2312 | CP14: =$U14 -> Group | CR14: =E14-W14 -> -5371 | CS14: =F14-X14 -> -236 | CT14: =G14-Y14 -> -84 | CU14: =H14-Z14 -> -291 | CV14: =I14-AA14 -> 139 | CW14: =J14-AB14 -> -540 | CX14: =K14-AC14 -> -410 | CY14: =L14-AD14 -> -630 | ... DE14: =R14-AJ14 -> -605 | DH14: =$U14 -> Group | DJ14: =IFERROR(((E14-W14)/ABS(W14))+1,"") -> 0.18 | DK14: =IFERROR(((F14-X14)/ABS(X14))+1,"") -> 0.83321555 | DL14: =IFERROR(((G14-Y14)/ABS(Y14))+1,"") -> 0.72459016 | DM14: =IFERROR(((H14-Z14)/ABS(Z14))+1,"") -> 0.48947368 | DN14: =IFERROR(((I14-AA14)/ABS(AA14))+1,"") -> 1.2574074 | DO14: =IFERROR(((J14-AB14)/ABS(AB14))+1,"") -> 0 | DP14: =IFERROR(((K14-AC14)/ABS(AC14))+1,"") -> 0 | DQ14: =IFERROR(((L14-AD14)/ABS(AD14))+1,"") -> 0 | ... DW14: =IFERROR(((R14-AJ14)/ABS(AJ14))+1,"") -> 0
C15: Transient | E15: =SUM(G15:R15) -> 14969 | F15: =SUMPRODUCT((G$6:R$6<=F$6)*(G15:R15)) -> 14969 | G15: 5590 | H15: 4589 | I15: 4790 | U15: Transient | W15: =SUM(Y15:AJ15) -> 67684 | X15: =SUMPRODUCT((Y$6:AJ$6<=X$6)*(Y15:AJ15)) -> 15912 | Y15: 5812 | Z15: 4500 | AA15: 5600 | AB15: 5656 | AC15: 5864 | AD15: 5900 | AE15: 6300 | AF15: 5964 | AG15: 5272 | AH15: 5400 | AI15: 5550 | AJ15: 5866 | AM15: =$U15 -> Transient | AO15: =SUM(AQ15:BB15) -> 62582 | AP15: =SUMPRODUCT((AQ$6:BB$6<=AP$6)*(AQ15:BB15)) -> 15580 | AQ15: 5649 | AR15: 4705 | AS15: 5226 | AT15: 4726 | AU15: 5252 | AV15: 5230 | AW15: 5787 | AX15: 5429 | AY15: 5659 | AZ15: 4912 | BA15: 4117 | BB15: 5890 | BE15: =$U15 -> Transient | BG15: =SUM(BI15:BT15) -> 57090 | BH15: =SUMPRODUCT((BI$6:BT$6<=BH$6)*(BI15:BT15)) -> 15110 | BI15: 5363 | BJ15: 4765 | BK15: 4982 | BL15: 4972 | BM15: 4607 | BN15: 4834 | BO15: 5179 | BP15: 4725 | BQ15: 3833 | BR15: 3895 | BS15: 4550 | BT15: 5385 | BW15: =$U15 -> Transient | BY15: =SUM(BZ15:CC15) -> 14969 | BZ15: =SUM(G15:I15) -> 14969 | CA15: =SUM(J15:L15) -> 0 | CB15: =SUM(M15:O15) -> 0 | CC15: =SUM(P15:R15) -> 0 | CD15: =SUM(CE15:CH15) -> 67684 | CE15: =SUM(Y15:AA15) -> 15912 | CF15: =SUM(AB15:AD15) -> 17420 | CG15: =SUM(AE15:AG15) -> 17536 | CH15: =SUM(AH15:AJ15) -> 16816 | CI15: =SUM(CJ15:CM15) -> 62582 | CJ15: =SUM(AQ15:AS15) -> 15580 | CK15: =SUM(AT15:AV15) -> 15208 | CL15: =SUM(AW15:AY15) -> 16875 | CM15: =SUM(AZ15:BB15) -> 14919 | CP15: =$U15 -> Transient | CR15: =E15-W15 -> -52715 | CS15: =F15-X15 -> -943 | CT15: =G15-Y15 -> -222 | CU15: =H15-Z15 -> 89 | CV15: =I15-AA15 -> -810 | CW15: =J15-AB15 -> -5656 | CX15: =K15-AC15 -> -5864 | CY15: =L15-AD15 -> -5900 | ... DE15: =R15-AJ15 -> -5866 | DH15: =$U15 -> Transient | DJ15: =IFERROR(((E15-W15)/ABS(W15))+1,"") -> 0.2211601 | DK15: =IFERROR(((F15-X15)/ABS(X15))+1,"") -> 0.94073655 | DL15: =IFERROR(((G15-Y15)/ABS(Y15))+1,"") -> 0.96180317 | DM15: =IFERROR(((H15-Z15)/ABS(Z15))+1,"") -> 1.0197778 | DN15: =IFERROR(((I15-AA15)/ABS(AA15))+1,"") -> 0.85535714 | DO15: =IFERROR(((J15-AB15)/ABS(AB15))+1,"") -> 0 | DP15: =IFERROR(((K15-AC15)/ABS(AC15))+1,"") -> 0 | DQ15: =IFERROR(((L15-AD15)/ABS(AD15))+1,"") -> 0 | ... DW15: =IFERROR(((R15-AJ15)/ABS(AJ15))+1,"") -> 0
C16: Wholesale | E16: =SUM(G16:R16) -> 4395 | F16: =SUMPRODUCT((G$6:R$6<=F$6)*(G16:R16)) -> 4395 | G16: 1455 | H16: 1661 | I16: 1279 | U16: Wholesale | W16: =SUM(Y16:AJ16) -> 15000 | X16: =SUMPRODUCT((Y$6:AJ$6<=X$6)*(Y16:AJ16)) -> 4355 | Y16: 1310 | Z16: 1805 | AA16: 1240 | AB16: 1190 | AC16: 1400 | AD16: 1045 | AE16: 820 | AF16: 770 | AG16: 1780 | AH16: 1545 | AI16: 1120 | AJ16: 975 | AM16: =$U16 -> Wholesale | AO16: =SUM(AQ16:BB16) -> 11953 | AP16: =SUMPRODUCT((AQ$6:BB$6<=AP$6)*(AQ16:BB16)) -> 2747 | AQ16: 870 | AR16: 1138 | AS16: 739 | AT16: 1028 | AU16: 1241 | AV16: 800 | AW16: 762 | AX16: 673 | AY16: 1009 | AZ16: 1333 | BA16: 1379 | BB16: 981 | BE16: =$U16 -> Wholesale | BG16: =SUM(BI16:BT16) -> 14749 | BH16: =SUMPRODUCT((BI$6:BT$6<=BH$6)*(BI16:BT16)) -> 3935 | BI16: 1385 | BJ16: 1414 | BK16: 1136 | BL16: 982 | BM16: 1647 | BN16: 1270 | BO16: 1044 | BP16: 765 | BQ16: 1519 | BR16: 1309 | BS16: 1166 | BT16: 1112 | BW16: =$U16 -> Wholesale | BY16: =SUM(BZ16:CC16) -> 4395 | BZ16: =SUM(G16:I16) -> 4395 | CA16: =SUM(J16:L16) -> 0 | CB16: =SUM(M16:O16) -> 0 | CC16: =SUM(P16:R16) -> 0 | CD16: =SUM(CE16:CH16) -> 15000 | CE16: =SUM(Y16:AA16) -> 4355 | CF16: =SUM(AB16:AD16) -> 3635 | CG16: =SUM(AE16:AG16) -> 3370 | CH16: =SUM(AH16:AJ16) -> 3640 | CI16: =SUM(CJ16:CM16) -> 11953 | CJ16: =SUM(AQ16:AS16) -> 2747 | CK16: =SUM(AT16:AV16) -> 3069 | CL16: =SUM(AW16:AY16) -> 2444 | CM16: =SUM(AZ16:BB16) -> 3693 | CP16: =$U16 -> Wholesale | CR16: =E16-W16 -> -10605 | CS16: =F16-X16 -> 40 | CT16: =G16-Y16 -> 145 | CU16: =H16-Z16 -> -144 | CV16: =I16-AA16 -> 39 | CW16: =J16-AB16 -> -1190 | CX16: =K16-AC16 -> -1400 | CY16: =L16-AD16 -> -1045 | ... DE16: =R16-AJ16 -> -975 | DH16: =$U16 -> Wholesale | DJ16: =IFERROR(((E16-W16)/ABS(W16))+1,"") -> 0.293 | DK16: =IFERROR(((F16-X16)/ABS(X16))+1,"") -> 1.0091848 | DL16: =IFERROR(((G16-Y16)/ABS(Y16))+1,"") -> 1.110687 | DM16: =IFERROR(((H16-Z16)/ABS(Z16))+1,"") -> 0.92022161 | DN16: =IFERROR(((I16-AA16)/ABS(AA16))+1,"") -> 1.0314516 | DO16: =IFERROR(((J16-AB16)/ABS(AB16))+1,"") -> 0 | DP16: =IFERROR(((K16-AC16)/ABS(AC16))+1,"") -> 0 | DQ16: =IFERROR(((L16-AD16)/ABS(AD16))+1,"") -> 0 | ... DW16: =IFERROR(((R16-AJ16)/ABS(AJ16))+1,"") -> 0
B17: Revenue | E17: =SUM(G17:R17) -> 3021745.7 | F17: =SUM(F18:F22) -> 3021745.7 | G17: =SUM(G18:G22) -> 1092651 | H17: =SUM(H18:H22) -> 955163.12 | I17: =SUM(I18:I22) -> 973931.53 | J17: =SUM(J18:J22) -> 0 | K17: =SUM(K18:K22) -> 0 | L17: =SUM(L18:L22) -> 0 | M17: =SUM(M18:M22) -> 0 | ... R17: =SUM(R18:R22) -> 0 | T17: Revenue | W17: =SUM(Y17:AJ17) -> 15059136 | X17: =SUM(X18:X22) -> 3484775 | Y17: =SUM(Y18:Y22) -> 1117500 | Z17: =SUM(Z18:Z22) -> 1140150 | AA17: =SUM(AA18:AA22) -> 1227125 | AB17: =SUM(AB18:AB22) -> 1139688 | AC17: =SUM(AC18:AC22) -> 1264550 | AD17: =SUM(AD18:AD22) -> 1297355 | AE17: =SUM(AE18:AE22) -> 1385310 | ... AJ17: =SUM(AJ18:AJ22) -> 1397900 | AL17: =$T17 -> Revenue | AO17: =SUM(AQ17:BB17) -> 13883262 | AP17: =SUM(AP18:AP22) -> 3558306.8 | AQ17: =SUM(AQ18:AQ22) -> 1212787.7 | AR17: =SUM(AR18:AR22) -> 1134012.4 | AS17: =SUM(AS18:AS22) -> 1211506.7 | AT17: =SUM(AT18:AT22) -> 1156927.7 | AU17: =SUM(AU18:AU22) -> 1179641.1 | AV17: =SUM(AV18:AV22) -> 1214914.9 | AW17: =SUM(AW18:AW22) -> 1339566.5 | ... BB17: =SUM(BB18:BB22) -> 1221383.3 | BD17: =$T17 -> Revenue | BG17: =SUM(BI17:BT17) -> 14564421 | BH17: =SUM(BH18:BH22) -> 3694560 | BI17: =SUM(BI18:BI22) -> 1288486 | BJ17: =SUM(BJ18:BJ22) -> 1227343 | BK17: =SUM(BK18:BK22) -> 1178731 | BL17: =SUM(BL18:BL22) -> 1097294 | BM17: =SUM(BM18:BM22) -> 1177323 | BN17: =SUM(BN18:BN22) -> 1291824 | BO17: =SUM(BO18:BO22) -> 1427372 | ... BT17: =SUM(BT18:BT22) -> 1330894.7 | BV17: =$T17 -> Revenue | BY17: =SUM(BY18:BY22) -> 3021745.7 | BZ17: =SUM(BZ18:BZ22) -> 3021745.7 | CA17: =SUM(CA18:CA22) -> 0 | CB17: =SUM(CB18:CB22) -> 0 | CC17: =SUM(CC18:CC22) -> 0 | CD17: =SUM(CD18:CD22) -> 15059136 | CE17: =SUM(CE18:CE22) -> 3484775 | CF17: =SUM(CF18:CF22) -> 3701593 | ... CM17: =SUM(CM18:CM22) -> 3102647.5 | CO17: =$T17 -> Revenue | CR17: =E17-W17 -> -12037390 | CS17: =F17-X17 -> -463029.35 | CT17: =G17-Y17 -> -24849 | CU17: =H17-Z17 -> -184986.88 | CV17: =I17-AA17 -> -253193.47 | CW17: =J17-AB17 -> -1139688 | CX17: =K17-AC17 -> -1264550 | CY17: =L17-AD17 -> -1297355 | ... DE17: =R17-AJ17 -> -1397900 | DG17: =$T17 -> Revenue | DJ17: =IFERROR(((E17-W17)/ABS(W17))+1,"") -> 0.20065863 | DK17: =IFERROR(((F17-X17)/ABS(X17))+1,"") -> 0.86712791 | DL17: =IFERROR(((G17-Y17)/ABS(Y17))+1,"") -> 0.97776376 | DM17: =IFERROR(((H17-Z17)/ABS(Z17))+1,"") -> 0.83775216 | DN17: =IFERROR(((I17-AA17)/ABS(AA17))+1,"") -> 0.79366937 | DO17: =IFERROR(((J17-AB17)/ABS(AB17))+1,"") -> 0 | DP17: =IFERROR(((K17-AC17)/ABS(AC17))+1,"") -> 0 | DQ17: =IFERROR(((L17-AD17)/ABS(AD17))+1,"") -> 0 | ... DW17: =IFERROR(((R17-AJ17)/ABS(AJ17))+1,"") -> 0
C18: Crew | E18: =SUM(G18:R18) -> 0 | F18: =SUMPRODUCT((G$6:R$6<=F$6)*(G18:R18)) -> 0 | G18: 0 | H18: 0 | I18: 0 | U18: Crew | W18: =SUM(Y18:AJ18) -> 0 | X18: =SUMPRODUCT((Y$6:AJ$6<=X$6)*(Y18:AJ18)) -> 0 | Y18: 0 | Z18: 0 | AA18: 0 | AB18: 0 | AC18: 0 | AD18: 0 | AE18: 0 | AF18: 0 | AG18: 0 | AH18: 0 | AI18: 0 | AJ18: 0 | AM18: =$U18 -> Crew | AO18: =SUM(AQ18:BB18) -> 1234455 | AP18: =SUMPRODUCT((AQ$6:BB$6<=AP$6)*(AQ18:BB18)) -> 436020 | AQ18: 149136 | AR18: 136344 | AS18: 150540 | AT18: 140712 | AU18: 148668 | AV18: 142116 | AW18: 149694 | AX18: 151212 | AY18: 66033 | AZ18: 0 | BA18: 0 | BB18: 0 | BE18: =$U18 -> Crew | BG18: =SUM(BI18:BT18) -> 1639750 | BH18: =SUMPRODUCT((BI$6:BT$6<=BH$6)*(BI18:BT18)) -> 268822 | BI18: 92976 | BJ18: 86926 | BK18: 88920 | BL18: 147576 | BM18: 163020 | BN18: 159432 | BO18: 165984 | BP18: 164268 | BQ18: 156000 | BR18: 143208 | BS18: 121836 | BT18: 149604 | BW18: =$U18 -> Crew | BY18: =SUM(BZ18:CC18) -> 0 | BZ18: =SUM(G18:I18) -> 0 | CA18: =SUM(J18:L18) -> 0 | CB18: =SUM(M18:O18) -> 0 | CC18: =SUM(P18:R18) -> 0 | CD18: =SUM(CE18:CH18) -> 0 | CE18: =SUM(Y18:AA18) -> 0 | CF18: =SUM(AB18:AD18) -> 0 | CG18: =SUM(AE18:AG18) -> 0 | CH18: =SUM(AH18:AJ18) -> 0 | CI18: =SUM(CJ18:CM18) -> 1234455 | CJ18: =SUM(AQ18:AS18) -> 436020 | CK18: =SUM(AT18:AV18) -> 431496 | CL18: =SUM(AW18:AY18) -> 366939 | CM18: =SUM(AZ18:BB18) -> 0 | CP18: =$U18 -> Crew | CR18: =E18-W18 -> 0 | CS18: =F18-X18 -> 0 | CT18: =G18-Y18 -> 0 | CU18: =H18-Z18 -> 0 | CV18: =I18-AA18 -> 0 | CW18: =J18-AB18 -> 0 | CX18: =K18-AC18 -> 0 | CY18: =L18-AD18 -> 0 | ... DE18: =R18-AJ18 -> 0 | DH18: =$U18 -> Crew | DJ18: =IFERROR(((E18-W18)/ABS(W18))+1,"") | DK18: =IFERROR(((F18-X18)/ABS(X18))+1,"") | DL18: =IFERROR(((G18-Y18)/ABS(Y18))+1,"") | DM18: =IFERROR(((H18-Z18)/ABS(Z18))+1,"") | DN18: =IFERROR(((I18-AA18)/ABS(AA18))+1,"") | DO18: =IFERROR(((J18-AB18)/ABS(AB18))+1,"") | DP18: =IFERROR(((K18-AC18)/ABS(AC18))+1,"") | DQ18: =IFERROR(((L18-AD18)/ABS(AD18))+1,"") | ... DW18: =IFERROR(((R18-AJ18)/ABS(AJ18))+1,"")
C19: Group | E19: =SUM(G19:R19) -> 194874 | F19: =SUMPRODUCT((G$6:R$6<=F$6)*(G19:R19)) -> 194874 | G19: 39053 | H19: 50112 | I19: 105709 | U19: Group | W19: =SUM(Y19:AJ19) -> 1005005 | X19: =SUMPRODUCT((Y$6:AJ$6<=X$6)*(Y19:AJ19)) -> 231575 | Y19: 52500 | Z19: 95050 | AA19: 84025 | AB19: 78210 | AC19: 60450 | AD19: 102480 | AE19: 44625 | AF19: 71850 | AG19: 72450 | AH19: 127365 | AI19: 129900 | AJ19: 86100 | AM19: =$U19 -> Group | AO19: =SUM(AQ19:BB19) -> 944360.5 | AP19: =SUMPRODUCT((AQ$6:BB$6<=AP$6)*(AQ19:BB19)) -> 149257 | AQ19: 24369 | AR19: 24983 | AS19: 99905 | AT19: 104616 | AU19: 36067 | AV19: 92467 | AW19: 41955 | AX19: 121008 | AY19: 38815 | AZ19: 149479 | BA19: 119658.5 | BB19: 91038 | BE19: =$U19 -> Group | BG19: =SUM(BI19:BT19) -> 1034156.3 | BH19: =SUMPRODUCT((BI$6:BT$6<=BH$6)*(BI19:BT19)) -> 278603 | BI19: 68476 | BJ19: 98502 | BK19: 111625 | BL19: 57378 | BM19: 35470 | BN19: 83767 | BO19: 77060 | BP19: 119045 | BQ19: 49457 | BR19: 163725 | BS19: 113777 | BT19: 55874.31 | BW19: =$U19 -> Group | BY19: =SUM(BZ19:CC19) -> 194874 | BZ19: =SUM(G19:I19) -> 194874 | CA19: =SUM(J19:L19) -> 0 | CB19: =SUM(M19:O19) -> 0 | CC19: =SUM(P19:R19) -> 0 | CD19: =SUM(CE19:CH19) -> 1005005 | CE19: =SUM(Y19:AA19) -> 231575 | CF19: =SUM(AB19:AD19) -> 241140 | CG19: =SUM(AE19:AG19) -> 188925 | CH19: =SUM(AH19:AJ19) -> 343365 | CI19: =SUM(CJ19:CM19) -> 944360.5 | CJ19: =SUM(AQ19:AS19) -> 149257 | CK19: =SUM(AT19:AV19) -> 233150 | CL19: =SUM(AW19:AY19) -> 201778 | CM19: =SUM(AZ19:BB19) -> 360175.5 | CP19: =$U19 -> Group | CR19: =E19-W19 -> -810131 | CS19: =F19-X19 -> -36701 | CT19: =G19-Y19 -> -13447 | CU19: =H19-Z19 -> -44938 | CV19: =I19-AA19 -> 21684 | CW19: =J19-AB19 -> -78210 | CX19: =K19-AC19 -> -60450 | CY19: =L19-AD19 -> -102480 | ... DE19: =R19-AJ19 -> -86100 | DH19: =$U19 -> Group | DJ19: =IFERROR(((E19-W19)/ABS(W19))+1,"") -> 0.19390351 | DK19: =IFERROR(((F19-X19)/ABS(X19))+1,"") -> 0.84151571 | DL19: =IFERROR(((G19-Y19)/ABS(Y19))+1,"") -> 0.74386667 | DM19: =IFERROR(((H19-Z19)/ABS(Z19))+1,"") -> 0.52721725 | DN19: =IFERROR(((I19-AA19)/ABS(AA19))+1,"") -> 1.2580661 | DO19: =IFERROR(((J19-AB19)/ABS(AB19))+1,"") -> 0 | DP19: =IFERROR(((K19-AC19)/ABS(AC19))+1,"") -> 0 | DQ19: =IFERROR(((L19-AD19)/ABS(AD19))+1,"") -> 0 | ... DW19: =IFERROR(((R19-AJ19)/ABS(AJ19))+1,"") -> 0
C20: Transient | E20: =SUM(G20:R20) -> 1986002.6 | F20: =SUMPRODUCT((G$6:R$6<=F$6)*(G20:R20)) -> 1986002.6 | G20: 748448 | H20: 607553.12 | I20: 630001.52 | U20: Transient | W20: =SUM(Y20:AJ20) -> 11542386 | X20: =SUMPRODUCT((Y$6:AJ$6<=X$6)*(Y20:AJ20)) -> 2480400 | Y20: 824600 | Z20: 725200 | AA20: 930600 | AB20: 874428 | AC20: 979800 | AD20: 1017000 | AE20: 1184100 | AF20: 1063208 | AG20: 938400 | AH20: 906500 | AI20: 957550 | AJ20: 1141000 | AM20: =$U20 -> Transient | AO20: =SUM(AQ20:BB20) -> 9649856.5 | AP20: =SUMPRODUCT((AQ$6:BB$6<=AP$6)*(AQ20:BB20)) -> 2432326.9 | AQ20: 854748.98 | AR20: 751739.75 | AS20: 825838.18 | AT20: 741268.3 | AU20: 789595.47 | AV20: 840947.42 | AW20: 1002890.8 | AX20: 870457.73 | AY20: 798824.54 | AZ20: 672654.42 | BA20: 530549.31 | BB20: 970341.52 | BE20: =$U20 -> Transient | BG20: =SUM(BI20:BT20) -> 9366045.7 | BH20: =SUMPRODUCT((BI$6:BT$6<=BH$6)*(BI20:BT20)) -> 2399779 | BI20: 859069 | BJ20: 775530 | BK20: 765180 | BL20: 737988 | BM20: 732299 | BN20: 837289 | BO20: 979986 | BP20: 844745 | BQ20: 665540 | BR20: 597878 | BS20: 644623.34 | BT20: 925918.4 | BW20: =$U20 -> Transient | BY20: =SUM(BZ20:CC20) -> 1986002.6 | BZ20: =SUM(G20:I20) -> 1986002.6 | CA20: =SUM(J20:L20) -> 0 | CB20: =SUM(M20:O20) -> 0 | CC20: =SUM(P20:R20) -> 0 | CD20: =SUM(CE20:CH20) -> 11542386 | CE20: =SUM(Y20:AA20) -> 2480400 | CF20: =SUM(AB20:AD20) -> 2871228 | CG20: =SUM(AE20:AG20) -> 3185708 | CH20: =SUM(AH20:AJ20) -> 3005050 | CI20: =SUM(CJ20:CM20) -> 9649856.5 | CJ20: =SUM(AQ20:AS20) -> 2432326.9 | CK20: =SUM(AT20:AV20) -> 2371811.2 | CL20: =SUM(AW20:AY20) -> 2672173.1 | CM20: =SUM(AZ20:BB20) -> 2173545.2 | CP20: =$U20 -> Transient | CR20: =E20-W20 -> -9556383.4 | CS20: =F20-X20 -> -494397.36 | CT20: =G20-Y20 -> -76152 | CU20: =H20-Z20 -> -117646.88 | CV20: =I20-AA20 -> -300598.48 | CW20: =J20-AB20 -> -874428 | CX20: =K20-AC20 -> -979800 | CY20: =L20-AD20 -> -1017000 | ... DE20: =R20-AJ20 -> -1141000 | DH20: =$U20 -> Transient | DJ20: =IFERROR(((E20-W20)/ABS(W20))+1,"") -> 0.17206171 | DK20: =IFERROR(((F20-X20)/ABS(X20))+1,"") -> 0.80067837 | DL20: =IFERROR(((G20-Y20)/ABS(Y20))+1,"") -> 0.90764977 | DM20: =IFERROR(((H20-Z20)/ABS(Z20))+1,"") -> 0.83777319 | DN20: =IFERROR(((I20-AA20)/ABS(AA20))+1,"") -> 0.67698423 | DO20: =IFERROR(((J20-AB20)/ABS(AB20))+1,"") -> 0 | DP20: =IFERROR(((K20-AC20)/ABS(AC20))+1,"") -> 0 | DQ20: =IFERROR(((L20-AD20)/ABS(AD20))+1,"") -> 0 | ... DW20: =IFERROR(((R20-AJ20)/ABS(AJ20))+1,"") -> 0
C21: Wholesale | E21: =SUM(G21:R21) -> 721965 | F21: =SUMPRODUCT((G$6:R$6<=F$6)*(G21:R21)) -> 721965 | G21: 246958 | H21: 274223 | I21: 200784 | U21: Wholesale | W21: =SUM(Y21:AJ21) -> 2360745 | X21: =SUMPRODUCT((Y$6:AJ$6<=X$6)*(Y21:AJ21)) -> 734800 | Y21: 227400 | Z21: 307900 | AA21: 199500 | AB21: 175050 | AC21: 211300 | AD21: 165875 | AE21: 143585 | AF21: 131000 | AG21: 260450 | AH21: 220335 | AI21: 160550 | AJ21: 157800 | AM21: =$U21 -> Wholesale | AO21: =SUM(AQ21:BB21) -> 1920933.9 | AP21: =SUMPRODUCT((AQ$6:BB$6<=AP$6)*(AQ21:BB21)) -> 496715 | AQ21: 167310 | AR21: 207028 | AS21: 122377 | AT21: 154204 | AU21: 189697 | AV21: 129205 | AW21: 134791 | AX21: 122993.52 | AY21: 148434 | AZ21: 199070.42 | BA21: 195894 | BB21: 149930 | BE21: =$U21 -> Wholesale | BG21: =SUM(BI21:BT21) -> 2380227.1 | BH21: =SUMPRODUCT((BI$6:BT$6<=BH$6)*(BI21:BT21)) -> 708592 | BI21: 255469 | BJ21: 256468 | BK21: 196655 | BL21: 144090 | BM21: 236445 | BN21: 199888 | BO21: 191936 | BP21: 128801 | BQ21: 220102 | BR21: 187699 | BS21: 177447.14 | BT21: 185227 | BW21: =$U21 -> Wholesale | BY21: =SUM(BZ21:CC21) -> 721965 | BZ21: =SUM(G21:I21) -> 721965 | CA21: =SUM(J21:L21) -> 0 | CB21: =SUM(M21:O21) -> 0 | CC21: =SUM(P21:R21) -> 0 | CD21: =SUM(CE21:CH21) -> 2360745 | CE21: =SUM(Y21:AA21) -> 734800 | CF21: =SUM(AB21:AD21) -> 552225 | CG21: =SUM(AE21:AG21) -> 535035 | CH21: =SUM(AH21:AJ21) -> 538685 | CI21: =SUM(CJ21:CM21) -> 1920933.9 | CJ21: =SUM(AQ21:AS21) -> 496715 | CK21: =SUM(AT21:AV21) -> 473106 | CL21: =SUM(AW21:AY21) -> 406218.52 | CM21: =SUM(AZ21:BB21) -> 544894.42 | CP21: =$U21 -> Wholesale | CR21: =E21-W21 -> -1638780 | CS21: =F21-X21 -> -12835 | CT21: =G21-Y21 -> 19558 | CU21: =H21-Z21 -> -33677 | CV21: =I21-AA21 -> 1284 | CW21: =J21-AB21 -> -175050 | CX21: =K21-AC21 -> -211300 | CY21: =L21-AD21 -> -165875 | ... DE21: =R21-AJ21 -> -157800 | DH21: =$U21 -> Wholesale | DJ21: =IFERROR(((E21-W21)/ABS(W21))+1,"") -> 0.30582083 | DK21: =IFERROR(((F21-X21)/ABS(X21))+1,"") -> 0.98253266 | DL21: =IFERROR(((G21-Y21)/ABS(Y21))+1,"") -> 1.086007 | DM21: =IFERROR(((H21-Z21)/ABS(Z21))+1,"") -> 0.89062358 | DN21: =IFERROR(((I21-AA21)/ABS(AA21))+1,"") -> 1.0064361 | DO21: =IFERROR(((J21-AB21)/ABS(AB21))+1,"") -> 0 | DP21: =IFERROR(((K21-AC21)/ABS(AC21))+1,"") -> 0 | DQ21: =IFERROR(((L21-AD21)/ABS(AD21))+1,"") -> 0 | ... DW21: =IFERROR(((R21-AJ21)/ABS(AJ21))+1,"") -> 0
C22: Other | E22: =SUM(G22:R22) -> 118904.01 | F22: =SUMPRODUCT((G$6:R$6<=F$6)*(G22:R22)) -> 118904.01 | G22: 58192 | H22: 23275 | I22: 37437.01 | U22: Other | W22: =SUM(Y22:AJ22) -> 151000 | X22: =SUMPRODUCT((Y$6:AJ$6<=X$6)*(Y22:AJ22)) -> 38000 | Y22: 13000 | Z22: 12000 | AA22: 13000 | AB22: 12000 | AC22: 13000 | AD22: 12000 | AE22: 13000 | AF22: 12000 | AG22: 13000 | AH22: 13000 | AI22: 12000 | AJ22: 13000 | AM22: =$U22 -> Other | AO22: =SUM(AQ22:BB22) -> 133656.1 | AP22: =SUMPRODUCT((AQ$6:BB$6<=AP$6)*(AQ22:BB22)) -> 43987.88 | AQ22: 17223.71 | AR22: 13917.63 | AS22: 12846.54 | AT22: 16127.39 | AU22: 15613.59 | AV22: 10179.46 | AW22: 10235.64 | AX22: 7059.78 | AY22: 6420 | AZ22: 6160.05 | BA22: 7798.52 | BB22: 10073.79 | BE22: =$U22 -> Other | BG22: =SUM(BI22:BT22) -> 144241.81 | BH22: =SUMPRODUCT((BI$6:BT$6<=BH$6)*(BI22:BT22)) -> 38764 | BI22: 12496 | BJ22: 9917 | BK22: 16351 | BL22: 10262 | BM22: 10089 | BN22: 11448 | BO22: 12406 | BP22: 8968 | BQ22: 11625 | BR22: 11563 | BS22: 14845.8 | BT22: 14271.01 | BW22: =$U22 -> Other | BY22: =SUM(BZ22:CC22) -> 118904.01 | BZ22: =SUM(G22:I22) -> 118904.01 | CA22: =SUM(J22:L22) -> 0 | CB22: =SUM(M22:O22) -> 0 | CC22: =SUM(P22:R22) -> 0 | CD22: =SUM(CE22:CH22) -> 151000 | CE22: =SUM(Y22:AA22) -> 38000 | CF22: =SUM(AB22:AD22) -> 37000 | CG22: =SUM(AE22:AG22) -> 38000 | CH22: =SUM(AH22:AJ22) -> 38000 | CI22: =SUM(CJ22:CM22) -> 133656.1 | CJ22: =SUM(AQ22:AS22) -> 43987.88 | CK22: =SUM(AT22:AV22) -> 41920.44 | CL22: =SUM(AW22:AY22) -> 23715.42 | CM22: =SUM(AZ22:BB22) -> 24032.36 | CP22: =$U22 -> Other | CR22: =E22-W22 -> -32095.99 | CS22: =F22-X22 -> 80904.01 | CT22: =G22-Y22 -> 45192 | CU22: =H22-Z22 -> 11275 | CV22: =I22-AA22 -> 24437.01 | CW22: =J22-AB22 -> -12000 | CX22: =K22-AC22 -> -13000 | CY22: =L22-AD22 -> -12000 | ... DE22: =R22-AJ22 -> -13000 | DH22: =$U22 -> Other | DJ22: =IFERROR(((E22-W22)/ABS(W22))+1,"") -> 0.78744377 | DK22: =IFERROR(((F22-X22)/ABS(X22))+1,"") -> 3.1290529 | DL22: =IFERROR(((G22-Y22)/ABS(Y22))+1,"") -> 4.4763077 | DM22: =IFERROR(((H22-Z22)/ABS(Z22))+1,"") -> 1.9395833 | DN22: =IFERROR(((I22-AA22)/ABS(AA22))+1,"") -> 2.87977 | DO22: =IFERROR(((J22-AB22)/ABS(AB22))+1,"") -> 0 | DP22: =IFERROR(((K22-AC22)/ABS(AC22))+1,"") -> 0 | DQ22: =IFERROR(((L22-AD22)/ABS(AD22))+1,"") -> 0 | ... DW22: =IFERROR(((R22-AJ22)/ABS(AJ22))+1,"") -> 0
B23: ADR | E23: =IFERROR(E17/E12,0) -> 147.09369 | F23: =IFERROR(F17/F12,0) -> 147.09369 | G23: =IFERROR(G17/G12,0) -> 150.37861 | H23: =IFERROR(H17/H12,0) -> 146.29547 | I23: =IFERROR(I17/I12,0) -> 144.32892 | J23: =IFERROR(J17/J12,0) -> 0 | K23: =IFERROR(K17/K12,0) -> 0 | L23: =IFERROR(L17/L12,0) -> 0 | ... R23: =IFERROR(R17/R12,0) -> 0 | T23: ADR | W23: =IFERROR(W17/W12,0) -> 168.76007 | X23: =IFERROR(X17/X12,0) -> 160.72203 | Y23: =IFERROR(Y17/Y12,0) -> 150.46452 | Z23: =IFERROR(Z17/Z12,0) -> 165.84 | AA23: =IFERROR(AA17/AA12,0) -> 166.2771 | AB23: =IFERROR(AB17/AB12,0) -> 154.30382 | AC23: =IFERROR(AC17/AC12,0) -> 164.78369 | AD23: =IFERROR(AD17/AD12,0) -> 171.26799 | ... AJ23: =IFERROR(AJ17/AJ12,0) -> 187.73838 | AL23: =$T23 -> ADR | AO23: =IFERROR(AO17/AO12,0) -> 157.13402 | AP23: =IFERROR(AP17/AP12,0) -> 161.96208 | AQ23: =IFERROR(AQ17/AQ12,0) -> 159.57733 | AR23: =IFERROR(AR17/AR12,0) -> 165.18753 | AS23: =IFERROR(AS17/AS12,0) -> 161.42661 | AT23: =IFERROR(AT17/AT12,0) -> 156.82902 | AU23: =IFERROR(AU17/AU12,0) -> 153.43926 | AV23: =IFERROR(AV17/AV12,0) -> 161.77295 | ... BB23: =IFERROR(BB17/BB12,0) -> 163.3739 | BD23: =$T23 -> ADR | BG23: =IFERROR(BG17/BG12,0) -> 164.71118 | BH23: =IFERROR(BH17/BH12,0) -> 165.45275 | BI23: =IFERROR(BI17/BI12,0) -> 166.98885 | BJ23: =IFERROR(BJ17/BJ12,0) -> 168.73013 | BK23: =IFERROR(BK17/BK12,0) -> 160.59005 | BL23: =IFERROR(BL17/BL12,0) -> 150.47916 | BM23: =IFERROR(BM17/BM12,0) -> 156.04016 | BN23: =IFERROR(BN17/BN12,0) -> 169.46399 | ... BT23: =IFERROR(BT17/BT12,0) -> 170.62753 | BV23: =$T23 -> ADR | BY23: =IFERROR(BY17/BY12,0) -> 147.09369 | BZ23: =IFERROR(BZ17/BZ12,0) -> 147.09369 | CA23: =IFERROR(CA17/CA12,0) -> 0 | CB23: =IFERROR(CB17/CB12,0) -> 0 | CC23: =IFERROR(CC17/CC12,0) -> 0 | CD23: =IFERROR(CD17/CD12,0) -> 168.76007 | CE23: =IFERROR(CE17/CE12,0) -> 160.72203 | CF23: =IFERROR(CF17/CF12,0) -> 163.53404 | ... CM23: =IFERROR(CM17/CM12,0) -> 148.28176 | CO23: =$T23 -> ADR | CR23: =E23-W23 -> -21.66638 | CS23: =F23-X23 -> -13.628339 | CT23: =G23-Y23 -> -0.085908624 | CU23: =H23-Z23 -> -19.544531 | CV23: =I23-AA23 -> -21.948184 | CW23: =J23-AB23 -> -154.30382 | CX23: =K23-AC23 -> -164.78369 | CY23: =L23-AD23 -> -171.26799 | ... DE23: =R23-AJ23 -> -187.73838 | DG23: =$T23 -> ADR | DJ23: =IFERROR(((E23-W23)/ABS(W23))+1,0) -> 0.8716143 | DK23: =IFERROR(((F23-X23)/ABS(X23))+1,0) -> 0.91520553 | DL23: =IFERROR(((G23-Y23)/ABS(Y23))+1,0) -> 0.99942904 | DM23: =IFERROR(((H23-Z23)/ABS(Z23))+1,0) -> 0.88214827 | DN23: =IFERROR(((I23-AA23)/ABS(AA23))+1,0) -> 0.86800237 | DO23: =IFERROR(((J23-AB23)/ABS(AB23))+1,0) -> 0 | DP23: =IFERROR(((K23-AC23)/ABS(AC23))+1,0) -> 0 | DQ23: =IFERROR(((L23-AD23)/ABS(AD23))+1,0) -> 0 | ... DW23: =IFERROR(((R23-AJ23)/ABS(AJ23))+1,0) -> 0
C24: Crew | E24: =IFERROR(E18/E13,0) -> 0 | F24: =IFERROR(F18/F13,0) -> 0 | G24: =IFERROR(G18/G13,0) -> 0 | H24: =IFERROR(H18/H13,0) -> 0 | I24: =IFERROR(I18/I13,0) -> 0 | J24: =IFERROR(J18/J13,0) -> 0 | K24: =IFERROR(K18/K13,0) -> 0 | L24: =IFERROR(L18/L13,0) -> 0 | ... R24: =IFERROR(R18/R13,0) -> 0 | U24: Crew | W24: =IFERROR(W18/W13,0) -> 0 | X24: =IFERROR(X18/X13,0) -> 0 | Y24: =IFERROR(Y18/Y13,0) -> 0 | Z24: =IFERROR(Z18/Z13,0) -> 0 | AA24: =IFERROR(AA18/AA13,0) -> 0 | AB24: =IFERROR(AB18/AB13,0) -> 0 | AC24: =IFERROR(AC18/AC13,0) -> 0 | AD24: =IFERROR(AD18/AD13,0) -> 0 | ... AJ24: =IFERROR(AJ18/AJ13,0) -> 0 | AM24: =$U24 -> Crew | AO24: =IFERROR(AO18/AO13,0) -> 156.16129 | AP24: =IFERROR(AP18/AP13,0) -> 156.16762 | AQ24: =IFERROR(AQ18/AQ13,0) -> 156 | AR24: =IFERROR(AR18/AR13,0) -> 156 | AS24: =IFERROR(AS18/AS13,0) -> 156.48649 | AT24: =IFERROR(AT18/AT13,0) -> 156 | AU24: =IFERROR(AU18/AU13,0) -> 155.83648 | AV24: =IFERROR(AV18/AV13,0) -> 156 | ... BB24: =IFERROR(BB18/BB13,0) -> 0 | BE24: =$U24 -> Crew | BG24: =IFERROR(BG18/BG13,0) -> 155.98839 | BH24: =IFERROR(BH18/BH13,0) -> 156.20105 | BI24: =IFERROR(BI18/BI13,0) -> 156 | BJ24: =IFERROR(BJ18/BJ13,0) -> 156.62342 | BK24: =IFERROR(BK18/BK13,0) -> 156 | BL24: =IFERROR(BL18/BL13,0) -> 155.67089 | BM24: =IFERROR(BM18/BM13,0) -> 156 | BN24: =IFERROR(BN18/BN13,0) -> 156 | ... BT24: =IFERROR(BT18/BT13,0) -> 156 | BW24: =$U24 -> Crew | BY24: =IFERROR(BY18/BY13,0) -> 0 | BZ24: =IFERROR(BZ18/BZ13,0) -> 0 | CA24: =IFERROR(CA18/CA13,0) -> 0 | CB24: =IFERROR(CB18/CB13,0) -> 0 | CC24: =IFERROR(CC18/CC13,0) -> 0 | CD24: =IFERROR(CD18/CD13,0) -> 0 | CE24: =IFERROR(CE18/CE13,0) -> 0 | CF24: =IFERROR(CF18/CF13,0) -> 0 | ... CM24: =IFERROR(CM18/CM13,0) -> 0 | CP24: =$U24 -> Crew | CR24: =E24-W24 -> 0 | CS24: =F24-X24 -> 0 | CT24: =G24-Y24 -> 0 | CU24: =H24-Z24 -> 0 | CV24: =I24-AA24 -> 0 | CW24: =J24-AB24 -> 0 | CX24: =K24-AC24 -> 0 | CY24: =L24-AD24 -> 0 | ... DE24: =R24-AJ24 -> 0 | DH24: =$U24 -> Crew | DJ24: =IFERROR(((E24-W24)/ABS(W24))+1,0) -> 0 | DK24: =IFERROR(((F24-X24)/ABS(X24))+1,0) -> 0 | DL24: =IFERROR(((G24-Y24)/ABS(Y24))+1,0) -> 0 | DM24: =IFERROR(((H24-Z24)/ABS(Z24))+1,0) -> 0 | DN24: =IFERROR(((I24-AA24)/ABS(AA24))+1,0) -> 0 | DO24: =IFERROR(((J24-AB24)/ABS(AB24))+1,0) -> 0 | DP24: =IFERROR(((K24-AC24)/ABS(AC24))+1,0) -> 0 | DQ24: =IFERROR(((L24-AD24)/ABS(AD24))+1,0) -> 0 | ... DW24: =IFERROR(((R24-AJ24)/ABS(AJ24))+1,0) -> 0
C25: Group | E25: =IFERROR(E19/E14,0) -> 165.28753 | F25: =IFERROR(F19/F14,0) -> 165.28753 | G25: =IFERROR(G19/G14,0) -> 176.71041 | H25: =IFERROR(H19/H14,0) -> 179.6129 | I25: =IFERROR(I19/I14,0) -> 155.68336 | J25: =IFERROR(J19/J14,0) -> 0 | K25: =IFERROR(K19/K14,0) -> 0 | L25: =IFERROR(L19/L14,0) -> 0 | ... R25: =IFERROR(R19/R14,0) -> 0 | U25: Group | W25: =IFERROR(W19/W14,0) -> 153.43588 | X25: =IFERROR(X19/X14,0) -> 163.65724 | Y25: =IFERROR(Y19/Y14,0) -> 172.13115 | Z25: =IFERROR(Z19/Z14,0) -> 166.75439 | AA25: =IFERROR(AA19/AA14,0) -> 155.60185 | AB25: =IFERROR(AB19/AB14,0) -> 144.83333 | AC25: =IFERROR(AC19/AC14,0) -> 147.43902 | AD25: =IFERROR(AD19/AD14,0) -> 162.66667 | ... AJ25: =IFERROR(AJ19/AJ14,0) -> 142.31405 | AM25: =$U25 -> Group | AO25: =IFERROR(AO19/AO14,0) -> 159.7092 | AP25: =IFERROR(AP19/AP14,0) -> 175.39013 | AQ25: =IFERROR(AQ19/AQ14,0) -> 194.952 | AR25: =IFERROR(AR19/AR14,0) -> 168.80405 | AS25: =IFERROR(AS19/AS14,0) -> 172.84602 | AT25: =IFERROR(AT19/AT14,0) -> 145.09847 | AU25: =IFERROR(AU19/AU14,0) -> 149.6556 | AV25: =IFERROR(AV19/AV14,0) -> 162.50791 | ... BB25: =IFERROR(BB19/BB14,0) -> 150.47603 | BE25: =$U25 -> Group | BG25: =IFERROR(BG19/BG14,0) -> 170.28755 | BH25: =IFERROR(BH19/BH14,0) -> 178.13491 | BI25: =IFERROR(BI19/BI14,0) -> 184.07527 | BJ25: =IFERROR(BJ19/BJ14,0) -> 182.41111 | BK25: =IFERROR(BK19/BK14,0) -> 171.20399 | BL25: =IFERROR(BL19/BL14,0) -> 147.12308 | BM25: =IFERROR(BM19/BM14,0) -> 144.18699 | BN25: =IFERROR(BN19/BN14,0) -> 168.54527 | ... BT25: =IFERROR(BT19/BT14,0) -> 162.42532 | BW25: =$U25 -> Group | BY25: =IFERROR(BY19/BY14,0) -> 165.28753 | BZ25: =IFERROR(BZ19/BZ14,0) -> 165.28753 | CA25: =IFERROR(CA19/CA14,0) -> 0 | CB25: =IFERROR(CB19/CB14,0) -> 0 | CC25: =IFERROR(CC19/CC14,0) -> 0 | CD25: =IFERROR(CD19/CD14,0) -> 153.43588 | CE25: =IFERROR(CE19/CE14,0) -> 163.65724 | CF25: =IFERROR(CF19/CF14,0) -> 152.62025 | ... CM25: =IFERROR(CM19/CM14,0) -> 155.78525 | CP25: =$U25 -> Group | CR25: =E25-W25 -> 11.851654 | CS25: =F25-X25 -> 1.630288 | CT25: =G25-Y25 -> 4.5792597 | CU25: =H25-Z25 -> 12.858517 | CV25: =I25-AA25 -> 0.081506027 | CW25: =J25-AB25 -> -144.83333 | CX25: =K25-AC25 -> -147.43902 | CY25: =L25-AD25 -> -162.66667 | ... DE25: =R25-AJ25 -> -142.31405 | DH25: =$U25 -> Group | DJ25: =IFERROR(((E25-W25)/ABS(W25))+1,0) -> 1.0772417 | DK25: =IFERROR(((F25-X25)/ABS(X25))+1,0) -> 1.0099616 | DL25: =IFERROR(((G25-Y25)/ABS(Y25))+1,0) -> 1.0266033 | DM25: =IFERROR(((H25-Z25)/ABS(Z25))+1,0) -> 1.0771105 | DN25: =IFERROR(((I25-AA25)/ABS(AA25))+1,0) -> 1.0005238 | DO25: =IFERROR(((J25-AB25)/ABS(AB25))+1,0) -> 0 | DP25: =IFERROR(((K25-AC25)/ABS(AC25))+1,0) -> 0 | DQ25: =IFERROR(((L25-AD25)/ABS(AD25))+1,0) -> 0 | ... DW25: =IFERROR(((R25-AJ25)/ABS(AJ25))+1,0) -> 0
C26: Transient | E26: =IFERROR(E20/E15,0) -> 132.67437 | F26: =IFERROR(F20/F15,0) -> 132.67437 | G26: =IFERROR(G20/G15,0) -> 133.89052 | H26: =IFERROR(H20/H15,0) -> 132.39336 | I26: =IFERROR(I20/I15,0) -> 131.52433 | J26: =IFERROR(J20/J15,0) -> 0 | K26: =IFERROR(K20/K15,0) -> 0 | L26: =IFERROR(L20/L15,0) -> 0 | ... R26: =IFERROR(R20/R15,0) -> 0 | U26: Transient | W26: =IFERROR(W20/W15,0) -> 170.53345 | X26: =IFERROR(X20/X15,0) -> 155.88235 | Y26: =IFERROR(Y20/Y15,0) -> 141.87887 | Z26: =IFERROR(Z20/Z15,0) -> 161.15556 | AA26: =IFERROR(AA20/AA15,0) -> 166.17857 | AB26: =IFERROR(AB20/AB15,0) -> 154.60184 | AC26: =IFERROR(AC20/AC15,0) -> 167.08731 | AD26: =IFERROR(AD20/AD15,0) -> 172.37288 | ... AJ26: =IFERROR(AJ20/AJ15,0) -> 194.51074 | AM26: =$U26 -> Transient | AO26: =IFERROR(AO20/AO15,0) -> 154.1954 | AP26: =IFERROR(AP20/AP15,0) -> 156.11854 | AQ26: =IFERROR(AQ20/AQ15,0) -> 151.30979 | AR26: =IFERROR(AR20/AR15,0) -> 159.77465 | AS26: =IFERROR(AS20/AS15,0) -> 158.02491 | AT26: =IFERROR(AT20/AT15,0) -> 156.84898 | AU26: =IFERROR(AU20/AU15,0) -> 150.34186 | AV26: =IFERROR(AV20/AV15,0) -> 160.79301 | ... BB26: =IFERROR(BB20/BB15,0) -> 164.74389 | BE26: =$U26 -> Transient | BG26: =IFERROR(BG20/BG15,0) -> 164.05755 | BH26: =IFERROR(BH20/BH15,0) -> 158.82058 | BI26: =IFERROR(BI20/BI15,0) -> 160.18441 | BJ26: =IFERROR(BJ20/BJ15,0) -> 162.75551 | BK26: =IFERROR(BK20/BK15,0) -> 153.58892 | BL26: =IFERROR(BL20/BL15,0) -> 148.4288 | BM26: =IFERROR(BM20/BM15,0) -> 158.95355 | BN26: =IFERROR(BN20/BN15,0) -> 173.20832 | ... BT26: =IFERROR(BT20/BT15,0) -> 171.94399 | BW26: =$U26 -> Transient | BY26: =IFERROR(BY20/BY15,0) -> 132.67437 | BZ26: =IFERROR(BZ20/BZ15,0) -> 132.67437 | CA26: =IFERROR(CA20/CA15,0) -> 0 | CB26: =IFERROR(CB20/CB15,0) -> 0 | CC26: =IFERROR(CC20/CC15,0) -> 0 | CD26: =IFERROR(CD20/CD15,0) -> 170.53345 | CE26: =IFERROR(CE20/CE15,0) -> 155.88235 | CF26: =IFERROR(CF20/CF15,0) -> 164.82365 | ... CM26: =IFERROR(CM20/CM15,0) -> 145.68974 | CP26: =$U26 -> Transient | CR26: =E26-W26 -> -37.85908 | CS26: =F26-X26 -> -23.207983 | CT26: =G26-Y26 -> -7.9883525 | CU26: =H26-Z26 -> -28.762198 | CV26: =I26-AA26 -> -34.654246 | CW26: =J26-AB26 -> -154.60184 | CX26: =K26-AC26 -> -167.08731 | CY26: =L26-AD26 -> -172.37288 | ... DE26: =R26-AJ26 -> -194.51074 | DH26: =$U26 -> Transient | DJ26: =IFERROR(((E26-W26)/ABS(W26))+1,0) -> 0.77799616 | DK26: =IFERROR(((F26-X26)/ABS(X26))+1,0) -> 0.8511186 | DL26: =IFERROR(((G26-Y26)/ABS(Y26))+1,0) -> 0.94369597 | DM26: =IFERROR(((H26-Z26)/ABS(Z26))+1,0) -> 0.82152525 | DN26: =IFERROR(((I26-AA26)/ABS(AA26))+1,0) -> 0.79146381 | DO26: =IFERROR(((J26-AB26)/ABS(AB26))+1,0) -> 0 | DP26: =IFERROR(((K26-AC26)/ABS(AC26))+1,0) -> 0 | DQ26: =IFERROR(((L26-AD26)/ABS(AD26))+1,0) -> 0 | ... DW26: =IFERROR(((R26-AJ26)/ABS(AJ26))+1,0) -> 0
C27: Wholesale | E27: =IFERROR(E21/E16,0) -> 164.26962 | F27: =IFERROR(F21/F16,0) -> 164.26962 | G27: =IFERROR(G21/G16,0) -> 169.73058 | H27: =IFERROR(H21/H16,0) -> 165.09512 | I27: =IFERROR(I21/I16,0) -> 156.98514 | J27: =IFERROR(J21/J16,0) -> 0 | K27: =IFERROR(K21/K16,0) -> 0 | L27: =IFERROR(L21/L16,0) -> 0 | ... R27: =IFERROR(R21/R16,0) -> 0 | U27: Wholesale | W27: =IFERROR(W21/W16,0) -> 157.383 | X27: =IFERROR(X21/X16,0) -> 168.7256 | Y27: =IFERROR(Y21/Y16,0) -> 173.58779 | Z27: =IFERROR(Z21/Z16,0) -> 170.58172 | AA27: =IFERROR(AA21/AA16,0) -> 160.8871 | AB27: =IFERROR(AB21/AB16,0) -> 147.10084 | AC27: =IFERROR(AC21/AC16,0) -> 150.92857 | AD27: =IFERROR(AD21/AD16,0) -> 158.73206 | ... AJ27: =IFERROR(AJ21/AJ16,0) -> 161.84615 | AM27: =$U27 -> Wholesale | AO27: =IFERROR(AO21/AO16,0) -> 160.70727 | AP27: =IFERROR(AP21/AP16,0) -> 180.8209 | AQ27: =IFERROR(AQ21/AQ16,0) -> 192.31034 | AR27: =IFERROR(AR21/AR16,0) -> 181.92267 | AS27: =IFERROR(AS21/AS16,0) -> 165.59811 | AT27: =IFERROR(AT21/AT16,0) -> 150.00389 | AU27: =IFERROR(AU21/AU16,0) -> 152.85818 | AV27: =IFERROR(AV21/AV16,0) -> 161.50625 | ... BB27: =IFERROR(BB21/BB16,0) -> 152.83384 | BE27: =$U27 -> Wholesale | BG27: =IFERROR(BG21/BG16,0) -> 161.38227 | BH27: =IFERROR(BH21/BH16,0) -> 180.07421 | BI27: =IFERROR(BI21/BI16,0) -> 184.45415 | BJ27: =IFERROR(BJ21/BJ16,0) -> 181.37765 | BK27: =IFERROR(BK21/BK16,0) -> 173.1118 | BL27: =IFERROR(BL21/BL16,0) -> 146.73116 | BM27: =IFERROR(BM21/BM16,0) -> 143.56102 | BN27: =IFERROR(BN21/BN16,0) -> 157.39213 | ... BT27: =IFERROR(BT21/BT16,0) -> 166.57104 | BW27: =$U27 -> Wholesale | BY27: =IFERROR(BY21/BY16,0) -> 164.26962 | BZ27: =IFERROR(BZ21/BZ16,0) -> 164.26962 | CA27: =IFERROR(CA21/CA16,0) -> 0 | CB27: =IFERROR(CB21/CB16,0) -> 0 | CC27: =IFERROR(CC21/CC16,0) -> 0 | CD27: =IFERROR(CD21/CD16,0) -> 157.383 | CE27: =IFERROR(CE21/CE16,0) -> 168.7256 | CF27: =IFERROR(CF21/CF16,0) -> 151.91884 | ... CM27: =IFERROR(CM21/CM16,0) -> 147.54791 | CP27: =$U27 -> Wholesale | CR27: =E27-W27 -> 6.8866246 | CS27: =F27-X27 -> -4.4559782 | CT27: =G27-Y27 -> -3.8572021 | CU27: =H27-Z27 -> -5.486594 | CV27: =I27-AA27 -> -3.9019521 | CW27: =J27-AB27 -> -147.10084 | CX27: =K27-AC27 -> -150.92857 | CY27: =L27-AD27 -> -158.73206 | ... DE27: =R27-AJ27 -> -161.84615 | DH27: =$U27 -> Wholesale | DJ27: =IFERROR(((E27-W27)/ABS(W27))+1,0) -> 1.0437571 | DK27: =IFERROR(((F27-X27)/ABS(X27))+1,0) -> 0.97359039 | DL27: =IFERROR(((G27-Y27)/ABS(Y27))+1,0) -> 0.97777953 | DM27: =IFERROR(((H27-Z27)/ABS(Z27))+1,0) -> 0.96783598 | DN27: =IFERROR(((I27-AA27)/ABS(AA27))+1,0) -> 0.97574726 | DO27: =IFERROR(((J27-AB27)/ABS(AB27))+1,0) -> 0 | DP27: =IFERROR(((K27-AC27)/ABS(AC27))+1,0) -> 0 | DQ27: =IFERROR(((L27-AD27)/ABS(AD27))+1,0) -> 0 | ... DW27: =IFERROR(((R27-AJ27)/ABS(AJ27))+1,0) -> 0

Sheet 2) IS(Summary)
A1: ='1) Rooms'!$A$1 -> ＃ WHR Monthly Closing | R1: ='1) Rooms'!$R$1 -> Business Performance in 2026 | S1: =$A$1 -> ＃ WHR Monthly Closing | AJ1: =$R$1 -> Business Performance in 2026 | AK1: =$A$1 -> ＃ WHR Monthly Closing | BB1: =$R$1 -> Business Performance in 2026 | BC1: =$A$1 -> ＃ WHR Monthly Closing | BT1: =$R$1 -> Business Performance in 2026 | BU1: =$A$1 -> ＃ WHR Monthly Closing | CM1: =$R$1 -> Business Performance in 2026 | CN1: =$A$1 -> ＃ WHR Monthly Closing | DE1: =$R$1 -> Business Performance in 2026 | DF1: =$A$1 -> ＃ WHR Monthly Closing | DW1: =$R$1 -> Business Performance in 2026
A3: 1. 2026년 실적 | S3: 2. 2026년 목표 | AK3: 3. 2025년 실적 | BC3: 4. 2024년 실적 | BU3: 5. 분기별 | CN3: 6. 목표 대비 증감 | DF3: 7. 목표 대비 달성률
A4: 1) 손익계산서 | R4: * Unit : USD | S4: =$A$4 -> 1) 손익계산서 | AJ4: =$R$4 -> * Unit : USD | AK4: =$A$4 -> 1) 손익계산서 | BB4: =$R$4 -> * Unit : USD | BC4: =$A$4 -> 1) 손익계산서 | BT4: =$R$4 -> * Unit : USD | BU4: =$A$4 -> 1) 손익계산서 | CM4: =$R$4 -> * Unit : USD | CN4: =$A$4 -> 1) 손익계산서 | DE4: =$R$4 -> * Unit : USD | DF4: =$A$4 -> 1) 손익계산서
E5: Total | F5: Actual 2026 | W5: Total | X5: Budget 2026 | AO5: Total | AP5: Actual 2025 | BG5: Total | BH5: Actual 2024 | BY5: Actual 2026 | CD5: Budget 2026 | CI5: Actual 2025 | CR5: Total | CS5: Actual VS. Budget 2026 | DJ5: Total | DK5: Actual VS. Budget 2026(%)
F6: ='1) Rooms'!$AP$6 -> 3 | G6: ='1) Rooms'!G$6 -> 1 | H6: ='1) Rooms'!H$6 -> 2 | I6: ='1) Rooms'!I$6 -> 3 | J6: ='1) Rooms'!J$6 -> 4 | K6: ='1) Rooms'!K$6 -> 5 | L6: ='1) Rooms'!L$6 -> 6 | M6: ='1) Rooms'!M$6 -> 7 | N6: ='1) Rooms'!N$6 -> 8 | ... R6: ='1) Rooms'!R$6 -> 12 | X6: =$F$6 -> 3 | Y6: =$G$6 -> 1 | Z6: =$H$6 -> 2 | AA6: =$I$6 -> 3 | AB6: =$J$6 -> 4 | AC6: =$K$6 -> 5 | AD6: =$L$6 -> 6 | AE6: =$M$6 -> 7 | AF6: =$N$6 -> 8 | AG6: =$O$6 -> 9 | AH6: =$P$6 -> 10 | AI6: =$Q$6 -> 11 | AJ6: =$R$6 -> 12 | AP6: =$F$6 -> 3 | AQ6: =$G$6 -> 1 | AR6: =$H$6 -> 2 | AS6: =$I$6 -> 3 | AT6: =$J$6 -> 4 | AU6: =$K$6 -> 5 | AV6: =$L$6 -> 6 | AW6: =$M$6 -> 7 | AX6: =$N$6 -> 8 | AY6: =$O$6 -> 9 | AZ6: =$P$6 -> 10 | BA6: =$Q$6 -> 11 | BB6: =$R$6 -> 12 | BH6: =$F$6 -> 3 | BI6: =$G$6 -> 1 | BJ6: =$H$6 -> 2 | BK6: =$I$6 -> 3 | BL6: =$J$6 -> 4 | BM6: =$K$6 -> 5 | BN6: =$L$6 -> 6 | BO6: =$M$6 -> 7 | BP6: =$N$6 -> 8 | BQ6: =$O$6 -> 9 | BR6: =$P$6 -> 10 | BS6: =$Q$6 -> 11 | BT6: =$R$6 -> 12 | BY6: Total | BZ6: 1 | CA6: 2 | CB6: =BK$6 -> 3 | CC6: =BL$6 -> 4 | CD6: Total | CE6: 1 | CF6: 2 | CG6: 3 | CH6: 4 | CI6: Total | CJ6: 1 | CK6: 2 | CL6: 3 | CM6: 4 | CS6: =$F$6 -> 3 | CT6: =$G$6 -> 1 | CU6: =$H$6 -> 2 | CV6: =$I$6 -> 3 | CW6: =$J$6 -> 4 | CX6: =$K$6 -> 5 | CY6: =$L$6 -> 6 | CZ6: =$M$6 -> 7 | DA6: =$N$6 -> 8 | DB6: =$O$6 -> 9 | DC6: =$P$6 -> 10 | DD6: =$Q$6 -> 11 | DE6: =$R$6 -> 12 | DK6: =$F$6 -> 3 | DL6: =$G$6 -> 1 | DM6: =$H$6 -> 2 | DN6: =$I$6 -> 3 | DO6: =$J$6 -> 4 | DP6: =$K$6 -> 5 | DQ6: =$L$6 -> 6 | DR6: =$M$6 -> 7 | DS6: =$N$6 -> 8 | DT6: =$O$6 -> 9 | DU6: =$P$6 -> 10 | DV6: =$Q$6 -> 11 | DW6: =$R$6 -> 12
B7: Revenues | E7: =SUM(G7:R7) -> 4310538.8 | F7: =SUMPRODUCT((G$6:R$6<=F$6)*(G7:R7)) -> 4310538.8 | G7: =SUM(G8:G13) -> 1555066 | H7: =SUM(H8:H13) -> 1368148.1 | I7: =SUM(I8:I13) -> 1387324.7 | J7: =SUM(J8:J13) -> 0 | K7: =SUM(K8:K13) -> 0 | L7: =SUM(L8:L13) -> 0 | M7: =SUM(M8:M13) -> 0 | N7: =SUM(N8:N13) -> 0 | ... R7: =SUM(R8:R13) -> 0 | T7: =$B7 -> Revenues | W7: =SUM(Y7:AJ7) -> 20764818 | X7: =SUMPRODUCT((Y$6:AJ$6<=X$6)*(Y7:AJ7)) -> 4866593 | Y7: =SUM(Y8:Y13) -> 1587873 | Z7: =SUM(Z8:Z13) -> 1577895 | AA7: =SUM(AA8:AA13) -> 1700825 | AB7: =SUM(AB8:AB13) -> 1614662 | AC7: =SUM(AC8:AC13) -> 1748556 | AD7: =SUM(AD8:AD13) -> 1818668 | AE7: =SUM(AE8:AE13) -> 1875135 | AF7: =SUM(AF8:AF13) -> 1742289 | ... AJ7: =SUM(AJ8:AJ13) -> 1837282 | AL7: =$B7 -> Revenues | AO7: =SUM(AQ7:BB7) -> 19305126 | AP7: =SUMPRODUCT((AQ$6:BB$6<=AP$6)*(AQ7:BB7)) -> 4820598.7 | AQ7: =SUM(AQ8:AQ13) -> 1690312 | AR7: =SUM(AR8:AR13) -> 1513097.7 | AS7: =SUM(AS8:AS13) -> 1617189 | AT7: =SUM(AT8:AT13) -> 1565955.7 | AU7: =SUM(AU8:AU13) -> 1681619.4 | AV7: =SUM(AV8:AV13) -> 1633697 | AW7: =SUM(AW8:AW13) -> 1797674 | AX7: =SUM(AX8:AX13) -> 1724903.3 | ... BB7: =SUM(BB8:BB13) -> 1775702.2 | BD7: =$B7 -> Revenues | BG7: =SUM(BI7:BT7) -> 18831187 | BH7: =SUMPRODUCT((BI$6:BT$6<=BH$6)*(BI7:BT7)) -> 4686483 | BI7: =SUM(BI8:BI13) -> 1612115 | BJ7: =SUM(BJ8:BJ13) -> 1548089 | BK7: =SUM(BK8:BK13) -> 1526279 | BL7: =SUM(BL8:BL13) -> 1456335 | BM7: =SUM(BM8:BM13) -> 1507953 | BN7: =SUM(BN8:BN13) -> 1623602 | BO7: =SUM(BO8:BO13) -> 1788189 | BP7: =SUM(BP8:BP13) -> 1619153 | ... BT7: =SUM(BT8:BT13) -> 1764023.7 | BV7: =$B7 -> Revenues | BY7: =SUM(BZ7:CC7) -> 4310538.8 | BZ7: =SUM(BZ8:BZ13) -> 4310538.8 | CA7: =SUM(CA8:CA13) -> 0 | CB7: =SUM(CB8:CB13) -> 0 | CC7: =SUM(CC8:CC13) -> 0 | CD7: =SUM(CE7:CH7) -> 20764818 | CE7: =SUM(CE8:CE13) -> 4866593 | CF7: =SUM(CF8:CF13) -> 5181886 | CG7: =SUM(CG8:CG13) -> 5366212 | CH7: =SUM(CH8:CH13) -> 5350127 | CI7: =SUM(CJ7:CM7) -> 19305126 | CJ7: =SUM(CJ8:CJ13) -> 4820598.7 | CK7: =SUM(CK8:CK13) -> 4881272.1 | CL7: =SUM(CL8:CL13) -> 5049222.8 | CM7: =SUM(CM8:CM13) -> 4554032.9 | CO7: =$B7 -> Revenues | CR7: =E7-W7 -> -16454279 | CS7: =F7-X7 -> -556054.21 | CT7: =G7-Y7 -> -32807 | CU7: =H7-Z7 -> -209746.88 | CV7: =I7-AA7 -> -313500.33 | CW7: =J7-AB7 -> -1614662 | CX7: =K7-AC7 -> -1748556 | CY7: =L7-AD7 -> -1818668 | ... DE7: =R7-AJ7 -> -1837282 | DG7: =$B7 -> Revenues | DJ7: =IFERROR(((E7-W7)/ABS(W7))+1,"") -> 0.20758857 | DK7: =IFERROR(((F7-X7)/ABS(X7))+1,"") -> 0.88574056 | DL7: =IFERROR(((G7-Y7)/ABS(Y7))+1,"") -> 0.97933903 | DM7: =IFERROR(((H7-Z7)/ABS(Z7))+1,"") -> 0.86707171 | DN7: =IFERROR(((I7-AA7)/ABS(AA7))+1,"") -> 0.81567749 | DO7: =IFERROR(((J7-AB7)/ABS(AB7))+1,"") -> 0 | DP7: =IFERROR(((K7-AC7)/ABS(AC7))+1,"") -> 0 | DQ7: =IFERROR(((L7-AD7)/ABS(AD7))+1,"") -> 0 | ... DW7: =IFERROR(((R7-AJ7)/ABS(AJ7))+1,"") -> 0
C8: Rooms | E8: =SUM(G8:R8) -> 3021745.7 | F8: =SUMPRODUCT((G$6:R$6<=F$6)*(G8:R8)) -> 3021745.7 | G8: ='1) Rooms'!G17 -> 1092651 | H8: ='1) Rooms'!H17 -> 955163.12 | I8: ='1) Rooms'!I17 -> 973931.53 | J8: ='1) Rooms'!J17 -> 0 | K8: ='1) Rooms'!K17 -> 0 | L8: ='1) Rooms'!L17 -> 0 | M8: ='1) Rooms'!M17 -> 0 | N8: ='1) Rooms'!N17 -> 0 | ... R8: ='1) Rooms'!R17 -> 0 | U8: Rooms | W8: =SUM(Y8:AJ8) -> 15059136 | X8: =SUMPRODUCT((Y$6:AJ$6<=X$6)*(Y8:AJ8)) -> 3484775 | Y8: ='1) Rooms'!Y17 -> 1117500 | Z8: ='1) Rooms'!Z17 -> 1140150 | AA8: ='1) Rooms'!AA17 -> 1227125 | AB8: ='1) Rooms'!AB17 -> 1139688 | AC8: ='1) Rooms'!AC17 -> 1264550 | AD8: ='1) Rooms'!AD17 -> 1297355 | AE8: ='1) Rooms'!AE17 -> 1385310 | AF8: ='1) Rooms'!AF17 -> 1278058 | ... AJ8: ='1) Rooms'!AJ17 -> 1397900 | AM8: Rooms | AO8: =SUM(AQ8:BB8) -> 13883262 | AP8: =SUMPRODUCT((AQ$6:BB$6<=AP$6)*(AQ8:BB8)) -> 3558306.8 | AQ8: ='1) Rooms'!AQ17 -> 1212787.7 | AR8: ='1) Rooms'!AR17 -> 1134012.4 | AS8: ='1) Rooms'!AS17 -> 1211506.7 | AT8: ='1) Rooms'!AT17 -> 1156927.7 | AU8: ='1) Rooms'!AU17 -> 1179641.1 | AV8: ='1) Rooms'!AV17 -> 1214914.9 | AW8: ='1) Rooms'!AW17 -> 1339566.5 | AX8: ='1) Rooms'!AX17 -> 1272731 | ... BB8: ='1) Rooms'!BB17 -> 1221383.3 | BE8: Rooms | BG8: =SUM(BI8:BT8) -> 14564421 | BH8: =SUMPRODUCT((BI$6:BT$6<=BH$6)*(BI8:BT8)) -> 3694560 | BI8: ='1) Rooms'!BI17 -> 1288486 | BJ8: ='1) Rooms'!BJ17 -> 1227343 | BK8: ='1) Rooms'!BK17 -> 1178731 | BL8: ='1) Rooms'!BL17 -> 1097294 | BM8: ='1) Rooms'!BM17 -> 1177323 | BN8: ='1) Rooms'!BN17 -> 1291824 | BO8: ='1) Rooms'!BO17 -> 1427372 | BP8: ='1) Rooms'!BP17 -> 1265827 | ... BT8: ='1) Rooms'!BT17 -> 1330894.7 | BW8: Rooms | BY8: =SUM(BZ8:CC8) -> 3021745.7 | BZ8: =SUM(G8:I8) -> 3021745.7 | CA8: =SUM(J8:L8) -> 0 | CB8: =SUM(M8:O8) -> 0 | CC8: =SUM(P8:R8) -> 0 | CD8: =SUM(CE8:CH8) -> 15059136 | CE8: =SUM(Y8:AA8) -> 3484775 | CF8: =SUM(AB8:AD8) -> 3701593 | CG8: =SUM(AE8:AG8) -> 3947668 | CH8: =SUM(AH8:AJ8) -> 3925100 | CI8: =SUM(CJ8:CM8) -> 13883262 | CJ8: =SUM(AQ8:AS8) -> 3558306.8 | CK8: =SUM(AT8:AV8) -> 3551483.6 | CL8: =SUM(AW8:AY8) -> 3670824.1 | CM8: =SUM(AZ8:BB8) -> 3102647.5 | CP8: Rooms | CR8: =E8-W8 -> -12037390 | CS8: =F8-X8 -> -463029.35 | CT8: =G8-Y8 -> -24849 | CU8: =H8-Z8 -> -184986.88 | CV8: =I8-AA8 -> -253193.47 | CW8: =J8-AB8 -> -1139688 | CX8: =K8-AC8 -> -1264550 | CY8: =L8-AD8 -> -1297355 | ... DE8: =R8-AJ8 -> -1397900 | DH8: Rooms | DJ8: =IFERROR(((E8-W8)/ABS(W8))+1,"") -> 0.20065863 | DK8: =IFERROR(((F8-X8)/ABS(X8))+1,"") -> 0.86712791 | DL8: =IFERROR(((G8-Y8)/ABS(Y8))+1,"") -> 0.97776376 | DM8: =IFERROR(((H8-Z8)/ABS(Z8))+1,"") -> 0.83775216 | DN8: =IFERROR(((I8-AA8)/ABS(AA8))+1,"") -> 0.79366937 | DO8: =IFERROR(((J8-AB8)/ABS(AB8))+1,"") -> 0 | DP8: =IFERROR(((K8-AC8)/ABS(AC8))+1,"") -> 0 | DQ8: =IFERROR(((L8-AD8)/ABS(AD8))+1,"") -> 0 | ... DW8: =IFERROR(((R8-AJ8)/ABS(AJ8))+1,"") -> 0
C9: Food and beverage | E9: =SUM(G9:R9) -> 452624.44 | F9: =SUMPRODUCT((G$6:R$6<=F$6)*(G9:R9)) -> 452624.44 | G9: ='⑴-2 IS(F&B)'!G7 -> 143277 | H9: ='⑴-2 IS(F&B)'!H7 -> 151934 | I9: ='⑴-2 IS(F&B)'!I7 -> 157413.44 | J9: ='⑴-2 IS(F&B)'!J7 -> 0 | K9: ='⑴-2 IS(F&B)'!K7 -> 0 | L9: ='⑴-2 IS(F&B)'!L7 -> 0 | M9: ='⑴-2 IS(F&B)'!M7 -> 0 | N9: ='⑴-2 IS(F&B)'!N7 -> 0 | ... R9: ='⑴-2 IS(F&B)'!R7 -> 0 | U9: Food and beverage | W9: =SUM(Y9:AJ9) -> 2236006 | X9: =SUMPRODUCT((Y$6:AJ$6<=X$6)*(Y9:AJ9)) -> 539034 | Y9: ='⑴-2 IS(F&B)'!Y7 -> 177257 | Z9: ='⑴-2 IS(F&B)'!Z7 -> 176864 | AA9: ='⑴-2 IS(F&B)'!AA7 -> 184913 | AB9: ='⑴-2 IS(F&B)'!AB7 -> 185136 | AC9: ='⑴-2 IS(F&B)'!AC7 -> 185328 | AD9: ='⑴-2 IS(F&B)'!AD7 -> 191207 | AE9: ='⑴-2 IS(F&B)'!AE7 -> 189535 | AF9: ='⑴-2 IS(F&B)'!AF7 -> 173361 | ... AJ9: ='⑴-2 IS(F&B)'!AJ7 -> 194035 | AM9: Food and beverage | AO9: =SUM(AQ9:BB9) -> 2280998.7 | AP9: =SUMPRODUCT((AQ$6:BB$6<=AP$6)*(AQ9:BB9)) -> 520035.91 | AQ9: ='⑴-2 IS(F&B)'!AQ7 -> 183550.31 | AR9: ='⑴-2 IS(F&B)'!AR7 -> 162416.29 | AS9: ='⑴-2 IS(F&B)'!AS7 -> 174069.31 | AT9: ='⑴-2 IS(F&B)'!AT7 -> 163899.72 | AU9: ='⑴-2 IS(F&B)'!AU7 -> 189888.48 | AV9: ='⑴-2 IS(F&B)'!AV7 -> 176917.5 | AW9: ='⑴-2 IS(F&B)'!AW7 -> 214127.23 | AX9: ='⑴-2 IS(F&B)'!AX7 -> 208175.6 | ... BB9: ='⑴-2 IS(F&B)'!BB7 -> 222965.11 | BE9: Food and beverage | BG9: =SUM(BI9:BT9) -> 1789864 | BH9: =SUMPRODUCT((BI$6:BT$6<=BH$6)*(BI9:BT9)) -> 447990 | BI9: 147469 | BJ9: 148387 | BK9: 152134 | BL9: 176500 | BM9: 134373 | BN9: 137135 | BO9: 138538 | BP9: 134464 | BQ9: 130672 | BR9: 207901 | BS9: 129292 | BT9: 152999 | BW9: Food and beverage | BY9: =SUM(BZ9:CC9) -> 452624.44 | BZ9: =SUM(G9:I9) -> 452624.44 | CA9: =SUM(J9:L9) -> 0 | CB9: =SUM(M9:O9) -> 0 | CC9: =SUM(P9:R9) -> 0 | CD9: =SUM(CE9:CH9) -> 2236006 | CE9: =SUM(Y9:AA9) -> 539034 | CF9: =SUM(AB9:AD9) -> 561671 | CG9: =SUM(AE9:AG9) -> 540875 | CH9: =SUM(AH9:AJ9) -> 594426 | CI9: =SUM(CJ9:CM9) -> 2280998.7 | CJ9: =SUM(AQ9:AS9) -> 520035.91 | CK9: =SUM(AT9:AV9) -> 530705.7 | CL9: =SUM(AW9:AY9) -> 645078.06 | CM9: =SUM(AZ9:BB9) -> 585179.02 | CP9: Food and beverage | CR9: =E9-W9 -> -1783381.6 | CS9: =F9-X9 -> -86409.56 | CT9: =G9-Y9 -> -33980 | CU9: =H9-Z9 -> -24930 | CV9: =I9-AA9 -> -27499.56 | CW9: =J9-AB9 -> -185136 | CX9: =K9-AC9 -> -185328 | CY9: =L9-AD9 -> -191207 | ... DE9: =R9-AJ9 -> -194035 | DH9: Food and beverage | DJ9: =IFERROR(((E9-W9)/ABS(W9))+1,"") -> 0.20242541 | DK9: =IFERROR(((F9-X9)/ABS(X9))+1,"") -> 0.83969553 | DL9: =IFERROR(((G9-Y9)/ABS(Y9))+1,"") -> 0.80830094 | DM9: =IFERROR(((H9-Z9)/ABS(Z9))+1,"") -> 0.85904424 | DN9: =IFERROR(((I9-AA9)/ABS(AA9))+1,"") -> 0.85128379 | DO9: =IFERROR(((J9-AB9)/ABS(AB9))+1,"") -> 0 | DP9: =IFERROR(((K9-AC9)/ABS(AC9))+1,"") -> 0 | DQ9: =IFERROR(((L9-AD9)/ABS(AD9))+1,"") -> 0 | ... DW9: =IFERROR(((R9-AJ9)/ABS(AJ9))+1,"") -> 0
C10: Comunications | E10: =SUM(G10:R10) -> 0 | F10: =SUMPRODUCT((G$6:R$6<=F$6)*(G10:R10)) -> 0 | G10: ='⑴-3 IS(Tele)'!G7 -> 0 | H10: ='⑴-3 IS(Tele)'!H7 -> 0 | I10: ='⑴-3 IS(Tele)'!I7 -> 0 | J10: ='⑴-3 IS(Tele)'!J7 -> 0 | K10: ='⑴-3 IS(Tele)'!K7 -> 0 | L10: ='⑴-3 IS(Tele)'!L7 -> 0 | M10: ='⑴-3 IS(Tele)'!M7 -> 0 | N10: ='⑴-3 IS(Tele)'!N7 -> 0 | ... R10: ='⑴-3 IS(Tele)'!R7 -> 0 | U10: Comunications | W10: =SUM(Y10:AJ10) -> 0 | X10: =SUMPRODUCT((Y$6:AJ$6<=X$6)*(Y10:AJ10)) -> 0 | Y10: ='⑴-3 IS(Tele)'!Y7 -> 0 | Z10: ='⑴-3 IS(Tele)'!Z7 -> 0 | AA10: ='⑴-3 IS(Tele)'!AA7 -> 0 | AB10: ='⑴-3 IS(Tele)'!AB7 -> 0 | AC10: ='⑴-3 IS(Tele)'!AC7 -> 0 | AD10: ='⑴-3 IS(Tele)'!AD7 -> 0 | AE10: ='⑴-3 IS(Tele)'!AE7 -> 0 | AF10: ='⑴-3 IS(Tele)'!AF7 -> 0 | ... AJ10: ='⑴-3 IS(Tele)'!AJ7 -> 0 | AM10: Comunications | AO10: =SUM(AQ10:BB10) -> 299 | AP10: =SUMPRODUCT((AQ$6:BB$6<=AP$6)*(AQ10:BB10)) -> 191 | AQ10: ='⑴-3 IS(Tele)'!AQ7 -> 147 | AR10: ='⑴-3 IS(Tele)'!AR7 -> 0 | AS10: ='⑴-3 IS(Tele)'!AS7 -> 44 | AT10: ='⑴-3 IS(Tele)'!AT7 -> 40 | AU10: ='⑴-3 IS(Tele)'!AU7 -> 0 | AV10: ='⑴-3 IS(Tele)'!AV7 -> 68 | AW10: ='⑴-3 IS(Tele)'!AW7 -> 0 | AX10: ='⑴-3 IS(Tele)'!AX7 -> 0 | ... BB10: ='⑴-3 IS(Tele)'!BB7 -> 0 | BE10: Comunications | BG10: =SUM(BI10:BT10) -> 2449 | BH10: =SUMPRODUCT((BI$6:BT$6<=BH$6)*(BI10:BT10)) -> 1067 | BI10: 851 | BJ10: 212 | BK10: 4 | BL10: 45 | BM10: 930 | BN10: 13 | BO10: 14 | BP10: 130 | BQ10: 64 | BR10: 88 | BS10: 8 | BT10: 90 | BW10: Comunications | BY10: =SUM(BZ10:CC10) -> 0 | BZ10: =SUM(G10:I10) -> 0 | CA10: =SUM(J10:L10) -> 0 | CB10: =SUM(M10:O10) -> 0 | CC10: =SUM(P10:R10) -> 0 | CD10: =SUM(CE10:CH10) -> 0 | CE10: =SUM(Y10:AA10) -> 0 | CF10: =SUM(AB10:AD10) -> 0 | CG10: =SUM(AE10:AG10) -> 0 | CH10: =SUM(AH10:AJ10) -> 0 | CI10: =SUM(CJ10:CM10) -> 299 | CJ10: =SUM(AQ10:AS10) -> 191 | CK10: =SUM(AT10:AV10) -> 108 | CL10: =SUM(AW10:AY10) -> 0 | CM10: =SUM(AZ10:BB10) -> 0 | CP10: Comunications | CR10: =E10-W10 -> 0 | CS10: =F10-X10 -> 0 | CT10: =G10-Y10 -> 0 | CU10: =H10-Z10 -> 0 | CV10: =I10-AA10 -> 0 | CW10: =J10-AB10 -> 0 | CX10: =K10-AC10 -> 0 | CY10: =L10-AD10 -> 0 | ... DE10: =R10-AJ10 -> 0 | DH10: Comunications | DJ10: =IFERROR(((E10-W10)/ABS(W10))+1,"") | DK10: =IFERROR(((F10-X10)/ABS(X10))+1,"") | DL10: =IFERROR(((G10-Y10)/ABS(Y10))+1,"") | DM10: =IFERROR(((H10-Z10)/ABS(Z10))+1,"") | DN10: =IFERROR(((I10-AA10)/ABS(AA10))+1,"") | DO10: =IFERROR(((J10-AB10)/ABS(AB10))+1,"") | DP10: =IFERROR(((K10-AC10)/ABS(AC10))+1,"") | DQ10: =IFERROR(((L10-AD10)/ABS(AD10))+1,"") | ... DW10: =IFERROR(((R10-AJ10)/ABS(AJ10))+1,"")
C11: Parking | E11: =SUM(G11:R11) -> 177883.01 | F11: =SUMPRODUCT((G$6:R$6<=F$6)*(G11:R11)) -> 177883.01 | G11: ='⑴-4 IS(Parking)'!G7 -> 64204 | H11: ='⑴-4 IS(Parking)'!H7 -> 51471 | I11: ='⑴-4 IS(Parking)'!I7 -> 62208.01 | J11: ='⑴-4 IS(Parking)'!J7 -> 0 | K11: ='⑴-4 IS(Parking)'!K7 -> 0 | L11: ='⑴-4 IS(Parking)'!L7 -> 0 | M11: ='⑴-4 IS(Parking)'!M7 -> 0 | N11: ='⑴-4 IS(Parking)'!N7 -> 0 | ... R11: ='⑴-4 IS(Parking)'!R7 -> 0 | U11: Parking | W11: =SUM(Y11:AJ11) -> 976214 | X11: =SUMPRODUCT((Y$6:AJ$6<=X$6)*(Y11:AJ11)) -> 234768 | Y11: ='⑴-4 IS(Parking)'!Y7 -> 85368 | Z11: ='⑴-4 IS(Parking)'!Z7 -> 67000 | AA11: ='⑴-4 IS(Parking)'!AA7 -> 82400 | AB11: ='⑴-4 IS(Parking)'!AB7 -> 83184 | AC11: ='⑴-4 IS(Parking)'!AC7 -> 86096 | AD11: ='⑴-4 IS(Parking)'!AD7 -> 86600 | AE11: ='⑴-4 IS(Parking)'!AE7 -> 92200 | AF11: ='⑴-4 IS(Parking)'!AF7 -> 87496 | ... AJ11: ='⑴-4 IS(Parking)'!AJ7 -> 66762 | AM11: Parking | AO11: =SUM(AQ11:BB11) -> 944489.61 | AP11: =SUMPRODUCT((AQ$6:BB$6<=AP$6)*(AQ11:BB11)) -> 211825.31 | AQ11: ='⑴-4 IS(Parking)'!AQ7 -> 81862.54 | AR11: ='⑴-4 IS(Parking)'!AR7 -> 65661.57 | AS11: ='⑴-4 IS(Parking)'!AS7 -> 64301.2 | AT11: ='⑴-4 IS(Parking)'!AT7 -> 60137.47 | AU11: ='⑴-4 IS(Parking)'!AU7 -> 145880.28 | AV11: ='⑴-4 IS(Parking)'!AV7 -> 81213.36 | AW11: ='⑴-4 IS(Parking)'!AW7 -> 88077.57 | AX11: ='⑴-4 IS(Parking)'!AX7 -> 79978.93 | ... BB11: ='⑴-4 IS(Parking)'!BB7 -> 75157.47 | BE11: Parking | BG11: =SUM(BI11:BT11) -> 813357 | BH11: =SUMPRODUCT((BI$6:BT$6<=BH$6)*(BI11:BT11)) -> 200714 | BI11: 70936 | BJ11: 59772 | BK11: 70006 | BL11: 66798 | BM11: 66558 | BN11: 66183 | BO11: 78158 | BP11: 75236 | BQ11: 72015 | BR11: 49865 | BS11: 64232 | BT11: 73598 | BW11: Parking | BY11: =SUM(BZ11:CC11) -> 177883.01 | BZ11: =SUM(G11:I11) -> 177883.01 | CA11: =SUM(J11:L11) -> 0 | CB11: =SUM(M11:O11) -> 0 | CC11: =SUM(P11:R11) -> 0 | CD11: =SUM(CE11:CH11) -> 976214 | CE11: =SUM(Y11:AA11) -> 234768 | CF11: =SUM(AB11:AD11) -> 255880 | CG11: =SUM(AE11:AG11) -> 257504 | CH11: =SUM(AH11:AJ11) -> 228062 | CI11: =SUM(CJ11:CM11) -> 944489.61 | CJ11: =SUM(AQ11:AS11) -> 211825.31 | CK11: =SUM(AT11:AV11) -> 287231.11 | CL11: =SUM(AW11:AY11) -> 240250.1 | CM11: =SUM(AZ11:BB11) -> 205183.09 | CP11: Parking | CR11: =E11-W11 -> -798330.99 | CS11: =F11-X11 -> -56884.99 | CT11: =G11-Y11 -> -21164 | CU11: =H11-Z11 -> -15529 | CV11: =I11-AA11 -> -20191.99 | CW11: =J11-AB11 -> -83184 | CX11: =K11-AC11 -> -86096 | CY11: =L11-AD11 -> -86600 | ... DE11: =R11-AJ11 -> -66762 | DH11: Parking | DJ11: =IFERROR(((E11-W11)/ABS(W11))+1,"") -> 0.18221723 | DK11: =IFERROR(((F11-X11)/ABS(X11))+1,"") -> 0.757697 | DL11: =IFERROR(((G11-Y11)/ABS(Y11))+1,"") -> 0.75208509 | DM11: =IFERROR(((H11-Z11)/ABS(Z11))+1,"") -> 0.76822388 | DN11: =IFERROR(((I11-AA11)/ABS(AA11))+1,"") -> 0.75495158 | DO11: =IFERROR(((J11-AB11)/ABS(AB11))+1,"") -> 0 | DP11: =IFERROR(((K11-AC11)/ABS(AC11))+1,"") -> 0 | DQ11: =IFERROR(((L11-AD11)/ABS(AD11))+1,"") -> 0 | ... DW11: =IFERROR(((R11-AJ11)/ABS(AJ11))+1,"") -> 0
C12: Other operated | E12: =SUM(G12:R12) -> 499376.01 | F12: =SUMPRODUCT((G$6:R$6<=F$6)*(G12:R12)) -> 499376.01 | G12: ='⑴-5 IS(Amenity)'!G7 -> 199082 | H12: ='⑴-5 IS(Amenity)'!H7 -> 156188 | I12: ='⑴-5 IS(Amenity)'!I7 -> 144106.01 | J12: ='⑴-5 IS(Amenity)'!J7 -> 0 | K12: ='⑴-5 IS(Amenity)'!K7 -> 0 | L12: ='⑴-5 IS(Amenity)'!L7 -> 0 | M12: ='⑴-5 IS(Amenity)'!M7 -> 0 | N12: ='⑴-5 IS(Amenity)'!N7 -> 0 | ... R12: ='⑴-5 IS(Amenity)'!R7 -> 0 | U12: Other operated | W12: =SUM(Y12:AJ12) -> 1869462 | X12: =SUMPRODUCT((Y$6:AJ$6<=X$6)*(Y12:AJ12)) -> 452016 | Y12: ='⑴-5 IS(Amenity)'!Y7 -> 155748 | Z12: ='⑴-5 IS(Amenity)'!Z7 -> 141881 | AA12: ='⑴-5 IS(Amenity)'!AA7 -> 154387 | AB12: ='⑴-5 IS(Amenity)'!AB7 -> 154654 | AC12: ='⑴-5 IS(Amenity)'!AC7 -> 160582 | AD12: ='⑴-5 IS(Amenity)'!AD7 -> 191506 | AE12: ='⑴-5 IS(Amenity)'!AE7 -> 156090 | AF12: ='⑴-5 IS(Amenity)'!AF7 -> 151374 | ... AJ12: ='⑴-5 IS(Amenity)'!AJ7 -> 126585 | AM12: Other operated | AO12: =SUM(AQ12:BB12) -> 1557235.3 | AP12: =SUMPRODUCT((AQ$6:BB$6<=AP$6)*(AQ12:BB12)) -> 380093.12 | AQ12: ='⑴-5 IS(Amenity)'!AQ7 -> 162088.54 | AR12: ='⑴-5 IS(Amenity)'!AR7 -> 99660.1 | AS12: ='⑴-5 IS(Amenity)'!AS7 -> 118344.48 | AT12: ='⑴-5 IS(Amenity)'!AT7 -> 135193.66 | AU12: ='⑴-5 IS(Amenity)'!AU7 -> 113920.2 | AV12: ='⑴-5 IS(Amenity)'!AV7 -> 106163.92 | AW12: ='⑴-5 IS(Amenity)'!AW7 -> 99607.76 | AX12: ='⑴-5 IS(Amenity)'!AX7 -> 107769.38 | ... BB12: ='⑴-5 IS(Amenity)'!BB7 -> 203836.33 | BE12: Other operated | BG12: =SUM(BI12:BT12) -> 1213846 | BH12: =SUMPRODUCT((BI$6:BT$6<=BH$6)*(BI12:BT12)) -> 250109 | BI12: 74307 | BJ12: 82277 | BK12: 93525 | BL12: 83593 | BM12: 96808 | BN12: 95974 | BO12: 112083 | BP12: 111288 | BQ12: 114433 | BR12: 94517 | BS12: 122293 | BT12: 132748 | BW12: Other operated | BY12: =SUM(BZ12:CC12) -> 499376.01 | BZ12: =SUM(G12:I12) -> 499376.01 | CA12: =SUM(J12:L12) -> 0 | CB12: =SUM(M12:O12) -> 0 | CC12: =SUM(P12:R12) -> 0 | CD12: =SUM(CE12:CH12) -> 1869462 | CE12: =SUM(Y12:AA12) -> 452016 | CF12: =SUM(AB12:AD12) -> 506742 | CG12: =SUM(AE12:AG12) -> 464165 | CH12: =SUM(AH12:AJ12) -> 446539 | CI12: =SUM(CJ12:CM12) -> 1557235.3 | CJ12: =SUM(AQ12:AS12) -> 380093.12 | CK12: =SUM(AT12:AV12) -> 355277.78 | CL12: =SUM(AW12:AY12) -> 325567.91 | CM12: =SUM(AZ12:BB12) -> 496296.52 | CP12: Other operated | CR12: =E12-W12 -> -1370086 | CS12: =F12-X12 -> 47360.01 | CT12: =G12-Y12 -> 43334 | CU12: =H12-Z12 -> 14307 | CV12: =I12-AA12 -> -10280.99 | CW12: =J12-AB12 -> -154654 | CX12: =K12-AC12 -> -160582 | CY12: =L12-AD12 -> -191506 | ... DE12: =R12-AJ12 -> -126585 | DH12: Other operated | DJ12: =IFERROR(((E12-W12)/ABS(W12))+1,"") -> 0.26712285 | DK12: =IFERROR(((F12-X12)/ABS(X12))+1,"") -> 1.1047751 | DL12: =IFERROR(((G12-Y12)/ABS(Y12))+1,"") -> 1.2782315 | DM12: =IFERROR(((H12-Z12)/ABS(Z12))+1,"") -> 1.100838 | DN12: =IFERROR(((I12-AA12)/ABS(AA12))+1,"") -> 0.93340767 | DO12: =IFERROR(((J12-AB12)/ABS(AB12))+1,"") -> 0 | DP12: =IFERROR(((K12-AC12)/ABS(AC12))+1,"") -> 0 | DQ12: =IFERROR(((L12-AD12)/ABS(AD12))+1,"") -> 0 | ... DW12: =IFERROR(((R12-AJ12)/ABS(AJ12))+1,"") -> 0
C13: Rent and other | E13: =SUM(G13:R13) -> 158909.68 | F13: =SUMPRODUCT((G$6:R$6<=F$6)*(G13:R13)) -> 158909.68 | G13: ='⑴-6 IS(Others)'!G7 -> 55852 | H13: ='⑴-6 IS(Others)'!H7 -> 53392 | I13: ='⑴-6 IS(Others)'!I7 -> 49665.68 | J13: ='⑴-6 IS(Others)'!J7 -> 0 | K13: ='⑴-6 IS(Others)'!K7 -> 0 | L13: ='⑴-6 IS(Others)'!L7 -> 0 | M13: ='⑴-6 IS(Others)'!M7 -> 0 | N13: ='⑴-6 IS(Others)'!N7 -> 0 | ... R13: ='⑴-6 IS(Others)'!R7 -> 0 | U13: Rent and other | W13: =SUM(Y13:AJ13) -> 624000 | X13: =SUMPRODUCT((Y$6:AJ$6<=X$6)*(Y13:AJ13)) -> 156000 | Y13: ='⑴-6 IS(Others)'!Y7 -> 52000 | Z13: ='⑴-6 IS(Others)'!Z7 -> 52000 | AA13: ='⑴-6 IS(Others)'!AA7 -> 52000 | AB13: ='⑴-6 IS(Others)'!AB7 -> 52000 | AC13: ='⑴-6 IS(Others)'!AC7 -> 52000 | AD13: ='⑴-6 IS(Others)'!AD7 -> 52000 | AE13: ='⑴-6 IS(Others)'!AE7 -> 52000 | AF13: ='⑴-6 IS(Others)'!AF7 -> 52000 | ... AJ13: ='⑴-6 IS(Others)'!AJ7 -> 52000 | AM13: Rent and other | AO13: =SUM(AQ13:BB13) -> 638841.85 | AP13: =SUMPRODUCT((AQ$6:BB$6<=AP$6)*(AQ13:BB13)) -> 150146.53 | AQ13: ='⑴-6 IS(Others)'!AQ7 -> 49875.91 | AR13: ='⑴-6 IS(Others)'!AR7 -> 51347.33 | AS13: ='⑴-6 IS(Others)'!AS7 -> 48923.29 | AT13: ='⑴-6 IS(Others)'!AT7 -> 49757.16 | AU13: ='⑴-6 IS(Others)'!AU7 -> 52289.36 | AV13: ='⑴-6 IS(Others)'!AV7 -> 54419.32 | AW13: ='⑴-6 IS(Others)'!AW7 -> 56294.94 | AX13: ='⑴-6 IS(Others)'!AX7 -> 56248.39 | ... BB13: ='⑴-6 IS(Others)'!BB7 -> 52359.99 | BE13: Rent and other | BG13: =SUM(BI13:BT13) -> 447250 | BH13: =SUMPRODUCT((BI$6:BT$6<=BH$6)*(BI13:BT13)) -> 92043 | BI13: 30066 | BJ13: 30098 | BK13: 31879 | BL13: 32105 | BM13: 31961 | BN13: 32473 | BO13: 32024 | BP13: 32208 | BQ13: 33212 | BR13: 32705 | BS13: 54825 | BT13: 73694 | BW13: Rent and other | BY13: =SUM(BZ13:CC13) -> 158909.68 | BZ13: =SUM(G13:I13) -> 158909.68 | CA13: =SUM(J13:L13) -> 0 | CB13: =SUM(M13:O13) -> 0 | CC13: =SUM(P13:R13) -> 0 | CD13: =SUM(CE13:CH13) -> 624000 | CE13: =SUM(Y13:AA13) -> 156000 | CF13: =SUM(AB13:AD13) -> 156000 | CG13: =SUM(AE13:AG13) -> 156000 | CH13: =SUM(AH13:AJ13) -> 156000 | CI13: =SUM(CJ13:CM13) -> 638841.85 | CJ13: =SUM(AQ13:AS13) -> 150146.53 | CK13: =SUM(AT13:AV13) -> 156465.84 | CL13: =SUM(AW13:AY13) -> 167502.7 | CM13: =SUM(AZ13:BB13) -> 164726.78 | CP13: Rent and other | CR13: =E13-W13 -> -465090.32 | CS13: =F13-X13 -> 2909.68 | CT13: =G13-Y13 -> 3852 | CU13: =H13-Z13 -> 1392 | CV13: =I13-AA13 -> -2334.32 | CW13: =J13-AB13 -> -52000 | CX13: =K13-AC13 -> -52000 | CY13: =L13-AD13 -> -52000 | ... DE13: =R13-AJ13 -> -52000 | DH13: Rent and other | DJ13: =IFERROR(((E13-W13)/ABS(W13))+1,"") -> 0.25466295 | DK13: =IFERROR(((F13-X13)/ABS(X13))+1,"") -> 1.0186518 | DL13: =IFERROR(((G13-Y13)/ABS(Y13))+1,"") -> 1.0740769 | DM13: =IFERROR(((H13-Z13)/ABS(Z13))+1,"") -> 1.0267692 | DN13: =IFERROR(((I13-AA13)/ABS(AA13))+1,"") -> 0.95510923 | DO13: =IFERROR(((J13-AB13)/ABS(AB13))+1,"") -> 0 | DP13: =IFERROR(((K13-AC13)/ABS(AC13))+1,"") -> 0 | DQ13: =IFERROR(((L13-AD13)/ABS(AD13))+1,"") -> 0 | ... DW13: =IFERROR(((R13-AJ13)/ABS(AJ13))+1,"") -> 0
B14: Departmental expenses | E14: =SUM(G14:R14) -> 2397513.9 | F14: =SUMPRODUCT((G$6:R$6<=F$6)*(G14:R14)) -> 2397513.9 | G14: =SUM(G15:G20) -> 849707.05 | H14: =SUM(H15:H20) -> 750988 | I14: =SUM(I15:I20) -> 796818.83 | J14: =SUM(J15:J20) -> 0 | K14: =SUM(K15:K20) -> 0 | L14: =SUM(L15:L20) -> 0 | M14: =SUM(M15:M20) -> 0 | N14: =SUM(N15:N20) -> 0 | ... R14: =SUM(R15:R20) -> 0 | T14: =$B14 -> Departmental expenses | W14: =SUM(Y14:AJ14) -> 9452095.4 | X14: =SUMPRODUCT((Y$6:AJ$6<=X$6)*(Y14:AJ14)) -> 2299357.9 | Y14: =SUM(Y15:Y20) -> 785482.28 | Z14: =SUM(Z15:Z20) -> 709707.72 | AA14: =SUM(AA15:AA20) -> 804167.87 | AB14: =SUM(AB15:AB20) -> 782902.35 | AC14: =SUM(AC15:AC20) -> 792643.44 | AD14: =SUM(AD15:AD20) -> 776431 | AE14: =SUM(AE15:AE20) -> 796648.35 | AF14: =SUM(AF15:AF20) -> 791298.99 | ... AJ14: =SUM(AJ15:AJ20) -> 827724.98 | AL14: =$B14 -> Departmental expenses | AO14: =SUM(AQ14:BB14) -> 9426963.8 | AP14: =SUMPRODUCT((AQ$6:BB$6<=AP$6)*(AQ14:BB14)) -> 2302817.9 | AQ14: =SUM(AQ15:AQ20) -> 764279.76 | AR14: =SUM(AR15:AR20) -> 736986.08 | AS14: =SUM(AS15:AS20) -> 801552.03 | AT14: =SUM(AT15:AT20) -> 725035.68 | AU14: =SUM(AU15:AU20) -> 766172.25 | AV14: =SUM(AV15:AV20) -> 721583.96 | AW14: =SUM(AW15:AW20) -> 780355.76 | AX14: =SUM(AX15:AX20) -> 844139.06 | ... BB14: =SUM(BB15:BB20) -> 984934.56 | BD14: =$B14 -> Departmental expenses | BG14: =SUM(BI14:BT14) -> 8163167 | BH14: =SUMPRODUCT((BI$6:BT$6<=BH$6)*(BI14:BT14)) -> 1945906 | BI14: =SUM(BI15:BI20) -> 661834 | BJ14: =SUM(BJ15:BJ20) -> 617917 | BK14: =SUM(BK15:BK20) -> 666155 | BL14: =SUM(BL15:BL20) -> 662546 | BM14: =SUM(BM15:BM20) -> 622344 | BN14: =SUM(BN15:BN20) -> 650409 | BO14: =SUM(BO15:BO20) -> 648663 | BP14: =SUM(BP15:BP20) -> 687943 | ... BT14: =SUM(BT15:BT20) -> 789161 | BV14: =$B14 -> Departmental expenses | BY14: =SUM(BZ14:CC14) -> 2397513.9 | BZ14: =SUM(BZ15:BZ20) -> 2397513.9 | CA14: =SUM(CA15:CA20) -> 0 | CB14: =SUM(CB15:CB20) -> 0 | CC14: =SUM(CC15:CC20) -> 0 | CD14: =SUM(CE14:CH14) -> 9452095.4 | CE14: =SUM(CE15:CE20) -> 2299357.9 | CF14: =SUM(CF15:CF20) -> 2351976.8 | CG14: =SUM(CG15:CG20) -> 2351574.1 | CH14: =SUM(CH15:CH20) -> 2449186.7 | CI14: =SUM(CJ14:CM14) -> 9426963.8 | CJ14: =SUM(CJ15:CJ20) -> 2302817.9 | CK14: =SUM(CK15:CK20) -> 2212791.9 | CL14: =SUM(CL15:CL20) -> 2390427.7 | CM14: =SUM(CM15:CM20) -> 2520926.3 | CO14: =$B14 -> Departmental expenses | CR14: =E14-W14 -> -7054581.5 | CS14: =F14-X14 -> 98156.005 | CT14: =G14-Y14 -> 64224.769 | CU14: =H14-Z14 -> 41280.276 | CV14: =I14-AA14 -> -7349.0392 | CW14: =J14-AB14 -> -782902.35 | CX14: =K14-AC14 -> -792643.44 | CY14: =L14-AD14 -> -776431 | ... DE14: =R14-AJ14 -> -827724.98 | DG14: =$B14 -> Departmental expenses | DJ14: =IFERROR(((E14-W14)/ABS(W14))+1,"") -> 0.25364893 | DK14: =IFERROR(((F14-X14)/ABS(X14))+1,"") -> 1.0426884 | DL14: =IFERROR(((G14-Y14)/ABS(Y14))+1,"") -> 1.0817648 | DM14: =IFERROR(((H14-Z14)/ABS(Z14))+1,"") -> 1.0581652 | DN14: =IFERROR(((I14-AA14)/ABS(AA14))+1,"") -> 0.99086131 | DO14: =IFERROR(((J14-AB14)/ABS(AB14))+1,"") -> 0 | DP14: =IFERROR(((K14-AC14)/ABS(AC14))+1,"") -> 0 | DQ14: =IFERROR(((L14-AD14)/ABS(AD14))+1,"") -> 0 | ... DW14: =IFERROR(((R14-AJ14)/ABS(AJ14))+1,"") -> 0
C15: Rooms | E15: =SUM(G15:R15) -> 1800972.9 | F15: =SUMPRODUCT((G$6:R$6<=F$6)*(G15:R15)) -> 1800972.9 | G15: ='⑴-1 IS(Rooms)'!G18 -> 634628 | H15: ='⑴-1 IS(Rooms)'!H18 -> 567035 | I15: ='⑴-1 IS(Rooms)'!I18 -> 599309.9 | J15: ='⑴-1 IS(Rooms)'!J18 -> 0 | K15: ='⑴-1 IS(Rooms)'!K18 -> 0 | L15: ='⑴-1 IS(Rooms)'!L18 -> 0 | M15: ='⑴-1 IS(Rooms)'!M18 -> 0 | N15: ='⑴-1 IS(Rooms)'!N18 -> 0 | ... R15: ='⑴-1 IS(Rooms)'!R18 -> 0 | U15: =$C15 -> Rooms | W15: =SUM(Y15:AJ15) -> 7131859 | X15: =SUMPRODUCT((Y$6:AJ$6<=X$6)*(Y15:AJ15)) -> 1732463.6 | Y15: ='⑴-1 IS(Rooms)'!Y18 -> 595707.11 | Z15: ='⑴-1 IS(Rooms)'!Z18 -> 529739.57 | AA15: ='⑴-1 IS(Rooms)'!AA18 -> 607016.94 | AB15: ='⑴-1 IS(Rooms)'!AB18 -> 594767.22 | AC15: ='⑴-1 IS(Rooms)'!AC18 -> 601182.27 | AD15: ='⑴-1 IS(Rooms)'!AD18 -> 580795.22 | AE15: ='⑴-1 IS(Rooms)'!AE18 -> 603761.27 | AF15: ='⑴-1 IS(Rooms)'!AF18 -> 603824.27 | ... AJ15: ='⑴-1 IS(Rooms)'!AJ18 -> 622064.96 | AM15: =$C15 -> Rooms | AO15: =SUM(AQ15:BB15) -> 6858534.6 | AP15: =SUMPRODUCT((AQ$6:BB$6<=AP$6)*(AQ15:BB15)) -> 1710066.8 | AQ15: ='⑴-1 IS(Rooms)'!AQ18 -> 573133.3 | AR15: ='⑴-1 IS(Rooms)'!AR18 -> 544532.64 | AS15: ='⑴-1 IS(Rooms)'!AS18 -> 592400.87 | AT15: ='⑴-1 IS(Rooms)'!AT18 -> 535017.28 | AU15: ='⑴-1 IS(Rooms)'!AU18 -> 578292.69 | AV15: ='⑴-1 IS(Rooms)'!AV18 -> 536278.78 | AW15: ='⑴-1 IS(Rooms)'!AW18 -> 582844.12 | AX15: ='⑴-1 IS(Rooms)'!AX18 -> 609579.81 | ... BB15: ='⑴-1 IS(Rooms)'!BB18 -> 691049.78 | BE15: =$C15 -> Rooms | BG15: =SUM(BI15:BT15) -> 6397159 | BH15: =SUMPRODUCT((BI$6:BT$6<=BH$6)*(BI15:BT15)) -> 1534411 | BI15: 531732 | BJ15: 479160 | BK15: 523519 | BL15: 515743 | BM15: 485474 | BN15: 510056 | BO15: 506538 | BP15: 550985 | BQ15: 558561 | BR15: 556026 | BS15: 557203 | BT15: 622162 | BW15: =$C15 -> Rooms | BY15: =SUM(BZ15:CC15) -> 1800972.9 | BZ15: =SUM(G15:I15) -> 1800972.9 | CA15: =SUM(J15:L15) -> 0 | CB15: =SUM(M15:O15) -> 0 | CC15: =SUM(P15:R15) -> 0 | CD15: =SUM(CE15:CH15) -> 7131859 | CE15: =SUM(Y15:AA15) -> 1732463.6 | CF15: =SUM(AB15:AD15) -> 1776744.7 | CG15: =SUM(AE15:AG15) -> 1780741.8 | CH15: =SUM(AH15:AJ15) -> 1841908.9 | CI15: =SUM(CJ15:CM15) -> 6858534.6 | CJ15: =SUM(AQ15:AS15) -> 1710066.8 | CK15: =SUM(AT15:AV15) -> 1649588.8 | CL15: =SUM(AW15:AY15) -> 1731329.6 | CM15: =SUM(AZ15:BB15) -> 1767549.5 | CP15: =$C15 -> Rooms | CR15: =E15-W15 -> -5330886.1 | CS15: =F15-X15 -> 68509.274 | CT15: =G15-Y15 -> 38920.886 | CU15: =H15-Z15 -> 37295.43 | CV15: =I15-AA15 -> -7707.0418 | CW15: =J15-AB15 -> -594767.22 | CX15: =K15-AC15 -> -601182.27 | CY15: =L15-AD15 -> -580795.22 | ... DE15: =R15-AJ15 -> -622064.96 | DH15: =$C15 -> Rooms | DJ15: =IFERROR(((E15-W15)/ABS(W15))+1,"") -> 0.25252503 | DK15: =IFERROR(((F15-X15)/ABS(X15))+1,"") -> 1.0395444 | DL15: =IFERROR(((G15-Y15)/ABS(Y15))+1,"") -> 1.0653356 | DM15: =IFERROR(((H15-Z15)/ABS(Z15))+1,"") -> 1.0704033 | DN15: =IFERROR(((I15-AA15)/ABS(AA15))+1,"") -> 0.98730342 | DO15: =IFERROR(((J15-AB15)/ABS(AB15))+1,"") -> 0 | DP15: =IFERROR(((K15-AC15)/ABS(AC15))+1,"") -> 0 | DQ15: =IFERROR(((L15-AD15)/ABS(AD15))+1,"") -> 0 | ... DW15: =IFERROR(((R15-AJ15)/ABS(AJ15))+1,"") -> 0
C16: Food and beverage | E16: =SUM(G16:R16) -> 565431.4 | F16: =SUMPRODUCT((G$6:R$6<=F$6)*(G16:R16)) -> 565431.4 | G16: ='⑴-2 IS(F&B)'!G18 -> 202656 | H16: ='⑴-2 IS(F&B)'!H18 -> 175699 | I16: ='⑴-2 IS(F&B)'!I18 -> 187076.4 | J16: ='⑴-2 IS(F&B)'!J18 -> 0 | K16: ='⑴-2 IS(F&B)'!K18 -> 0 | L16: ='⑴-2 IS(F&B)'!L18 -> 0 | M16: ='⑴-2 IS(F&B)'!M18 -> 0 | N16: ='⑴-2 IS(F&B)'!N18 -> 0 | ... R16: ='⑴-2 IS(F&B)'!R18 -> 0 | U16: =$C16 -> Food and beverage | W16: =SUM(Y16:AJ16) -> 2192028.4 | X16: =SUMPRODUCT((Y$6:AJ$6<=X$6)*(Y16:AJ16)) -> 534842.25 | Y16: ='⑴-2 IS(F&B)'!Y18 -> 179091.17 | Z16: ='⑴-2 IS(F&B)'!Z18 -> 169284.15 | AA16: ='⑴-2 IS(F&B)'!AA18 -> 186466.93 | AB16: ='⑴-2 IS(F&B)'!AB18 -> 177451.13 | AC16: ='⑴-2 IS(F&B)'!AC18 -> 180777.18 | AD16: ='⑴-2 IS(F&B)'!AD18 -> 184951.78 | AE16: ='⑴-2 IS(F&B)'!AE18 -> 182203.09 | AF16: ='⑴-2 IS(F&B)'!AF18 -> 176790.72 | ... AJ16: ='⑴-2 IS(F&B)'!AJ18 -> 194976.03 | AM16: =$C16 -> Food and beverage | AO16: =SUM(AQ16:BB16) -> 2398209.5 | AP16: =SUMPRODUCT((AQ$6:BB$6<=AP$6)*(AQ16:BB16)) -> 539863.89 | AQ16: ='⑴-2 IS(F&B)'!AQ18 -> 174078.67 | AR16: ='⑴-2 IS(F&B)'!AR18 -> 173381.06 | AS16: ='⑴-2 IS(F&B)'!AS18 -> 192404.16 | AT16: ='⑴-2 IS(F&B)'!AT18 -> 174972.57 | AU16: ='⑴-2 IS(F&B)'!AU18 -> 171737.3 | AV16: ='⑴-2 IS(F&B)'!AV18 -> 175430.22 | AW16: ='⑴-2 IS(F&B)'!AW18 -> 186880.18 | AX16: ='⑴-2 IS(F&B)'!AX18 -> 217902.02 | ... BB16: ='⑴-2 IS(F&B)'!BB18 -> 281984.78 | BE16: =$C16 -> Food and beverage | BG16: =SUM(BI16:BT16) -> 1640787 | BH16: =SUMPRODUCT((BI$6:BT$6<=BH$6)*(BI16:BT16)) -> 383978 | BI16: 121489 | BJ16: 129443 | BK16: 133046 | BL16: 137852 | BM16: 127070 | BN16: 130312 | BO16: 130698 | BP16: 126245 | BQ16: 129254 | BR16: 189437 | BS16: 132796 | BT16: 153145 | BW16: =$C16 -> Food and beverage | BY16: =SUM(BZ16:CC16) -> 565431.4 | BZ16: =SUM(G16:I16) -> 565431.4 | CA16: =SUM(J16:L16) -> 0 | CB16: =SUM(M16:O16) -> 0 | CC16: =SUM(P16:R16) -> 0 | CD16: =SUM(CE16:CH16) -> 2192028.4 | CE16: =SUM(Y16:AA16) -> 534842.25 | CF16: =SUM(AB16:AD16) -> 543180.09 | CG16: =SUM(AE16:AG16) -> 538780.32 | CH16: =SUM(AH16:AJ16) -> 575225.73 | CI16: =SUM(CJ16:CM16) -> 2398209.5 | CJ16: =SUM(AQ16:AS16) -> 539863.89 | CK16: =SUM(AT16:AV16) -> 522140.09 | CL16: =SUM(AW16:AY16) -> 615391.41 | CM16: =SUM(AZ16:BB16) -> 720814.14 | CP16: =$C16 -> Food and beverage | CR16: =E16-W16 -> -1626597 | CS16: =F16-X16 -> 30589.152 | CT16: =G16-Y16 -> 23564.833 | CU16: =H16-Z16 -> 6414.8464 | CV16: =I16-AA16 -> 609.47262 | CW16: =J16-AB16 -> -177451.13 | CX16: =K16-AC16 -> -180777.18 | CY16: =L16-AD16 -> -184951.78 | ... DE16: =R16-AJ16 -> -194976.03 | DH16: =$C16 -> Food and beverage | DJ16: =IFERROR(((E16-W16)/ABS(W16))+1,"") -> 0.25794894 | DK16: =IFERROR(((F16-X16)/ABS(X16))+1,"") -> 1.0571928 | DL16: =IFERROR(((G16-Y16)/ABS(Y16))+1,"") -> 1.1315801 | DM16: =IFERROR(((H16-Z16)/ABS(Z16))+1,"") -> 1.037894 | DN16: =IFERROR(((I16-AA16)/ABS(AA16))+1,"") -> 1.0032685 | DO16: =IFERROR(((J16-AB16)/ABS(AB16))+1,"") -> 0 | DP16: =IFERROR(((K16-AC16)/ABS(AC16))+1,"") -> 0 | DQ16: =IFERROR(((L16-AD16)/ABS(AD16))+1,"") -> 0 | ... DW16: =IFERROR(((R16-AJ16)/ABS(AJ16))+1,"") -> 0
C17: Comunications | E17: =SUM(G17:R17) -> 7694.06 | F17: =SUMPRODUCT((G$6:R$6<=F$6)*(G17:R17)) -> 7694.06 | G17: ='⑴-3 IS(Tele)'!G18 -> 2041.05 | H17: ='⑴-3 IS(Tele)'!H18 -> 2037 | I17: ='⑴-3 IS(Tele)'!I18 -> 3616.01 | J17: ='⑴-3 IS(Tele)'!J18 -> 0 | K17: ='⑴-3 IS(Tele)'!K18 -> 0 | L17: ='⑴-3 IS(Tele)'!L18 -> 0 | M17: ='⑴-3 IS(Tele)'!M18 -> 0 | N17: ='⑴-3 IS(Tele)'!N18 -> 0 | ... R17: ='⑴-3 IS(Tele)'!R18 -> 0 | U17: =$C17 -> Comunications | W17: =SUM(Y17:AJ17) -> 10200 | X17: =SUMPRODUCT((Y$6:AJ$6<=X$6)*(Y17:AJ17)) -> 2550 | Y17: ='⑴-3 IS(Tele)'!Y18 -> 850 | Z17: ='⑴-3 IS(Tele)'!Z18 -> 850 | AA17: ='⑴-3 IS(Tele)'!AA18 -> 850 | AB17: ='⑴-3 IS(Tele)'!AB18 -> 850 | AC17: ='⑴-3 IS(Tele)'!AC18 -> 850 | AD17: ='⑴-3 IS(Tele)'!AD18 -> 850 | AE17: ='⑴-3 IS(Tele)'!AE18 -> 850 | AF17: ='⑴-3 IS(Tele)'!AF18 -> 850 | ... AJ17: ='⑴-3 IS(Tele)'!AJ18 -> 850 | AM17: =$C17 -> Comunications | AO17: =SUM(AQ17:BB17) -> 11289.42 | AP17: =SUMPRODUCT((AQ$6:BB$6<=AP$6)*(AQ17:BB17)) -> 1213.52 | AQ17: ='⑴-3 IS(Tele)'!AQ18 -> 408.79 | AR17: ='⑴-3 IS(Tele)'!AR18 -> 405.73 | AS17: ='⑴-3 IS(Tele)'!AS18 -> 399 | AT17: ='⑴-3 IS(Tele)'!AT18 -> 592.49 | AU17: ='⑴-3 IS(Tele)'!AU18 -> 600.98 | AV17: ='⑴-3 IS(Tele)'!AV18 -> 617.65 | AW17: ='⑴-3 IS(Tele)'!AW18 -> 1377.55 | AX17: ='⑴-3 IS(Tele)'!AX18 -> 1375.23 | ... BB17: ='⑴-3 IS(Tele)'!BB18 -> 1378 | BE17: =$C17 -> Comunications | BG17: =SUM(BI17:BT17) -> 4492 | BH17: =SUMPRODUCT((BI$6:BT$6<=BH$6)*(BI17:BT17)) -> 1112 | BI17: 366 | BJ17: 376 | BK17: 370 | BL17: 367 | BM17: 370 | BN17: 370 | BO17: 357 | BP17: 353 | BQ17: 472 | BR17: 369 | BS17: 363 | BT17: 359 | BW17: =$C17 -> Comunications | BY17: =SUM(BZ17:CC17) -> 7694.06 | BZ17: =SUM(G17:I17) -> 7694.06 | CA17: =SUM(J17:L17) -> 0 | CB17: =SUM(M17:O17) -> 0 | CC17: =SUM(P17:R17) -> 0 | CD17: =SUM(CE17:CH17) -> 10200 | CE17: =SUM(Y17:AA17) -> 2550 | CF17: =SUM(AB17:AD17) -> 2550 | CG17: =SUM(AE17:AG17) -> 2550 | CH17: =SUM(AH17:AJ17) -> 2550 | CI17: =SUM(CJ17:CM17) -> 11289.42 | CJ17: =SUM(AQ17:AS17) -> 1213.52 | CK17: =SUM(AT17:AV17) -> 1811.12 | CL17: =SUM(AW17:AY17) -> 4130.78 | CM17: =SUM(AZ17:BB17) -> 4134 | CP17: =$C17 -> Comunications | CR17: =E17-W17 -> -2505.94 | CS17: =F17-X17 -> 5144.06 | CT17: =G17-Y17 -> 1191.05 | CU17: =H17-Z17 -> 1187 | CV17: =I17-AA17 -> 2766.01 | CW17: =J17-AB17 -> -850 | CX17: =K17-AC17 -> -850 | CY17: =L17-AD17 -> -850 | ... DE17: =R17-AJ17 -> -850 | DH17: =$C17 -> Comunications | DJ17: =IFERROR(((E17-W17)/ABS(W17))+1,"") -> 0.75431961 | DK17: =IFERROR(((F17-X17)/ABS(X17))+1,"") -> 3.0172784 | DL17: =IFERROR(((G17-Y17)/ABS(Y17))+1,"") -> 2.4012353 | DM17: =IFERROR(((H17-Z17)/ABS(Z17))+1,"") -> 2.3964706 | DN17: =IFERROR(((I17-AA17)/ABS(AA17))+1,"") -> 4.2541294 | DO17: =IFERROR(((J17-AB17)/ABS(AB17))+1,"") -> 0 | DP17: =IFERROR(((K17-AC17)/ABS(AC17))+1,"") -> 0 | DQ17: =IFERROR(((L17-AD17)/ABS(AD17))+1,"") -> 0 | ... DW17: =IFERROR(((R17-AJ17)/ABS(AJ17))+1,"") -> 0
C18: Parking | E18: =SUM(G18:R18) -> 0 | F18: =SUMPRODUCT((G$6:R$6<=F$6)*(G18:R18)) -> 0 | G18: ='⑴-4 IS(Parking)'!G18 -> 0 | H18: ='⑴-4 IS(Parking)'!H18 -> 0 | I18: ='⑴-4 IS(Parking)'!I18 -> 0 | J18: ='⑴-4 IS(Parking)'!J18 -> 0 | K18: ='⑴-4 IS(Parking)'!K18 -> 0 | L18: ='⑴-4 IS(Parking)'!L18 -> 0 | M18: ='⑴-4 IS(Parking)'!M18 -> 0 | N18: ='⑴-4 IS(Parking)'!N18 -> 0 | ... R18: ='⑴-4 IS(Parking)'!R18 -> 0 | U18: =$C18 -> Parking | W18: =SUM(Y18:AJ18) -> 0 | X18: =SUMPRODUCT((Y$6:AJ$6<=X$6)*(Y18:AJ18)) -> 0 | Y18: ='⑴-4 IS(Parking)'!Y18 -> 0 | Z18: ='⑴-4 IS(Parking)'!Z18 -> 0 | AA18: ='⑴-4 IS(Parking)'!AA18 -> 0 | AB18: ='⑴-4 IS(Parking)'!AB18 -> 0 | AC18: ='⑴-4 IS(Parking)'!AC18 -> 0 | AD18: ='⑴-4 IS(Parking)'!AD18 -> 0 | AE18: ='⑴-4 IS(Parking)'!AE18 -> 0 | AF18: ='⑴-4 IS(Parking)'!AF18 -> 0 | ... AJ18: ='⑴-4 IS(Parking)'!AJ18 -> 0 | AM18: =$C18 -> Parking | AO18: =SUM(AQ18:BB18) -> 0 | AP18: =SUMPRODUCT((AQ$6:BB$6<=AP$6)*(AQ18:BB18)) -> 0 | AQ18: ='⑴-4 IS(Parking)'!AQ18 -> 0 | AR18: ='⑴-4 IS(Parking)'!AR18 -> 0 | AS18: ='⑴-4 IS(Parking)'!AS18 -> 0 | AT18: ='⑴-4 IS(Parking)'!AT18 -> 0 | AU18: ='⑴-4 IS(Parking)'!AU18 -> 0 | AV18: ='⑴-4 IS(Parking)'!AV18 -> 0 | AW18: ='⑴-4 IS(Parking)'!AW18 -> 0 | AX18: ='⑴-4 IS(Parking)'!AX18 -> 0 | ... BB18: ='⑴-4 IS(Parking)'!BB18 -> 0 | BE18: =$C18 -> Parking | BG18: =SUM(BI18:BT18) -> 3077 | BH18: =SUMPRODUCT((BI$6:BT$6<=BH$6)*(BI18:BT18)) -> 0 | BI18: 0 | BJ18: 0 | BK18: 0 | BL18: 0 | BM18: 0 | BN18: 0 | BO18: 660 | BP18: 0 | BQ18: 0 | BR18: 0 | BS18: 657 | BT18: 1760 | BW18: =$C18 -> Parking | BY18: =SUM(BZ18:CC18) -> 0 | BZ18: =SUM(G18:I18) -> 0 | CA18: =SUM(J18:L18) -> 0 | CB18: =SUM(M18:O18) -> 0 | CC18: =SUM(P18:R18) -> 0 | CD18: =SUM(CE18:CH18) -> 0 | CE18: =SUM(Y18:AA18) -> 0 | CF18: =SUM(AB18:AD18) -> 0 | CG18: =SUM(AE18:AG18) -> 0 | CH18: =SUM(AH18:AJ18) -> 0 | CI18: =SUM(CJ18:CM18) -> 0 | CJ18: =SUM(AQ18:AS18) -> 0 | CK18: =SUM(AT18:AV18) -> 0 | CL18: =SUM(AW18:AY18) -> 0 | CM18: =SUM(AZ18:BB18) -> 0 | CP18: =$C18 -> Parking | CR18: =E18-W18 -> 0 | CS18: =F18-X18 -> 0 | CT18: =G18-Y18 -> 0 | CU18: =H18-Z18 -> 0 | CV18: =I18-AA18 -> 0 | CW18: =J18-AB18 -> 0 | CX18: =K18-AC18 -> 0 | CY18: =L18-AD18 -> 0 | ... DE18: =R18-AJ18 -> 0 | DH18: =$C18 -> Parking | DJ18: =IFERROR(((E18-W18)/ABS(W18))+1,"") | DK18: =IFERROR(((F18-X18)/ABS(X18))+1,"") | DL18: =IFERROR(((G18-Y18)/ABS(Y18))+1,"") | DM18: =IFERROR(((H18-Z18)/ABS(Z18))+1,"") | DN18: =IFERROR(((I18-AA18)/ABS(AA18))+1,"") | DO18: =IFERROR(((J18-AB18)/ABS(AB18))+1,"") | DP18: =IFERROR(((K18-AC18)/ABS(AC18))+1,"") | DQ18: =IFERROR(((L18-AD18)/ABS(AD18))+1,"") | ... DW18: =IFERROR(((R18-AJ18)/ABS(AJ18))+1,"")
C19: Other operated | E19: =SUM(G19:R19) -> 23415.52 | F19: =SUMPRODUCT((G$6:R$6<=F$6)*(G19:R19)) -> 23415.52 | G19: ='⑴-5 IS(Amenity)'!G18 -> 10382 | H19: ='⑴-5 IS(Amenity)'!H18 -> 6217 | I19: ='⑴-5 IS(Amenity)'!I18 -> 6816.52 | J19: ='⑴-5 IS(Amenity)'!J18 -> 0 | K19: ='⑴-5 IS(Amenity)'!K18 -> 0 | L19: ='⑴-5 IS(Amenity)'!L18 -> 0 | M19: ='⑴-5 IS(Amenity)'!M18 -> 0 | N19: ='⑴-5 IS(Amenity)'!N18 -> 0 | ... R19: ='⑴-5 IS(Amenity)'!R18 -> 0 | U19: =$C19 -> Other operated | W19: =SUM(Y19:AJ19) -> 118008 | X19: =SUMPRODUCT((Y$6:AJ$6<=X$6)*(Y19:AJ19)) -> 29502 | Y19: ='⑴-5 IS(Amenity)'!Y18 -> 9834 | Z19: ='⑴-5 IS(Amenity)'!Z18 -> 9834 | AA19: ='⑴-5 IS(Amenity)'!AA18 -> 9834 | AB19: ='⑴-5 IS(Amenity)'!AB18 -> 9834 | AC19: ='⑴-5 IS(Amenity)'!AC18 -> 9834 | AD19: ='⑴-5 IS(Amenity)'!AD18 -> 9834 | AE19: ='⑴-5 IS(Amenity)'!AE18 -> 9834 | AF19: ='⑴-5 IS(Amenity)'!AF18 -> 9834 | ... AJ19: ='⑴-5 IS(Amenity)'!AJ18 -> 9834 | AM19: =$C19 -> Other operated | AO19: =SUM(AQ19:BB19) -> 158930.19 | AP19: =SUMPRODUCT((AQ$6:BB$6<=AP$6)*(AQ19:BB19)) -> 51673.66 | AQ19: ='⑴-5 IS(Amenity)'!AQ18 -> 16659 | AR19: ='⑴-5 IS(Amenity)'!AR18 -> 18666.66 | AS19: ='⑴-5 IS(Amenity)'!AS18 -> 16348 | AT19: ='⑴-5 IS(Amenity)'!AT18 -> 14453.34 | AU19: ='⑴-5 IS(Amenity)'!AU18 -> 15541.28 | AV19: ='⑴-5 IS(Amenity)'!AV18 -> 9257.31 | AW19: ='⑴-5 IS(Amenity)'!AW18 -> 9253.91 | AX19: ='⑴-5 IS(Amenity)'!AX18 -> 15282 | ... BB19: ='⑴-5 IS(Amenity)'!BB18 -> 10522 | BE19: =$C19 -> Other operated | BG19: =SUM(BI19:BT19) -> 117652 | BH19: =SUMPRODUCT((BI$6:BT$6<=BH$6)*(BI19:BT19)) -> 26405 | BI19: 8247 | BJ19: 8938 | BK19: 9220 | BL19: 8584 | BM19: 9430 | BN19: 9671 | BO19: 10410 | BP19: 10360 | BQ19: 10560 | BR19: 9432 | BS19: 11065 | BT19: 11735 | BW19: =$C19 -> Other operated | BY19: =SUM(BZ19:CC19) -> 23415.52 | BZ19: =SUM(G19:I19) -> 23415.52 | CA19: =SUM(J19:L19) -> 0 | CB19: =SUM(M19:O19) -> 0 | CC19: =SUM(P19:R19) -> 0 | CD19: =SUM(CE19:CH19) -> 118008 | CE19: =SUM(Y19:AA19) -> 29502 | CF19: =SUM(AB19:AD19) -> 29502 | CG19: =SUM(AE19:AG19) -> 29502 | CH19: =SUM(AH19:AJ19) -> 29502 | CI19: =SUM(CJ19:CM19) -> 158930.19 | CJ19: =SUM(AQ19:AS19) -> 51673.66 | CK19: =SUM(AT19:AV19) -> 39251.93 | CL19: =SUM(AW19:AY19) -> 39575.91 | CM19: =SUM(AZ19:BB19) -> 28428.69 | CP19: =$C19 -> Other operated | CR19: =E19-W19 -> -94592.48 | CS19: =F19-X19 -> -6086.48 | CT19: =G19-Y19 -> 548 | CU19: =H19-Z19 -> -3617 | CV19: =I19-AA19 -> -3017.48 | CW19: =J19-AB19 -> -9834 | CX19: =K19-AC19 -> -9834 | CY19: =L19-AD19 -> -9834 | ... DE19: =R19-AJ19 -> -9834 | DH19: =$C19 -> Other operated | DJ19: =IFERROR(((E19-W19)/ABS(W19))+1,"") -> 0.19842316 | DK19: =IFERROR(((F19-X19)/ABS(X19))+1,"") -> 0.79369263 | DL19: =IFERROR(((G19-Y19)/ABS(Y19))+1,"") -> 1.055725 | DM19: =IFERROR(((H19-Z19)/ABS(Z19))+1,"") -> 0.63219443 | DN19: =IFERROR(((I19-AA19)/ABS(AA19))+1,"") -> 0.69315843 | DO19: =IFERROR(((J19-AB19)/ABS(AB19))+1,"") -> 0 | DP19: =IFERROR(((K19-AC19)/ABS(AC19))+1,"") -> 0 | DQ19: =IFERROR(((L19-AD19)/ABS(AD19))+1,"") -> 0 | ... DW19: =IFERROR(((R19-AJ19)/ABS(AJ19))+1,"") -> 0
C20: Rent and other | E20: =SUM(G20:R20) -> 0 | F20: =SUMPRODUCT((G$6:R$6<=F$6)*(G20:R20)) -> 0 | G20: ='⑴-6 IS(Others)'!G18 -> 0 | H20: ='⑴-6 IS(Others)'!H18 -> 0 | I20: ='⑴-6 IS(Others)'!I18 -> 0 | J20: ='⑴-6 IS(Others)'!J18 -> 0 | K20: ='⑴-6 IS(Others)'!K18 -> 0 | L20: ='⑴-6 IS(Others)'!L18 -> 0 | M20: ='⑴-6 IS(Others)'!M18 -> 0 | N20: ='⑴-6 IS(Others)'!N18 -> 0 | ... R20: ='⑴-6 IS(Others)'!R18 -> 0 | U20: =$C20 -> Rent and other | W20: =SUM(Y20:AJ20) -> 0 | X20: =SUMPRODUCT((Y$6:AJ$6<=X$6)*(Y20:AJ20)) -> 0 | Y20: ='⑴-6 IS(Others)'!Y18 -> 0 | Z20: ='⑴-6 IS(Others)'!Z18 -> 0 | AA20: ='⑴-6 IS(Others)'!AA18 -> 0 | AB20: ='⑴-6 IS(Others)'!AB18 -> 0 | AC20: ='⑴-6 IS(Others)'!AC18 -> 0 | AD20: ='⑴-6 IS(Others)'!AD18 -> 0 | AE20: ='⑴-6 IS(Others)'!AE18 -> 0 | AF20: ='⑴-6 IS(Others)'!AF18 -> 0 | ... AJ20: ='⑴-6 IS(Others)'!AJ18 -> 0 | AM20: =$C20 -> Rent and other | AO20: =SUM(AQ20:BB20) -> 0 | AP20: =SUMPRODUCT((AQ$6:BB$6<=AP$6)*(AQ20:BB20)) -> 0 | AQ20: ='⑴-6 IS(Others)'!AQ18 -> 0 | AR20: ='⑴-6 IS(Others)'!AR18 -> 0 | AS20: ='⑴-6 IS(Others)'!AS18 -> 0 | AT20: ='⑴-6 IS(Others)'!AT18 -> 0 | AU20: ='⑴-6 IS(Others)'!AU18 -> 0 | AV20: ='⑴-6 IS(Others)'!AV18 -> 0 | AW20: ='⑴-6 IS(Others)'!AW18 -> 0 | AX20: ='⑴-6 IS(Others)'!AX18 -> 0 | ... BB20: ='⑴-6 IS(Others)'!BB18 -> 0 | BE20: =$C20 -> Rent and other | BG20: =SUM(BI20:BT20) -> 0 | BH20: =SUMPRODUCT((BI$6:BT$6<=BH$6)*(BI20:BT20)) -> 0 | BI20: 0 | BJ20: 0 | BK20: 0 | BL20: 0 | BM20: 0 | BN20: 0 | BO20: 0 | BP20: 0 | BQ20: 0 | BR20: 0 | BS20: 0 | BT20: 0 | BW20: =$C20 -> Rent and other | BY20: =SUM(BZ20:CC20) -> 0 | BZ20: =SUM(G20:I20) -> 0 | CA20: =SUM(J20:L20) -> 0 | CB20: =SUM(M20:O20) -> 0 | CC20: =SUM(P20:R20) -> 0 | CD20: =SUM(CE20:CH20) -> 0 | CE20: =SUM(Y20:AA20) -> 0 | CF20: =SUM(AB20:AD20) -> 0 | CG20: =SUM(AE20:AG20) -> 0 | CH20: =SUM(AH20:AJ20) -> 0 | CI20: =SUM(CJ20:CM20) -> 0 | CJ20: =SUM(AQ20:AS20) -> 0 | CK20: =SUM(AT20:AV20) -> 0 | CL20: =SUM(AW20:AY20) -> 0 | CM20: =SUM(AZ20:BB20) -> 0 | CP20: =$C20 -> Rent and other | CR20: =E20-W20 -> 0 | CS20: =F20-X20 -> 0 | CT20: =G20-Y20 -> 0 | CU20: =H20-Z20 -> 0 | CV20: =I20-AA20 -> 0 | CW20: =J20-AB20 -> 0 | CX20: =K20-AC20 -> 0 | CY20: =L20-AD20 -> 0 | ... DE20: =R20-AJ20 -> 0 | DH20: =$C20 -> Rent and other | DJ20: =IFERROR(((E20-W20)/ABS(W20))+1,"") | DK20: =IFERROR(((F20-X20)/ABS(X20))+1,"") | DL20: =IFERROR(((G20-Y20)/ABS(Y20))+1,"") | DM20: =IFERROR(((H20-Z20)/ABS(Z20))+1,"") | DN20: =IFERROR(((I20-AA20)/ABS(AA20))+1,"") | DO20: =IFERROR(((J20-AB20)/ABS(AB20))+1,"") | DP20: =IFERROR(((K20-AC20)/ABS(AC20))+1,"") | DQ20: =IFERROR(((L20-AD20)/ABS(AD20))+1,"") | ... DW20: =IFERROR(((R20-AJ20)/ABS(AJ20))+1,"")
B21: Departmental profit | E21: =SUM(G21:R21) -> 1913024.9 | F21: =SUMPRODUCT((G$6:R$6<=F$6)*(G21:R21)) -> 1913024.9 | G21: =SUM(G22:G27) -> 705358.95 | H21: =SUM(H22:H27) -> 617160.12 | I21: =SUM(I22:I27) -> 590505.84 | J21: =SUM(J22:J27) -> 0 | K21: =SUM(K22:K27) -> 0 | L21: =SUM(L22:L27) -> 0 | M21: =SUM(M22:M27) -> 0 | N21: =SUM(N22:N27) -> 0 | ... R21: =SUM(R22:R27) -> 0 | T21: =$B21 -> Departmental profit | W21: =SUM(Y21:AJ21) -> 11312723 | X21: =SUMPRODUCT((Y$6:AJ$6<=X$6)*(Y21:AJ21)) -> 2567235.1 | Y21: =SUM(Y22:Y27) -> 802390.72 | Z21: =SUM(Z22:Z27) -> 868187.28 | AA21: =SUM(AA22:AA27) -> 896657.13 | AB21: =SUM(AB22:AB27) -> 831759.65 | AC21: =SUM(AC22:AC27) -> 955912.56 | AD21: =SUM(AD22:AD27) -> 1042237 | AE21: =SUM(AE22:AE27) -> 1078486.6 | AF21: =SUM(AF22:AF27) -> 950990.01 | ... AJ21: =SUM(AJ22:AJ27) -> 1009557 | AL21: =$B21 -> Departmental profit | AO21: =SUM(AQ21:BB21) -> 9878162.7 | AP21: =SUMPRODUCT((AQ$6:BB$6<=AP$6)*(AQ21:BB21)) -> 2517780.8 | AQ21: =SUM(AQ22:AQ27) -> 926032.23 | AR21: =SUM(AR22:AR27) -> 776111.59 | AS21: =SUM(AS22:AS27) -> 815636.97 | AT21: =SUM(AT22:AT27) -> 840920.02 | AU21: =SUM(AU22:AU27) -> 915447.13 | AV21: =SUM(AV22:AV27) -> 912113.02 | AW21: =SUM(AW22:AW27) -> 1017318.2 | AX21: =SUM(AX22:AX27) -> 880764.27 | ... BB21: =SUM(BB22:BB27) -> 790767.65 | BD21: =$B21 -> Departmental profit | BG21: =SUM(BI21:BT21) -> 10668020 | BH21: =SUMPRODUCT((BI$6:BT$6<=BH$6)*(BI21:BT21)) -> 2740577 | BI21: =SUM(BI22:BI27) -> 950281 | BJ21: =SUM(BJ22:BJ27) -> 930172 | BK21: =SUM(BK22:BK27) -> 860124 | BL21: =SUM(BL22:BL27) -> 793789 | BM21: =SUM(BM22:BM27) -> 885609 | BN21: =SUM(BN22:BN27) -> 973193 | BO21: =SUM(BO22:BO27) -> 1139526 | BP21: =SUM(BP22:BP27) -> 931210 | ... BT21: =SUM(BT22:BT27) -> 974862.72 | BV21: =$B21 -> Departmental profit | BY21: =SUM(BZ21:CC21) -> 1913024.9 | BZ21: =BZ7-BZ14 -> 1913024.9 | CA21: =CA7-CA14 -> 0 | CB21: =CB7-CB14 -> 0 | CC21: =CC7-CC14 -> 0 | CD21: =SUM(CE21:CH21) -> 11312723 | CE21: =CE7-CE14 -> 2567235.1 | CF21: =CF7-CF14 -> 2829909.2 | CG21: =CG7-CG14 -> 3014637.9 | CH21: =CH7-CH14 -> 2900940.3 | CI21: =SUM(CJ21:CM21) -> 9878162.7 | CJ21: =CJ7-CJ14 -> 2517780.8 | CK21: =CK7-CK14 -> 2668480.2 | CL21: =CL7-CL14 -> 2658795.1 | CM21: =CM7-CM14 -> 2033106.6 | CO21: =$B21 -> Departmental profit | CR21: =E21-W21 -> -9399697.7 | CS21: =F21-X21 -> -654210.22 | CT21: =G21-Y21 -> -97031.769 | CU21: =H21-Z21 -> -251027.16 | CV21: =I21-AA21 -> -306151.29 | CW21: =J21-AB21 -> -831759.65 | CX21: =K21-AC21 -> -955912.56 | CY21: =L21-AD21 -> -1042237 | ... DE21: =R21-AJ21 -> -1009557 | DG21: =$B21 -> Departmental profit | DJ21: =IFERROR(((E21-W21)/ABS(W21))+1,"") -> 0.16910385 | DK21: =IFERROR(((F21-X21)/ABS(X21))+1,"") -> 0.74516934 | DL21: =IFERROR(((G21-Y21)/ABS(Y21))+1,"") -> 0.87907167 | DM21: =IFERROR(((H21-Z21)/ABS(Z21))+1,"") -> 0.71086059 | DN21: =IFERROR(((I21-AA21)/ABS(AA21))+1,"") -> 0.6585637 | DO21: =IFERROR(((J21-AB21)/ABS(AB21))+1,"") -> 0 | DP21: =IFERROR(((K21-AC21)/ABS(AC21))+1,"") -> 0 | DQ21: =IFERROR(((L21-AD21)/ABS(AD21))+1,"") -> 0 | ... DW21: =IFERROR(((R21-AJ21)/ABS(AJ21))+1,"") -> 0
C22: Rooms | E22: =SUM(G22:R22) -> 1220772.8 | F22: =SUMPRODUCT((G$6:R$6<=F$6)*(G22:R22)) -> 1220772.8 | G22: =G8-G15 -> 458023 | H22: =H8-H15 -> 388128.12 | I22: =I8-I15 -> 374621.63 | J22: =J8-J15 -> 0 | K22: =K8-K15 -> 0 | L22: =L8-L15 -> 0 | M22: =M8-M15 -> 0 | N22: =N8-N15 -> 0 | ... R22: =R8-R15 -> 0 | U22: =$C22 -> Rooms | W22: =SUM(Y22:AJ22) -> 7927277 | X22: =SUMPRODUCT((Y$6:AJ$6<=X$6)*(Y22:AJ22)) -> 1752311.4 | Y22: =Y8-Y15 -> 521792.89 | Z22: =Z8-Z15 -> 610410.43 | AA22: =AA8-AA15 -> 620108.06 | AB22: =AB8-AB15 -> 544920.78 | AC22: =AC8-AC15 -> 663367.73 | AD22: =AD8-AD15 -> 716559.78 | AE22: =AE8-AE15 -> 781548.73 | AF22: =AF8-AF15 -> 674233.73 | ... AJ22: =AJ8-AJ15 -> 775835.04 | AM22: =$C22 -> Rooms | AO22: =SUM(AQ22:BB22) -> 7024727.4 | AP22: =SUMPRODUCT((AQ$6:BB$6<=AP$6)*(AQ22:BB22)) -> 1848240 | AQ22: =AQ8-AQ15 -> 639654.39 | AR22: =AR8-AR15 -> 589479.74 | AS22: =AS8-AS15 -> 619105.85 | AT22: =AT8-AT15 -> 621910.41 | AU22: =AU8-AU15 -> 601348.37 | AV22: =AV8-AV15 -> 678636.1 | AW22: =AW8-AW15 -> 756722.37 | AX22: =AX8-AX15 -> 663151.22 | ... BB22: =BB8-BB15 -> 530333.53 | BE22: =$C22 -> Rooms | BG22: =SUM(BI22:BT22) -> 8167262 | BH22: =SUMPRODUCT((BI$6:BT$6<=BH$6)*(BI22:BT22)) -> 2160149 | BI22: =BI8-BI15 -> 756754 | BJ22: =BJ8-BJ15 -> 748183 | BK22: =BK8-BK15 -> 655212 | BL22: =BL8-BL15 -> 581551 | BM22: =BM8-BM15 -> 691849 | BN22: =BN8-BN15 -> 781768 | BO22: =BO8-BO15 -> 920834 | BP22: =BP8-BP15 -> 714842 | ... BT22: =BT8-BT15 -> 708732.72 | BW22: =$C22 -> Rooms | BY22: =SUM(BZ22:CC22) -> 1220772.8 | BZ22: =BZ8-BZ15 -> 1220772.8 | CA22: =CA8-CA15 -> 0 | CB22: =CB8-CB15 -> 0 | CC22: =CC8-CC15 -> 0 | CD22: =SUM(CE22:CH22) -> 7927277 | CE22: =CE8-CE15 -> 1752311.4 | CF22: =CF8-CF15 -> 1924848.3 | CG22: =CG8-CG15 -> 2166926.2 | CH22: =CH8-CH15 -> 2083191.1 | CI22: =SUM(CJ22:CM22) -> 7024727.4 | CJ22: =CJ8-CJ15 -> 1848240 | CK22: =CK8-CK15 -> 1901894.9 | CL22: =CL8-CL15 -> 1939494.4 | CM22: =CM8-CM15 -> 1335098.1 | CP22: =$C22 -> Rooms | CR22: =E22-W22 -> -6706504.2 | CS22: =F22-X22 -> -531538.62 | CT22: =G22-Y22 -> -63769.886 | CU22: =H22-Z22 -> -222282.31 | CV22: =I22-AA22 -> -245486.43 | CW22: =J22-AB22 -> -544920.78 | CX22: =K22-AC22 -> -663367.73 | CY22: =L22-AD22 -> -716559.78 | ... DE22: =R22-AJ22 -> -775835.04 | DH22: =$C22 -> Rooms | DJ22: =IFERROR(((E22-W22)/ABS(W22))+1,"") -> 0.15399648 | DK22: =IFERROR(((F22-X22)/ABS(X22))+1,"") -> 0.69666428 | DL22: =IFERROR(((G22-Y22)/ABS(Y22))+1,"") -> 0.87778698 | DM22: =IFERROR(((H22-Z22)/ABS(Z22))+1,"") -> 0.63584779 | DN22: =IFERROR(((I22-AA22)/ABS(AA22))+1,"") -> 0.60412314 | DO22: =IFERROR(((J22-AB22)/ABS(AB22))+1,"") -> 0 | DP22: =IFERROR(((K22-AC22)/ABS(AC22))+1,"") -> 0 | DQ22: =IFERROR(((L22-AD22)/ABS(AD22))+1,"") -> 0 | ... DW22: =IFERROR(((R22-AJ22)/ABS(AJ22))+1,"") -> 0
C23: Food and beverage | E23: =SUM(G23:R23) -> -112806.96 | F23: =SUMPRODUCT((G$6:R$6<=F$6)*(G23:R23)) -> -112806.96 | G23: =G9-G16 -> -59379 | H23: =H9-H16 -> -23765 | I23: =I9-I16 -> -29662.96 | J23: =J9-J16 -> 0 | K23: =K9-K16 -> 0 | L23: =L9-L16 -> 0 | M23: =M9-M16 -> 0 | N23: =N9-N16 -> 0 | ... R23: =R9-R16 -> 0 | U23: =$C23 -> Food and beverage | W23: =SUM(Y23:AJ23) -> 43977.606 | X23: =SUMPRODUCT((Y$6:AJ$6<=X$6)*(Y23:AJ23)) -> 4191.7516 | Y23: =Y9-Y16 -> -1834.1675 | Z23: =Z9-Z16 -> 7579.8464 | AA23: =AA9-AA16 -> -1553.9274 | AB23: =AB9-AB16 -> 7684.8709 | AC23: =AC9-AC16 -> 4550.8243 | AD23: =AD9-AD16 -> 6255.215 | AE23: =AE9-AE16 -> 7331.9145 | AF23: =AF9-AF16 -> -3429.7221 | ... AJ23: =AJ9-AJ16 -> -941.02824 | AM23: =$C23 -> Food and beverage | AO23: =SUM(AQ23:BB23) -> -117210.84 | AP23: =SUMPRODUCT((AQ$6:BB$6<=AP$6)*(AQ23:BB23)) -> -19827.982 | AQ23: =AQ9-AQ16 -> 9471.64 | AR23: =AR9-AR16 -> -10964.769 | AS23: =AS9-AS16 -> -18334.853 | AT23: =AT9-AT16 -> -11072.849 | AU23: =AU9-AU16 -> 18151.18 | AV23: =AV9-AV16 -> 1487.28 | AW23: =AW9-AW16 -> 27247.05 | AX23: =AX9-AX16 -> -9726.42 | ... BB23: =BB9-BB16 -> -59019.67 | BE23: =$C23 -> Food and beverage | BG23: =SUM(BI23:BT23) -> 149077 | BH23: =SUMPRODUCT((BI$6:BT$6<=BH$6)*(BI23:BT23)) -> 64012 | BI23: =BI9-BI16 -> 25980 | BJ23: =BJ9-BJ16 -> 18944 | BK23: =BK9-BK16 -> 19088 | BL23: =BL9-BL16 -> 38648 | BM23: =BM9-BM16 -> 7303 | BN23: =BN9-BN16 -> 6823 | BO23: =BO9-BO16 -> 7840 | BP23: =BP9-BP16 -> 8219 | ... BT23: =BT9-BT16 -> -146 | BW23: =$C23 -> Food and beverage | BY23: =SUM(BZ23:CC23) -> -112806.96 | BZ23: =BZ9-BZ16 -> -112806.96 | CA23: =CA9-CA16 -> 0 | CB23: =CB9-CB16 -> 0 | CC23: =CC9-CC16 -> 0 | CD23: =SUM(CE23:CH23) -> 43977.606 | CE23: =CE9-CE16 -> 4191.7516 | CF23: =CF9-CF16 -> 18490.91 | CG23: =CG9-CG16 -> 2094.6782 | CH23: =CH9-CH16 -> 19200.266 | CI23: =SUM(CJ23:CM23) -> -117210.84 | CJ23: =CJ9-CJ16 -> -19827.982 | CK23: =CK9-CK16 -> 8565.6115 | CL23: =CL9-CL16 -> 29686.65 | CM23: =CM9-CM16 -> -135635.12 | CP23: =$C23 -> Food and beverage | CR23: =E23-W23 -> -156784.57 | CS23: =F23-X23 -> -116998.71 | CT23: =G23-Y23 -> -57544.833 | CU23: =H23-Z23 -> -31344.846 | CV23: =I23-AA23 -> -28109.033 | CW23: =J23-AB23 -> -7684.8709 | CX23: =K23-AC23 -> -4550.8243 | CY23: =L23-AD23 -> -6255.215 | ... DE23: =R23-AJ23 -> 941.02824 | DH23: =$C23 -> Food and beverage | DJ23: =IFERROR(((E23-W23)/ABS(W23))+1,"") -> -2.5651001 | DK23: =IFERROR(((F23-X23)/ABS(X23))+1,"") -> -26.911652 | DL23: =IFERROR(((G23-Y23)/ABS(Y23))+1,"") -> -30.373816 | DM23: =IFERROR(((H23-Z23)/ABS(Z23))+1,"") -> -3.1352878 | DN23: =IFERROR(((I23-AA23)/ABS(AA23))+1,"") -> -17.089026 | DO23: =IFERROR(((J23-AB23)/ABS(AB23))+1,"") -> 0 | DP23: =IFERROR(((K23-AC23)/ABS(AC23))+1,"") -> 0 | DQ23: =IFERROR(((L23-AD23)/ABS(AD23))+1,"") -> 0 | ... DW23: =IFERROR(((R23-AJ23)/ABS(AJ23))+1,"") -> 2
C24: Comunications | E24: =SUM(G24:R24) -> -7694.06 | F24: =SUMPRODUCT((G$6:R$6<=F$6)*(G24:R24)) -> -7694.06 | G24: =G10-G17 -> -2041.05 | H24: =H10-H17 -> -2037 | I24: =I10-I17 -> -3616.01 | J24: =J10-J17 -> 0 | K24: =K10-K17 -> 0 | L24: =L10-L17 -> 0 | M24: =M10-M17 -> 0 | N24: =N10-N17 -> 0 | ... R24: =R10-R17 -> 0 | U24: =$C24 -> Comunications | W24: =SUM(Y24:AJ24) -> -10200 | X24: =SUMPRODUCT((Y$6:AJ$6<=X$6)*(Y24:AJ24)) -> -2550 | Y24: =Y10-Y17 -> -850 | Z24: =Z10-Z17 -> -850 | AA24: =AA10-AA17 -> -850 | AB24: =AB10-AB17 -> -850 | AC24: =AC10-AC17 -> -850 | AD24: =AD10-AD17 -> -850 | AE24: =AE10-AE17 -> -850 | AF24: =AF10-AF17 -> -850 | ... AJ24: =AJ10-AJ17 -> -850 | AM24: =$C24 -> Comunications | AO24: =SUM(AQ24:BB24) -> -10990.42 | AP24: =SUMPRODUCT((AQ$6:BB$6<=AP$6)*(AQ24:BB24)) -> -1022.52 | AQ24: =AQ10-AQ17 -> -261.79 | AR24: =AR10-AR17 -> -405.73 | AS24: =AS10-AS17 -> -355 | AT24: =AT10-AT17 -> -552.49 | AU24: =AU10-AU17 -> -600.98 | AV24: =AV10-AV17 -> -549.65 | AW24: =AW10-AW17 -> -1377.55 | AX24: =AX10-AX17 -> -1375.23 | ... BB24: =BB10-BB17 -> -1378 | BE24: =$C24 -> Comunications | BG24: =SUM(BI24:BT24) -> -2043 | BH24: =SUMPRODUCT((BI$6:BT$6<=BH$6)*(BI24:BT24)) -> -45 | BI24: =BI10-BI17 -> 485 | BJ24: =BJ10-BJ17 -> -164 | BK24: =BK10-BK17 -> -366 | BL24: =BL10-BL17 -> -322 | BM24: =BM10-BM17 -> 560 | BN24: =BN10-BN17 -> -357 | BO24: =BO10-BO17 -> -343 | BP24: =BP10-BP17 -> -223 | ... BT24: =BT10-BT17 -> -269 | BW24: =$C24 -> Comunications | BY24: =SUM(BZ24:CC24) -> -7694.06 | BZ24: =BZ10-BZ17 -> -7694.06 | CA24: =CA10-CA17 -> 0 | CB24: =CB10-CB17 -> 0 | CC24: =CC10-CC17 -> 0 | CD24: =SUM(CE24:CH24) -> -10200 | CE24: =CE10-CE17 -> -2550 | CF24: =CF10-CF17 -> -2550 | CG24: =CG10-CG17 -> -2550 | CH24: =CH10-CH17 -> -2550 | CI24: =SUM(CJ24:CM24) -> -10990.42 | CJ24: =CJ10-CJ17 -> -1022.52 | CK24: =CK10-CK17 -> -1703.12 | CL24: =CL10-CL17 -> -4130.78 | CM24: =CM10-CM17 -> -4134 | CP24: =$C24 -> Comunications | CR24: =E24-W24 -> 2505.94 | CS24: =F24-X24 -> -5144.06 | CT24: =G24-Y24 -> -1191.05 | CU24: =H24-Z24 -> -1187 | CV24: =I24-AA24 -> -2766.01 | CW24: =J24-AB24 -> 850 | CX24: =K24-AC24 -> 850 | CY24: =L24-AD24 -> 850 | ... DE24: =R24-AJ24 -> 850 | DH24: =$C24 -> Comunications | DJ24: =IFERROR(((E24-W24)/ABS(W24))+1,"") -> 1.2456804 | DK24: =IFERROR(((F24-X24)/ABS(X24))+1,"") -> -1.0172784 | DL24: =IFERROR(((G24-Y24)/ABS(Y24))+1,"") -> -0.40123529 | DM24: =IFERROR(((H24-Z24)/ABS(Z24))+1,"") -> -0.39647059 | DN24: =IFERROR(((I24-AA24)/ABS(AA24))+1,"") -> -2.2541294 | DO24: =IFERROR(((J24-AB24)/ABS(AB24))+1,"") -> 2 | DP24: =IFERROR(((K24-AC24)/ABS(AC24))+1,"") -> 2 | DQ24: =IFERROR(((L24-AD24)/ABS(AD24))+1,"") -> 2 | ... DW24: =IFERROR(((R24-AJ24)/ABS(AJ24))+1,"") -> 2
C25: Parking | E25: =SUM(G25:R25) -> 177883.01 | F25: =SUMPRODUCT((G$6:R$6<=F$6)*(G25:R25)) -> 177883.01 | G25: =G11-G18 -> 64204 | H25: =H11-H18 -> 51471 | I25: =I11-I18 -> 62208.01 | J25: =J11-J18 -> 0 | K25: =K11-K18 -> 0 | L25: =L11-L18 -> 0 | M25: =M11-M18 -> 0 | N25: =N11-N18 -> 0 | ... R25: =R11-R18 -> 0 | U25: =$C25 -> Parking | W25: =SUM(Y25:AJ25) -> 976214 | X25: =SUMPRODUCT((Y$6:AJ$6<=X$6)*(Y25:AJ25)) -> 234768 | Y25: =Y11-Y18 -> 85368 | Z25: =Z11-Z18 -> 67000 | AA25: =AA11-AA18 -> 82400 | AB25: =AB11-AB18 -> 83184 | AC25: =AC11-AC18 -> 86096 | AD25: =AD11-AD18 -> 86600 | AE25: =AE11-AE18 -> 92200 | AF25: =AF11-AF18 -> 87496 | ... AJ25: =AJ11-AJ18 -> 66762 | AM25: =$C25 -> Parking | AO25: =SUM(AQ25:BB25) -> 944489.61 | AP25: =SUMPRODUCT((AQ$6:BB$6<=AP$6)*(AQ25:BB25)) -> 211825.31 | AQ25: =AQ11-AQ18 -> 81862.54 | AR25: =AR11-AR18 -> 65661.57 | AS25: =AS11-AS18 -> 64301.2 | AT25: =AT11-AT18 -> 60137.47 | AU25: =AU11-AU18 -> 145880.28 | AV25: =AV11-AV18 -> 81213.36 | AW25: =AW11-AW18 -> 88077.57 | AX25: =AX11-AX18 -> 79978.93 | ... BB25: =BB11-BB18 -> 75157.47 | BE25: =$C25 -> Parking | BG25: =SUM(BI25:BT25) -> 810280 | BH25: =SUMPRODUCT((BI$6:BT$6<=BH$6)*(BI25:BT25)) -> 200714 | BI25: =BI11-BI18 -> 70936 | BJ25: =BJ11-BJ18 -> 59772 | BK25: =BK11-BK18 -> 70006 | BL25: =BL11-BL18 -> 66798 | BM25: =BM11-BM18 -> 66558 | BN25: =BN11-BN18 -> 66183 | BO25: =BO11-BO18 -> 77498 | BP25: =BP11-BP18 -> 75236 | ... BT25: =BT11-BT18 -> 71838 | BW25: =$C25 -> Parking | BY25: =SUM(BZ25:CC25) -> 177883.01 | BZ25: =BZ11-BZ18 -> 177883.01 | CA25: =CA11-CA18 -> 0 | CB25: =CB11-CB18 -> 0 | CC25: =CC11-CC18 -> 0 | CD25: =SUM(CE25:CH25) -> 976214 | CE25: =CE11-CE18 -> 234768 | CF25: =CF11-CF18 -> 255880 | CG25: =CG11-CG18 -> 257504 | CH25: =CH11-CH18 -> 228062 | CI25: =SUM(CJ25:CM25) -> 944489.61 | CJ25: =CJ11-CJ18 -> 211825.31 | CK25: =CK11-CK18 -> 287231.11 | CL25: =CL11-CL18 -> 240250.1 | CM25: =CM11-CM18 -> 205183.09 | CP25: =$C25 -> Parking | CR25: =E25-W25 -> -798330.99 | CS25: =F25-X25 -> -56884.99 | CT25: =G25-Y25 -> -21164 | CU25: =H25-Z25 -> -15529 | CV25: =I25-AA25 -> -20191.99 | CW25: =J25-AB25 -> -83184 | CX25: =K25-AC25 -> -86096 | CY25: =L25-AD25 -> -86600 | ... DE25: =R25-AJ25 -> -66762 | DH25: =$C25 -> Parking | DJ25: =IFERROR(((E25-W25)/ABS(W25))+1,"") -> 0.18221723 | DK25: =IFERROR(((F25-X25)/ABS(X25))+1,"") -> 0.757697 | DL25: =IFERROR(((G25-Y25)/ABS(Y25))+1,"") -> 0.75208509 | DM25: =IFERROR(((H25-Z25)/ABS(Z25))+1,"") -> 0.76822388 | DN25: =IFERROR(((I25-AA25)/ABS(AA25))+1,"") -> 0.75495158 | DO25: =IFERROR(((J25-AB25)/ABS(AB25))+1,"") -> 0 | DP25: =IFERROR(((K25-AC25)/ABS(AC25))+1,"") -> 0 | DQ25: =IFERROR(((L25-AD25)/ABS(AD25))+1,"") -> 0 | ... DW25: =IFERROR(((R25-AJ25)/ABS(AJ25))+1,"") -> 0
C26: Other operated | E26: =SUM(G26:R26) -> 475960.49 | F26: =SUMPRODUCT((G$6:R$6<=F$6)*(G26:R26)) -> 475960.49 | G26: =G12-G19 -> 188700 | H26: =H12-H19 -> 149971 | I26: =I12-I19 -> 137289.49 | J26: =J12-J19 -> 0 | K26: =K12-K19 -> 0 | L26: =L12-L19 -> 0 | M26: =M12-M19 -> 0 | N26: =N12-N19 -> 0 | ... R26: =R12-R19 -> 0 | U26: =$C26 -> Other operated | W26: =SUM(Y26:AJ26) -> 1751454 | X26: =SUMPRODUCT((Y$6:AJ$6<=X$6)*(Y26:AJ26)) -> 422514 | Y26: =Y12-Y19 -> 145914 | Z26: =Z12-Z19 -> 132047 | AA26: =AA12-AA19 -> 144553 | AB26: =AB12-AB19 -> 144820 | AC26: =AC12-AC19 -> 150748 | AD26: =AD12-AD19 -> 181672 | AE26: =AE12-AE19 -> 146256 | AF26: =AF12-AF19 -> 141540 | ... AJ26: =AJ12-AJ19 -> 116751 | AM26: =$C26 -> Other operated | AO26: =SUM(AQ26:BB26) -> 1398305.1 | AP26: =SUMPRODUCT((AQ$6:BB$6<=AP$6)*(AQ26:BB26)) -> 328419.46 | AQ26: =AQ12-AQ19 -> 145429.54 | AR26: =AR12-AR19 -> 80993.44 | AS26: =AS12-AS19 -> 101996.48 | AT26: =AT12-AT19 -> 120740.32 | AU26: =AU12-AU19 -> 98378.92 | AV26: =AV12-AV19 -> 96906.61 | AW26: =AW12-AW19 -> 90353.85 | AX26: =AX12-AX19 -> 92487.38 | ... BB26: =BB12-BB19 -> 193314.33 | BE26: =$C26 -> Other operated | BG26: =SUM(BI26:BT26) -> 1096194 | BH26: =SUMPRODUCT((BI$6:BT$6<=BH$6)*(BI26:BT26)) -> 223704 | BI26: =BI12-BI19 -> 66060 | BJ26: =BJ12-BJ19 -> 73339 | BK26: =BK12-BK19 -> 84305 | BL26: =BL12-BL19 -> 75009 | BM26: =BM12-BM19 -> 87378 | BN26: =BN12-BN19 -> 86303 | BO26: =BO12-BO19 -> 101673 | BP26: =BP12-BP19 -> 100928 | ... BT26: =BT12-BT19 -> 121013 | BW26: =$C26 -> Other operated | BY26: =SUM(BZ26:CC26) -> 475960.49 | BZ26: =BZ12-BZ19 -> 475960.49 | CA26: =CA12-CA19 -> 0 | CB26: =CB12-CB19 -> 0 | CC26: =CC12-CC19 -> 0 | CD26: =SUM(CE26:CH26) -> 1751454 | CE26: =CE12-CE19 -> 422514 | CF26: =CF12-CF19 -> 477240 | CG26: =CG12-CG19 -> 434663 | CH26: =CH12-CH19 -> 417037 | CI26: =SUM(CJ26:CM26) -> 1398305.1 | CJ26: =CJ12-CJ19 -> 328419.46 | CK26: =CK12-CK19 -> 316025.85 | CL26: =CL12-CL19 -> 285992 | CM26: =CM12-CM19 -> 467867.83 | CP26: =$C26 -> Other operated | CR26: =E26-W26 -> -1275493.5 | CS26: =F26-X26 -> 53446.49 | CT26: =G26-Y26 -> 42786 | CU26: =H26-Z26 -> 17924 | CV26: =I26-AA26 -> -7263.51 | CW26: =J26-AB26 -> -144820 | CX26: =K26-AC26 -> -150748 | CY26: =L26-AD26 -> -181672 | ... DE26: =R26-AJ26 -> -116751 | DH26: =$C26 -> Other operated | DJ26: =IFERROR(((E26-W26)/ABS(W26))+1,"") -> 0.27175164 | DK26: =IFERROR(((F26-X26)/ABS(X26))+1,"") -> 1.1264964 | DL26: =IFERROR(((G26-Y26)/ABS(Y26))+1,"") -> 1.2932275 | DM26: =IFERROR(((H26-Z26)/ABS(Z26))+1,"") -> 1.1357395 | DN26: =IFERROR(((I26-AA26)/ABS(AA26))+1,"") -> 0.94975192 | DO26: =IFERROR(((J26-AB26)/ABS(AB26))+1,"") -> 0 | DP26: =IFERROR(((K26-AC26)/ABS(AC26))+1,"") -> 0 | DQ26: =IFERROR(((L26-AD26)/ABS(AD26))+1,"") -> 0 | ... DW26: =IFERROR(((R26-AJ26)/ABS(AJ26))+1,"") -> 0
C27: Rent and other | E27: =SUM(G27:R27) -> 158909.68 | F27: =SUMPRODUCT((G$6:R$6<=F$6)*(G27:R27)) -> 158909.68 | G27: =G13-G20 -> 55852 | H27: =H13-H20 -> 53392 | I27: =I13-I20 -> 49665.68 | J27: =J13-J20 -> 0 | K27: =K13-K20 -> 0 | L27: =L13-L20 -> 0 | M27: =M13-M20 -> 0 | N27: =N13-N20 -> 0 | ... R27: =R13-R20 -> 0 | U27: =$C27 -> Rent and other | W27: =SUM(Y27:AJ27) -> 624000 | X27: =SUMPRODUCT((Y$6:AJ$6<=X$6)*(Y27:AJ27)) -> 156000 | Y27: =Y13-Y20 -> 52000 | Z27: =Z13-Z20 -> 52000 | AA27: =AA13-AA20 -> 52000 | AB27: =AB13-AB20 -> 52000 | AC27: =AC13-AC20 -> 52000 | AD27: =AD13-AD20 -> 52000 | AE27: =AE13-AE20 -> 52000 | AF27: =AF13-AF20 -> 52000 | ... AJ27: =AJ13-AJ20 -> 52000 | AM27: =$C27 -> Rent and other | AO27: =SUM(AQ27:BB27) -> 638841.85 | AP27: =SUMPRODUCT((AQ$6:BB$6<=AP$6)*(AQ27:BB27)) -> 150146.53 | AQ27: =AQ13-AQ20 -> 49875.91 | AR27: =AR13-AR20 -> 51347.33 | AS27: =AS13-AS20 -> 48923.29 | AT27: =AT13-AT20 -> 49757.16 | AU27: =AU13-AU20 -> 52289.36 | AV27: =AV13-AV20 -> 54419.32 | AW27: =AW13-AW20 -> 56294.94 | AX27: =AX13-AX20 -> 56248.39 | ... BB27: =BB13-BB20 -> 52359.99 | BE27: =$C27 -> Rent and other | BG27: =SUM(BI27:BT27) -> 447250 | BH27: =SUMPRODUCT((BI$6:BT$6<=BH$6)*(BI27:BT27)) -> 92043 | BI27: =BI13-BI20 -> 30066 | BJ27: =BJ13-BJ20 -> 30098 | BK27: =BK13-BK20 -> 31879 | BL27: =BL13-BL20 -> 32105 | BM27: =BM13-BM20 -> 31961 | BN27: =BN13-BN20 -> 32473 | BO27: =BO13-BO20 -> 32024 | BP27: =BP13-BP20 -> 32208 | ... BT27: =BT13-BT20 -> 73694 | BW27: =$C27 -> Rent and other | BY27: =SUM(BZ27:CC27) -> 158909.68 | BZ27: =BZ13-BZ20 -> 158909.68 | CA27: =CA13-CA20 -> 0 | CB27: =CB13-CB20 -> 0 | CC27: =CC13-CC20 -> 0 | CD27: =SUM(CE27:CH27) -> 624000 | CE27: =CE13-CE20 -> 156000 | CF27: =CF13-CF20 -> 156000 | CG27: =CG13-CG20 -> 156000 | CH27: =CH13-CH20 -> 156000 | CI27: =SUM(CJ27:CM27) -> 638841.85 | CJ27: =CJ13-CJ20 -> 150146.53 | CK27: =CK13-CK20 -> 156465.84 | CL27: =CL13-CL20 -> 167502.7 | CM27: =CM13-CM20 -> 164726.78 | CP27: =$C27 -> Rent and other | CR27: =E27-W27 -> -465090.32 | CS27: =F27-X27 -> 2909.68 | CT27: =G27-Y27 -> 3852 | CU27: =H27-Z27 -> 1392 | CV27: =I27-AA27 -> -2334.32 | CW27: =J27-AB27 -> -52000 | CX27: =K27-AC27 -> -52000 | CY27: =L27-AD27 -> -52000 | ... DE27: =R27-AJ27 -> -52000 | DH27: =$C27 -> Rent and other | DJ27: =IFERROR(((E27-W27)/ABS(W27))+1,"") -> 0.25466295 | DK27: =IFERROR(((F27-X27)/ABS(X27))+1,"") -> 1.0186518 | DL27: =IFERROR(((G27-Y27)/ABS(Y27))+1,"") -> 1.0740769 | DM27: =IFERROR(((H27-Z27)/ABS(Z27))+1,"") -> 1.0267692 | DN27: =IFERROR(((I27-AA27)/ABS(AA27))+1,"") -> 0.95510923 | DO27: =IFERROR(((J27-AB27)/ABS(AB27))+1,"") -> 0 | DP27: =IFERROR(((K27-AC27)/ABS(AC27))+1,"") -> 0 | DQ27: =IFERROR(((L27-AD27)/ABS(AD27))+1,"") -> 0 | ... DW27: =IFERROR(((R27-AJ27)/ABS(AJ27))+1,"") -> 0
B28: Undistributed expenses | E28: =SUM(G28:R28) -> 1417888.2 | F28: =SUMPRODUCT((G$6:R$6<=F$6)*(G28:R28)) -> 1417888.2 | G28: =SUM(G29:G32) -> 467093 | H28: =SUM(H29:H32) -> 474827 | I28: =SUM(I29:I32) -> 475968.18 | J28: =SUM(J29:J32) -> 0 | K28: =SUM(K29:K32) -> 0 | L28: =SUM(L29:L32) -> 0 | M28: =SUM(M29:M32) -> 0 | N28: =SUM(N29:N32) -> 0 | ... R28: =SUM(R29:R32) -> 0 | T28: =$B28 -> Undistributed expenses | W28: =SUM(Y28:AJ28) -> 5682055.7 | X28: =SUMPRODUCT((Y$6:AJ$6<=X$6)*(Y28:AJ28)) -> 1446984 | Y28: =SUM(Y29:Y32) -> 462111.34 | Z28: =SUM(Z29:Z32) -> 460698.49 | AA28: =SUM(AA29:AA32) -> 524174.14 | AB28: =SUM(AB29:AB32) -> 468256.78 | AC28: =SUM(AC29:AC32) -> 467061.33 | AD28: =SUM(AD29:AD32) -> 478344.78 | AE28: =SUM(AE29:AE32) -> 467378.33 | AF28: =SUM(AF29:AF32) -> 473963.32 | ... AJ28: =SUM(AJ29:AJ32) -> 473477.3 | AL28: =$B28 -> Undistributed expenses | AO28: =SUM(AQ28:BB28) -> 5153609.6 | AP28: =SUMPRODUCT((AQ$6:BB$6<=AP$6)*(AQ28:BB28)) -> 1245068.3 | AQ28: =SUM(AQ29:AQ32) -> 308666.13 | AR28: =SUM(AR29:AR32) -> 485450.85 | AS28: =SUM(AS29:AS32) -> 450951.29 | AT28: =SUM(AT29:AT32) -> 415518.02 | AU28: =SUM(AU29:AU32) -> 458173.72 | AV28: =SUM(AV29:AV32) -> 401268.23 | AW28: =SUM(AW29:AW32) -> 388698.08 | AX28: =SUM(AX29:AX32) -> 426808.3 | ... BB28: =SUM(BB29:BB32) -> 553089.18 | BD28: =$B28 -> Undistributed expenses | BG28: =SUM(BI28:BT28) -> 4933344 | BH28: =SUMPRODUCT((BI$6:BT$6<=BH$6)*(BI28:BT28)) -> 1188806 | BI28: =SUM(BI29:BI32) -> 393917 | BJ28: =SUM(BJ29:BJ32) -> 377946 | BK28: =SUM(BK29:BK32) -> 416943 | BL28: =SUM(BL29:BL32) -> 429864 | BM28: =SUM(BM29:BM32) -> 410930 | BN28: =SUM(BN29:BN32) -> 415984 | BO28: =SUM(BO29:BO32) -> 403490 | BP28: =SUM(BP29:BP32) -> 377909 | ... BT28: =SUM(BT29:BT32) -> 466167 | BV28: =$B28 -> Undistributed expenses | BY28: =SUM(BZ28:CC28) -> 1417888.2 | BZ28: =SUM(BZ29:BZ32) -> 1417888.2 | CA28: =SUM(CA29:CA32) -> 0 | CB28: =SUM(CB29:CB32) -> 0 | CC28: =SUM(CC29:CC32) -> 0 | CD28: =SUM(CE28:CH28) -> 5682055.7 | CE28: =SUM(CE29:CE32) -> 1446984 | CF28: =SUM(CF29:CF32) -> 1413662.9 | CG28: =SUM(CG29:CG32) -> 1412784.3 | CH28: =SUM(CH29:CH32) -> 1408624.5 | CI28: =SUM(CJ28:CM28) -> 5153609.6 | CJ28: =SUM(CJ29:CJ32) -> 1245068.3 | CK28: =SUM(CK29:CK32) -> 1274960 | CL28: =SUM(CL29:CL32) -> 1212127.4 | CM28: =SUM(CM29:CM32) -> 1421454 | CO28: =$B28 -> Undistributed expenses | CR28: =E28-W28 -> -4264167.5 | CS28: =F28-X28 -> -29095.787 | CT28: =G28-Y28 -> 4981.6648 | CU28: =H28-Z28 -> 14128.511 | CV28: =I28-AA28 -> -48205.963 | CW28: =J28-AB28 -> -468256.78 | CX28: =K28-AC28 -> -467061.33 | CY28: =L28-AD28 -> -478344.78 | ... DE28: =R28-AJ28 -> -473477.3 | DG28: =$B28 -> Undistributed expenses | DJ28: =IFERROR(((E28-W28)/ABS(W28))+1,"") -> 0.24953789 | DK28: =IFERROR(((F28-X28)/ABS(X28))+1,"") -> 0.97989211 | DL28: =IFERROR(((G28-Y28)/ABS(Y28))+1,"") -> 1.0107802 | DM28: =IFERROR(((H28-Z28)/ABS(Z28))+1,"") -> 1.0306676 | DN28: =IFERROR(((I28-AA28)/ABS(AA28))+1,"") -> 0.90803445 | DO28: =IFERROR(((J28-AB28)/ABS(AB28))+1,"") -> 0 | DP28: =IFERROR(((K28-AC28)/ABS(AC28))+1,"") -> 0 | DQ28: =IFERROR(((L28-AD28)/ABS(AD28))+1,"") -> 0 | ... DW28: =IFERROR(((R28-AJ28)/ABS(AJ28))+1,"") -> 0
C29: Admin. And General | E29: =SUM(G29:R29) -> 758938.02 | F29: =SUMPRODUCT((G$6:R$6<=F$6)*(G29:R29)) -> 758938.02 | G29: ='⑵-1 IS(A&G)'!G18 -> 240989 | H29: ='⑵-1 IS(A&G)'!H18 -> 268532 | I29: ='⑵-1 IS(A&G)'!I18 -> 249417.02 | J29: ='⑵-1 IS(A&G)'!J18 -> 0 | K29: ='⑵-1 IS(A&G)'!K18 -> 0 | L29: ='⑵-1 IS(A&G)'!L18 -> 0 | M29: ='⑵-1 IS(A&G)'!M18 -> 0 | N29: ='⑵-1 IS(A&G)'!N18 -> 0 | ... R29: ='⑵-1 IS(A&G)'!R18 -> 0 | U29: =$C29 -> Admin. And General | W29: =SUM(Y29:AJ29) -> 2578223.9 | X29: =SUMPRODUCT((Y$6:AJ$6<=X$6)*(Y29:AJ29)) -> 651237.53 | Y29: ='⑵-1 IS(A&G)'!Y18 -> 205920.27 | Z29: ='⑵-1 IS(A&G)'!Z18 -> 200182.89 | AA29: ='⑵-1 IS(A&G)'!AA18 -> 245134.37 | AB29: ='⑵-1 IS(A&G)'!AB18 -> 204748.21 | AC29: ='⑵-1 IS(A&G)'!AC18 -> 216634.06 | AD29: ='⑵-1 IS(A&G)'!AD18 -> 220596.21 | AE29: ='⑵-1 IS(A&G)'!AE18 -> 215742.06 | AF29: ='⑵-1 IS(A&G)'!AF18 -> 217636.05 | ... AJ29: ='⑵-1 IS(A&G)'!AJ18 -> 215765.54 | AM29: =$C29 -> Admin. And General | AO29: =SUM(AQ29:BB29) -> 2354111.3 | AP29: =SUMPRODUCT((AQ$6:BB$6<=AP$6)*(AQ29:BB29)) -> 569845.1 | AQ29: ='⑵-1 IS(A&G)'!AQ18 -> 98665.38 | AR29: ='⑵-1 IS(A&G)'!AR18 -> 270265.52 | AS29: ='⑵-1 IS(A&G)'!AS18 -> 200914.2 | AT29: ='⑵-1 IS(A&G)'!AT18 -> 176469.56 | AU29: ='⑵-1 IS(A&G)'!AU18 -> 228314.05 | AV29: ='⑵-1 IS(A&G)'!AV18 -> 165987.33 | AW29: ='⑵-1 IS(A&G)'!AW18 -> 158767.13 | AX29: ='⑵-1 IS(A&G)'!AX18 -> 184808.06 | ... BB29: ='⑵-1 IS(A&G)'!BB18 -> 283505.17 | BE29: =$C29 -> Admin. And General | BG29: =SUM(BI29:BT29) -> 1993259 | BH29: =SUMPRODUCT((BI$6:BT$6<=BH$6)*(BI29:BT29)) -> 470557 | BI29: 144469 | BJ29: 149186 | BK29: 176902 | BL29: 187603 | BM29: 171189 | BN29: 174723 | BO29: 176444 | BP29: 131046 | BQ29: 181151 | BR29: 149619 | BS29: 140136 | BT29: 210791 | BW29: =$C29 -> Admin. And General | BY29: =SUM(BZ29:CC29) -> 758938.02 | BZ29: =SUM(G29:I29) -> 758938.02 | CA29: =SUM(J29:L29) -> 0 | CB29: =SUM(M29:O29) -> 0 | CC29: =SUM(P29:R29) -> 0 | CD29: =SUM(CE29:CH29) -> 2578223.9 | CE29: =SUM(Y29:AA29) -> 651237.53 | CF29: =SUM(AB29:AD29) -> 641978.48 | CG29: =SUM(AE29:AG29) -> 644436.23 | CH29: =SUM(AH29:AJ29) -> 640571.64 | CI29: =SUM(CJ29:CM29) -> 2354111.3 | CJ29: =SUM(AQ29:AS29) -> 569845.1 | CK29: =SUM(AT29:AV29) -> 570770.94 | CL29: =SUM(AW29:AY29) -> 502670.93 | CM29: =SUM(AZ29:BB29) -> 710824.38 | CP29: =$C29 -> Admin. And General | CR29: =E29-W29 -> -1819285.9 | CS29: =F29-X29 -> 107700.49 | CT29: =G29-Y29 -> 35068.728 | CU29: =H29-Z29 -> 68349.11 | CV29: =I29-AA29 -> 4282.653 | CW29: =J29-AB29 -> -204748.21 | CX29: =K29-AC29 -> -216634.06 | CY29: =L29-AD29 -> -220596.21 | ... DE29: =R29-AJ29 -> -215765.54 | DH29: =$C29 -> Admin. And General | DJ29: =IFERROR(((E29-W29)/ABS(W29))+1,"") -> 0.29436467 | DK29: =IFERROR(((F29-X29)/ABS(X29))+1,"") -> 1.1653782 | DL29: =IFERROR(((G29-Y29)/ABS(Y29))+1,"") -> 1.1703025 | DM29: =IFERROR(((H29-Z29)/ABS(Z29))+1,"") -> 1.3414333 | DN29: =IFERROR(((I29-AA29)/ABS(AA29))+1,"") -> 1.0174706 | DO29: =IFERROR(((J29-AB29)/ABS(AB29))+1,"") -> 0 | DP29: =IFERROR(((K29-AC29)/ABS(AC29))+1,"") -> 0 | DQ29: =IFERROR(((L29-AD29)/ABS(AD29))+1,"") -> 0 | ... DW29: =IFERROR(((R29-AJ29)/ABS(AJ29))+1,"") -> 0
C30: Sales and marketing | E30: =SUM(G30:R30) -> 96688.46 | F30: =SUMPRODUCT((G$6:R$6<=F$6)*(G30:R30)) -> 96688.46 | G30: ='⑵-2 IS(S&M)'!G18 -> 36855 | H30: ='⑵-2 IS(S&M)'!H18 -> 29481 | I30: ='⑵-2 IS(S&M)'!I18 -> 30352.46 | J30: ='⑵-2 IS(S&M)'!J18 -> 0 | K30: ='⑵-2 IS(S&M)'!K18 -> 0 | L30: ='⑵-2 IS(S&M)'!L18 -> 0 | M30: ='⑵-2 IS(S&M)'!M18 -> 0 | N30: ='⑵-2 IS(S&M)'!N18 -> 0 | ... R30: ='⑵-2 IS(S&M)'!R18 -> 0 | U30: =$C30 -> Sales and marketing | W30: =SUM(Y30:AJ30) -> 656677.48 | X30: =SUMPRODUCT((Y$6:AJ$6<=X$6)*(Y30:AJ30)) -> 184632.73 | Y30: ='⑵-2 IS(S&M)'!Y18 -> 55796.468 | Z30: ='⑵-2 IS(S&M)'!Z18 -> 66276.835 | AA30: ='⑵-2 IS(S&M)'!AA18 -> 62559.426 | AB30: ='⑵-2 IS(S&M)'!AB18 -> 64652.751 | AC30: ='⑵-2 IS(S&M)'!AC18 -> 48002.751 | AD30: ='⑵-2 IS(S&M)'!AD18 -> 49302.751 | AE30: ='⑵-2 IS(S&M)'!AE18 -> 52402.751 | AF30: ='⑵-2 IS(S&M)'!AF18 -> 55102.751 | ... AJ30: ='⑵-2 IS(S&M)'!AJ18 -> 51152.751 | AM30: =$C30 -> Sales and marketing | AO30: =SUM(AQ30:BB30) -> 473567.47 | AP30: =SUMPRODUCT((AQ$6:BB$6<=AP$6)*(AQ30:BB30)) -> 108328.72 | AQ30: ='⑵-2 IS(S&M)'!AQ18 -> 31487.88 | AR30: ='⑵-2 IS(S&M)'!AR18 -> 36632.958 | AS30: ='⑵-2 IS(S&M)'!AS18 -> 40207.879 | AT30: ='⑵-2 IS(S&M)'!AT18 -> 44828.438 | AU30: ='⑵-2 IS(S&M)'!AU18 -> 43954.21 | AV30: ='⑵-2 IS(S&M)'!AV18 -> 41838.59 | AW30: ='⑵-2 IS(S&M)'!AW18 -> 34642.89 | AX30: ='⑵-2 IS(S&M)'!AX18 -> 45406.02 | ... BB30: ='⑵-2 IS(S&M)'!BB18 -> 47361.38 | BE30: =$C30 -> Sales and marketing | BG30: =SUM(BI30:BT30) -> 520047 | BH30: =SUMPRODUCT((BI$6:BT$6<=BH$6)*(BI30:BT30)) -> 110613 | BI30: 38986 | BJ30: 35904 | BK30: 35723 | BL30: 39253 | BM30: 35185 | BN30: 41021 | BO30: 39995 | BP30: 48638 | BQ30: 60562 | BR30: 44091 | BS30: 49310 | BT30: 51379 | BW30: =$C30 -> Sales and marketing | BY30: =SUM(BZ30:CC30) -> 96688.46 | BZ30: =SUM(G30:I30) -> 96688.46 | CA30: =SUM(J30:L30) -> 0 | CB30: =SUM(M30:O30) -> 0 | CC30: =SUM(P30:R30) -> 0 | CD30: =SUM(CE30:CH30) -> 656677.48 | CE30: =SUM(Y30:AA30) -> 184632.73 | CF30: =SUM(AB30:AD30) -> 161958.25 | CG30: =SUM(AE30:AG30) -> 158158.25 | CH30: =SUM(AH30:AJ30) -> 151928.25 | CI30: =SUM(CJ30:CM30) -> 473567.47 | CJ30: =SUM(AQ30:AS30) -> 108328.72 | CK30: =SUM(AT30:AV30) -> 130621.24 | CL30: =SUM(AW30:AY30) -> 121211.93 | CM30: =SUM(AZ30:BB30) -> 113405.58 | CP30: =$C30 -> Sales and marketing | CR30: =E30-W30 -> -559989.02 | CS30: =F30-X30 -> -87944.269 | CT30: =G30-Y30 -> -18941.468 | CU30: =H30-Z30 -> -36795.835 | CV30: =I30-AA30 -> -32206.966 | CW30: =J30-AB30 -> -64652.751 | CX30: =K30-AC30 -> -48002.751 | CY30: =L30-AD30 -> -49302.751 | ... DE30: =R30-AJ30 -> -51152.751 | DH30: =$C30 -> Sales and marketing | DJ30: =IFERROR(((E30-W30)/ABS(W30))+1,"") -> 0.14723888 | DK30: =IFERROR(((F30-X30)/ABS(X30))+1,"") -> 0.52367996 | DL30: =IFERROR(((G30-Y30)/ABS(Y30))+1,"") -> 0.66052568 | DM30: =IFERROR(((H30-Z30)/ABS(Z30))+1,"") -> 0.44481605 | DN30: =IFERROR(((I30-AA30)/ABS(AA30))+1,"") -> 0.48517804 | DO30: =IFERROR(((J30-AB30)/ABS(AB30))+1,"") -> 0 | DP30: =IFERROR(((K30-AC30)/ABS(AC30))+1,"") -> 0 | DQ30: =IFERROR(((L30-AD30)/ABS(AD30))+1,"") -> 0 | ... DW30: =IFERROR(((R30-AJ30)/ABS(AJ30))+1,"") -> 0
C31: Engineering | E31: =SUM(G31:R31) -> 301227.16 | F31: =SUMPRODUCT((G$6:R$6<=F$6)*(G31:R31)) -> 301227.16 | G31: ='⑵-3 IS(ENG)'!G18 -> 98908 | H31: ='⑵-3 IS(ENG)'!H18 -> 95594 | I31: ='⑵-3 IS(ENG)'!I18 -> 106725.16 | J31: ='⑵-3 IS(ENG)'!J18 -> 0 | K31: ='⑵-3 IS(ENG)'!K18 -> 0 | L31: ='⑵-3 IS(ENG)'!L18 -> 0 | M31: ='⑵-3 IS(ENG)'!M18 -> 0 | N31: ='⑵-3 IS(ENG)'!N18 -> 0 | ... R31: ='⑵-3 IS(ENG)'!R18 -> 0 | U31: =$C31 -> Engineering | W31: =SUM(Y31:AJ31) -> 1296773.3 | X31: =SUMPRODUCT((Y$6:AJ$6<=X$6)*(Y31:AJ31)) -> 332156.71 | Y31: ='⑵-3 IS(ENG)'!Y18 -> 105328.6 | Z31: ='⑵-3 IS(ENG)'!Z18 -> 105549.76 | AA31: ='⑵-3 IS(ENG)'!AA18 -> 121278.35 | AB31: ='⑵-3 IS(ENG)'!AB18 -> 103576.82 | AC31: ='⑵-3 IS(ENG)'!AC18 -> 103429.52 | AD31: ='⑵-3 IS(ENG)'!AD18 -> 110726.82 | AE31: ='⑵-3 IS(ENG)'!AE18 -> 104094.52 | AF31: ='⑵-3 IS(ENG)'!AF18 -> 108744.52 | ... AJ31: ='⑵-3 IS(ENG)'!AJ18 -> 110506.01 | AM31: =$C31 -> Engineering | AO31: =SUM(AQ31:BB31) -> 1208308.9 | AP31: =SUMPRODUCT((AQ$6:BB$6<=AP$6)*(AQ31:BB31)) -> 301837.9 | AQ31: ='⑵-3 IS(ENG)'!AQ18 -> 89431.41 | AR31: ='⑵-3 IS(ENG)'!AR18 -> 95531.337 | AS31: ='⑵-3 IS(ENG)'!AS18 -> 116875.16 | AT31: ='⑵-3 IS(ENG)'!AT18 -> 103263.29 | AU31: ='⑵-3 IS(ENG)'!AU18 -> 94984.31 | AV31: ='⑵-3 IS(ENG)'!AV18 -> 99989.24 | AW31: ='⑵-3 IS(ENG)'!AW18 -> 98612.85 | AX31: ='⑵-3 IS(ENG)'!AX18 -> 96912.42 | ... BB31: ='⑵-3 IS(ENG)'!BB18 -> 131779.83 | BE31: =$C31 -> Engineering | BG31: =SUM(BI31:BT31) -> 1253787 | BH31: =SUMPRODUCT((BI$6:BT$6<=BH$6)*(BI31:BT31)) -> 317696 | BI31: 113118 | BJ31: 99852 | BK31: 104726 | BL31: 106702 | BM31: 111001 | BN31: 101426 | BO31: 92562 | BP31: 103787 | BQ31: 101778 | BR31: 108556 | BS31: 99712 | BT31: 110567 | BW31: =$C31 -> Engineering | BY31: =SUM(BZ31:CC31) -> 301227.16 | BZ31: =SUM(G31:I31) -> 301227.16 | CA31: =SUM(J31:L31) -> 0 | CB31: =SUM(M31:O31) -> 0 | CC31: =SUM(P31:R31) -> 0 | CD31: =SUM(CE31:CH31) -> 1296773.3 | CE31: =SUM(Y31:AA31) -> 332156.71 | CF31: =SUM(AB31:AD31) -> 317733.17 | CG31: =SUM(AE31:AG31) -> 325150.86 | CH31: =SUM(AH31:AJ31) -> 321732.58 | CI31: =SUM(CJ31:CM31) -> 1208308.9 | CJ31: =SUM(AQ31:AS31) -> 301837.9 | CK31: =SUM(AT31:AV31) -> 298236.84 | CL31: =SUM(AW31:AY31) -> 289395.8 | CM31: =SUM(AZ31:BB31) -> 318838.32 | CP31: =$C31 -> Engineering | CR31: =E31-W31 -> -995546.16 | CS31: =F31-X31 -> -30929.55 | CT31: =G31-Y31 -> -6420.5953 | CU31: =H31-Z31 -> -9955.7646 | CV31: =I31-AA31 -> -14553.19 | CW31: =J31-AB31 -> -103576.82 | CX31: =K31-AC31 -> -103429.52 | CY31: =L31-AD31 -> -110726.82 | ... DE31: =R31-AJ31 -> -110506.01 | DH31: =$C31 -> Engineering | DJ31: =IFERROR(((E31-W31)/ABS(W31))+1,"") -> 0.23228976 | DK31: =IFERROR(((F31-X31)/ABS(X31))+1,"") -> 0.90688266 | DL31: =IFERROR(((G31-Y31)/ABS(Y31))+1,"") -> 0.93904224 | DM31: =IFERROR(((H31-Z31)/ABS(Z31))+1,"") -> 0.90567705 | DN31: =IFERROR(((I31-AA31)/ABS(AA31))+1,"") -> 0.88000175 | DO31: =IFERROR(((J31-AB31)/ABS(AB31))+1,"") -> 0 | DP31: =IFERROR(((K31-AC31)/ABS(AC31))+1,"") -> 0 | DQ31: =IFERROR(((L31-AD31)/ABS(AD31))+1,"") -> 0 | ... DW31: =IFERROR(((R31-AJ31)/ABS(AJ31))+1,"") -> 0
C32: Energy costs | E32: =SUM(G32:R32) -> 261034.54 | F32: =SUMPRODUCT((G$6:R$6<=F$6)*(G32:R32)) -> 261034.54 | G32: ='⑵-4 IS(Energy)'!G18 -> 90341 | H32: ='⑵-4 IS(Energy)'!H18 -> 81220 | I32: ='⑵-4 IS(Energy)'!I18 -> 89473.54 | J32: ='⑵-4 IS(Energy)'!J18 -> 0 | K32: ='⑵-4 IS(Energy)'!K18 -> 0 | L32: ='⑵-4 IS(Energy)'!L18 -> 0 | M32: ='⑵-4 IS(Energy)'!M18 -> 0 | N32: ='⑵-4 IS(Energy)'!N18 -> 0 | ... R32: ='⑵-4 IS(Energy)'!R18 -> 0 | U32: =$C32 -> Energy costs | W32: =SUM(Y32:AJ32) -> 1150381 | X32: =SUMPRODUCT((Y$6:AJ$6<=X$6)*(Y32:AJ32)) -> 278957 | Y32: ='⑵-4 IS(Energy)'!Y18 -> 95066 | Z32: ='⑵-4 IS(Energy)'!Z18 -> 88689 | AA32: ='⑵-4 IS(Energy)'!AA18 -> 95202 | AB32: ='⑵-4 IS(Energy)'!AB18 -> 95279 | AC32: ='⑵-4 IS(Energy)'!AC18 -> 98995 | AD32: ='⑵-4 IS(Energy)'!AD18 -> 97719 | AE32: ='⑵-4 IS(Energy)'!AE18 -> 95139 | AF32: ='⑵-4 IS(Energy)'!AF18 -> 92480 | ... AJ32: ='⑵-4 IS(Energy)'!AJ18 -> 96053 | AM32: =$C32 -> Energy costs | AO32: =SUM(AQ32:BB32) -> 1117621.9 | AP32: =SUMPRODUCT((AQ$6:BB$6<=AP$6)*(AQ32:BB32)) -> 265056.55 | AQ32: ='⑵-4 IS(Energy)'!AQ18 -> 89081.46 | AR32: ='⑵-4 IS(Energy)'!AR18 -> 83021.03 | AS32: ='⑵-4 IS(Energy)'!AS18 -> 92954.06 | AT32: ='⑵-4 IS(Energy)'!AT18 -> 90956.74 | AU32: ='⑵-4 IS(Energy)'!AU18 -> 90921.15 | AV32: ='⑵-4 IS(Energy)'!AV18 -> 93453.07 | AW32: ='⑵-4 IS(Energy)'!AW18 -> 96675.21 | AX32: ='⑵-4 IS(Energy)'!AX18 -> 99681.8 | ... BB32: ='⑵-4 IS(Energy)'!BB18 -> 90442.8 | BE32: =$C32 -> Energy costs | BG32: =SUM(BI32:BT32) -> 1166251 | BH32: =SUMPRODUCT((BI$6:BT$6<=BH$6)*(BI32:BT32)) -> 289940 | BI32: 97344 | BJ32: 93004 | BK32: 99592 | BL32: 96306 | BM32: 93555 | BN32: 98814 | BO32: 94489 | BP32: 94438 | BQ32: 102561 | BR32: 102244 | BS32: 100474 | BT32: 93430 | BW32: =$C32 -> Energy costs | BY32: =SUM(BZ32:CC32) -> 261034.54 | BZ32: =SUM(G32:I32) -> 261034.54 | CA32: =SUM(J32:L32) -> 0 | CB32: =SUM(M32:O32) -> 0 | CC32: =SUM(P32:R32) -> 0 | CD32: =SUM(CE32:CH32) -> 1150381 | CE32: =SUM(Y32:AA32) -> 278957 | CF32: =SUM(AB32:AD32) -> 291993 | CG32: =SUM(AE32:AG32) -> 285039 | CH32: =SUM(AH32:AJ32) -> 294392 | CI32: =SUM(CJ32:CM32) -> 1117621.9 | CJ32: =SUM(AQ32:AS32) -> 265056.55 | CK32: =SUM(AT32:AV32) -> 275330.96 | CL32: =SUM(AW32:AY32) -> 298848.71 | CM32: =SUM(AZ32:BB32) -> 278385.69 | CP32: =$C32 -> Energy costs | CR32: =E32-W32 -> -889346.46 | CS32: =F32-X32 -> -17922.46 | CT32: =G32-Y32 -> -4725 | CU32: =H32-Z32 -> -7469 | CV32: =I32-AA32 -> -5728.46 | CW32: =J32-AB32 -> -95279 | CX32: =K32-AC32 -> -98995 | CY32: =L32-AD32 -> -97719 | ... DE32: =R32-AJ32 -> -96053 | DH32: =$C32 -> Energy costs | DJ32: =IFERROR(((E32-W32)/ABS(W32))+1,"") -> 0.22691138 | DK32: =IFERROR(((F32-X32)/ABS(X32))+1,"") -> 0.93575189 | DL32: =IFERROR(((G32-Y32)/ABS(Y32))+1,"") -> 0.95029769 | DM32: =IFERROR(((H32-Z32)/ABS(Z32))+1,"") -> 0.91578437 | DN32: =IFERROR(((I32-AA32)/ABS(AA32))+1,"") -> 0.93982836 | DO32: =IFERROR(((J32-AB32)/ABS(AB32))+1,"") -> 0 | DP32: =IFERROR(((K32-AC32)/ABS(AC32))+1,"") -> 0 | DQ32: =IFERROR(((L32-AD32)/ABS(AD32))+1,"") -> 0 | ... DW32: =IFERROR(((R32-AJ32)/ABS(AJ32))+1,"") -> 0
B33: Gross Operating Profit | E33: =SUM(G33:R33) -> 495136.73 | F33: =SUMPRODUCT((G$6:R$6<=F$6)*(G33:R33)) -> 495136.73 | G33: =G21-G28 -> 238265.95 | H33: =H21-H28 -> 142333.12 | I33: =I21-I28 -> 114537.66 | J33: =J21-J28 -> 0 | K33: =K21-K28 -> 0 | L33: =L21-L28 -> 0 | M33: =M21-M28 -> 0 | N33: =N21-N28 -> 0 | ... R33: =R21-R28 -> 0 | T33: =$B33 -> Gross Operating Profit | W33: =SUM(Y33:AJ33) -> 5630666.9 | X33: =SUMPRODUCT((Y$6:AJ$6<=X$6)*(Y33:AJ33)) -> 1120251.2 | Y33: =Y21-Y28 -> 340279.38 | Z33: =Z21-Z28 -> 407488.79 | AA33: =AA21-AA28 -> 372482.99 | AB33: =AB21-AB28 -> 363502.87 | AC33: =AC21-AC28 -> 488851.23 | AD33: =AD21-AD28 -> 563892.22 | AE33: =AE21-AE28 -> 611108.32 | AF33: =AF21-AF28 -> 477026.69 | ... AJ33: =AJ21-AJ28 -> 536079.72 | AL33: =$B33 -> Gross Operating Profit | AO33: =SUM(AQ33:BB33) -> 4724553.1 | AP33: =SUMPRODUCT((AQ$6:BB$6<=AP$6)*(AQ33:BB33)) -> 1272712.5 | AQ33: =AQ21-AQ28 -> 617366.1 | AR33: =AR21-AR28 -> 290660.74 | AS33: =AS21-AS28 -> 364685.68 | AT33: =AT21-AT28 -> 425402 | AU33: =AU21-AU28 -> 457273.41 | AV33: =AV21-AV28 -> 510844.79 | AW33: =AW21-AW28 -> 628620.15 | AX33: =AX21-AX28 -> 453955.97 | ... BB33: =BB21-BB28 -> 237678.47 | BD33: =$B33 -> Gross Operating Profit | BG33: =SUM(BI33:BT33) -> 5734676 | BH33: =SUMPRODUCT((BI$6:BT$6<=BH$6)*(BI33:BT33)) -> 1551771 | BI33: =BI21-BI28 -> 556364 | BJ33: =BJ21-BJ28 -> 552226 | BK33: =BK21-BK28 -> 443181 | BL33: =BL21-BL28 -> 363925 | BM33: =BM21-BM28 -> 474679 | BN33: =BN21-BN28 -> 557209 | BO33: =BO21-BO28 -> 736036 | BP33: =BP21-BP28 -> 553301 | ... BT33: =BT21-BT28 -> 508695.72 | BV33: =$B33 -> Gross Operating Profit | BY33: =SUM(BZ33:CC33) -> 495136.73 | BZ33: =BZ21-BZ28 -> 495136.73 | CA33: =CA21-CA28 -> 0 | CB33: =CB21-CB28 -> 0 | CC33: =CC21-CC28 -> 0 | CD33: =SUM(CE33:CH33) -> 5630666.9 | CE33: =CE21-CE28 -> 1120251.2 | CF33: =CF21-CF28 -> 1416246.3 | CG33: =CG21-CG28 -> 1601853.6 | CH33: =CH21-CH28 -> 1492315.9 | CI33: =SUM(CJ33:CM33) -> 4724553.1 | CJ33: =CJ21-CJ28 -> 1272712.5 | CK33: =CK21-CK28 -> 1393520.2 | CL33: =CL21-CL28 -> 1446667.8 | CM33: =CM21-CM28 -> 611652.68 | CO33: =$B33 -> Gross Operating Profit | CR33: =E33-W33 -> -5135530.2 | CS33: =F33-X33 -> -625114.43 | CT33: =G33-Y33 -> -102013.43 | CU33: =H33-Z33 -> -265155.67 | CV33: =I33-AA33 -> -257945.33 | CW33: =J33-AB33 -> -363502.87 | CX33: =K33-AC33 -> -488851.23 | CY33: =L33-AD33 -> -563892.22 | ... DE33: =R33-AJ33 -> -536079.72 | DG33: =$B33 -> Gross Operating Profit | DJ33: =IFERROR(((E33-W33)/ABS(W33))+1,"") -> 0.087935717 | DK33: =IFERROR(((F33-X33)/ABS(X33))+1,"") -> 0.44198725 | DL33: =IFERROR(((G33-Y33)/ABS(Y33))+1,"") -> 0.70020683 | DM33: =IFERROR(((H33-Z33)/ABS(Z33))+1,"") -> 0.34929334 | DN33: =IFERROR(((I33-AA33)/ABS(AA33))+1,"") -> 0.30749769 | DO33: =IFERROR(((J33-AB33)/ABS(AB33))+1,"") -> 0 | DP33: =IFERROR(((K33-AC33)/ABS(AC33))+1,"") -> 0 | DQ33: =IFERROR(((L33-AD33)/ABS(AD33))+1,"") -> 0 | ... DW33: =IFERROR(((R33-AJ33)/ABS(AJ33))+1,"") -> 0
B34: Fixed Charges | E34: =SUM(G34:R34) -> 478220.3 | F34: =SUMPRODUCT((G$6:R$6<=F$6)*(G34:R34)) -> 478220.3 | G34: =SUM(G35:G38) -> 161772.3 | H34: =SUM(H35:H38) -> 158032 | I34: =SUM(I35:I38) -> 158416 | J34: =SUM(J35:J38) -> 0 | K34: =SUM(K35:K38) -> 0 | L34: =SUM(L35:L38) -> 0 | M34: =SUM(M35:M38) -> 0 | N34: =SUM(N35:N38) -> 0 | ... R34: =SUM(R35:R38) -> 0 | T34: =$B34 -> Fixed Charges | W34: =SUM(Y34:AJ34) -> 2301262 | X34: =SUMPRODUCT((Y$6:AJ$6<=X$6)*(Y34:AJ34)) -> 565356 | Y34: =SUM(Y35:Y38) -> 187765 | Z34: =SUM(Z35:Z38) -> 187566 | AA34: =SUM(AA35:AA38) -> 190025 | AB34: =SUM(AB35:AB38) -> 189842 | AC34: =SUM(AC35:AC38) -> 192520 | AD34: =SUM(AD35:AD38) -> 193922 | AE34: =SUM(AE35:AE38) -> 195052 | AF34: =SUM(AF35:AF38) -> 192395 | ... AJ34: =SUM(AJ35:AJ38) -> 194295 | AL34: =$B34 -> Fixed Charges | AO34: =SUM(AQ34:BB34) -> 1808388 | AP34: =SUMPRODUCT((AQ$6:BB$6<=AP$6)*(AQ34:BB34)) -> 422064 | AQ34: =SUM(AQ35:AQ38) -> 140688 | AR34: =SUM(AR35:AR38) -> 140688 | AS34: =SUM(AS35:AS38) -> 140688 | AT34: =SUM(AT35:AT38) -> 154036 | AU34: =SUM(AU35:AU38) -> 154036 | AV34: =SUM(AV35:AV38) -> 154036 | AW34: =SUM(AW35:AW38) -> 154036 | AX34: =SUM(AX35:AX38) -> 154036 | ... BB34: =SUM(BB35:BB38) -> 154036 | BD34: =$B34 -> Fixed Charges | BG34: =SUM(BI34:BT34) -> 1362047 | BH34: =SUMPRODUCT((BI$6:BT$6<=BH$6)*(BI34:BT34)) -> 306053 | BI34: =SUM(BI35:BI38) -> 97725 | BJ34: =SUM(BJ35:BJ38) -> 97725 | BK34: =SUM(BK35:BK38) -> 110603 | BL34: =SUM(BL35:BL38) -> 110600 | BM34: =SUM(BM35:BM38) -> 110603 | BN34: =SUM(BN35:BN38) -> 110603 | BO34: =SUM(BO35:BO38) -> 120698 | BP34: =SUM(BP35:BP38) -> 120698 | ... BT34: =SUM(BT35:BT38) -> 120698 | BV34: =$B34 -> Fixed Charges | BY34: =SUM(BZ34:CC34) -> 478220.3 | BZ34: =SUM(BZ35:BZ38) -> 478220.3 | CA34: =SUM(CA35:CA38) -> 0 | CB34: =SUM(CB35:CB38) -> 0 | CC34: =SUM(CC35:CC38) -> 0 | CD34: =SUM(CE34:CH34) -> 2301262 | CE34: =SUM(CE35:CE38) -> 565356 | CF34: =SUM(CF35:CF38) -> 576284 | CG34: =SUM(CG35:CG38) -> 579972 | CH34: =SUM(CH35:CH38) -> 579650 | CI34: =SUM(CJ34:CM34) -> 1808388 | CJ34: =SUM(CJ35:CJ38) -> 422064 | CK34: =SUM(CK35:CK38) -> 462108 | CL34: =SUM(CL35:CL38) -> 462108 | CM34: =SUM(CM35:CM38) -> 462108 | CO34: =$B34 -> Fixed Charges | CR34: =E34-W34 -> -1823041.7 | CS34: =F34-X34 -> -87135.7 | CT34: =G34-Y34 -> -25992.7 | CU34: =H34-Z34 -> -29534 | CV34: =I34-AA34 -> -31609 | CW34: =J34-AB34 -> -189842 | CX34: =K34-AC34 -> -192520 | CY34: =L34-AD34 -> -193922 | ... DE34: =R34-AJ34 -> -194295 | DG34: =$B34 -> Fixed Charges | DJ34: =IFERROR(((E34-W34)/ABS(W34))+1,"") -> 0.20780785 | DK34: =IFERROR(((F34-X34)/ABS(X34))+1,"") -> 0.84587463 | DL34: =IFERROR(((G34-Y34)/ABS(Y34))+1,"") -> 0.86156792 | DM34: =IFERROR(((H34-Z34)/ABS(Z34))+1,"") -> 0.84254076 | DN34: =IFERROR(((I34-AA34)/ABS(AA34))+1,"") -> 0.83365873 | DO34: =IFERROR(((J34-AB34)/ABS(AB34))+1,"") -> 0 | DP34: =IFERROR(((K34-AC34)/ABS(AC34))+1,"") -> 0 | DQ34: =IFERROR(((L34-AD34)/ABS(AD34))+1,"") -> 0 | ... DW34: =IFERROR(((R34-AJ34)/ABS(AJ34))+1,"") -> 0
C35: Management Fees | E35: =SUM(G35:R35) -> 86211.3 | F35: =SUMPRODUCT((G$6:R$6<=F$6)*(G35:R35)) -> 86211.3 | G35: ='⑶ IS(Fixed)'!G85 -> 31101.3 | H35: ='⑶ IS(Fixed)'!H85 -> 27363 | I35: ='⑶ IS(Fixed)'!I85 -> 27747 | J35: ='⑶ IS(Fixed)'!J85 -> 0 | K35: ='⑶ IS(Fixed)'!K85 -> 0 | L35: ='⑶ IS(Fixed)'!L85 -> 0 | M35: ='⑶ IS(Fixed)'!M85 -> 0 | N35: ='⑶ IS(Fixed)'!N85 -> 0 | ... R35: ='⑶ IS(Fixed)'!R85 -> 0 | U35: =$C35 -> Management Fees | W35: =SUM(Y35:AJ35) -> 415297 | X35: =SUMPRODUCT((Y$6:AJ$6<=X$6)*(Y35:AJ35)) -> 97332 | Y35: ='⑶ IS(Fixed)'!Y85 -> 31757 | Z35: ='⑶ IS(Fixed)'!Z85 -> 31558 | AA35: ='⑶ IS(Fixed)'!AA85 -> 34017 | AB35: ='⑶ IS(Fixed)'!AB85 -> 32293 | AC35: ='⑶ IS(Fixed)'!AC85 -> 34971 | AD35: ='⑶ IS(Fixed)'!AD85 -> 36373 | AE35: ='⑶ IS(Fixed)'!AE85 -> 37503 | AF35: ='⑶ IS(Fixed)'!AF85 -> 34846 | ... AJ35: ='⑶ IS(Fixed)'!AJ85 -> 36746 | AM35: =$C35 -> Management Fees | AO35: =SUM(AQ35:BB35) -> 0 | AP35: =SUMPRODUCT((AQ$6:BB$6<=AP$6)*(AQ35:BB35)) -> 0 | AQ35: ='⑶ IS(Fixed)'!AQ85 -> 0 | AR35: ='⑶ IS(Fixed)'!AR85 -> 0 | AS35: ='⑶ IS(Fixed)'!AS85 -> 0 | AT35: ='⑶ IS(Fixed)'!AT85 -> 0 | AU35: ='⑶ IS(Fixed)'!AU85 -> 0 | AV35: ='⑶ IS(Fixed)'!AV85 -> 0 | AW35: ='⑶ IS(Fixed)'!AW85 -> 0 | AX35: ='⑶ IS(Fixed)'!AX85 -> 0 | ... BB35: ='⑶ IS(Fixed)'!BB85 -> 0 | BE35: =$C35 -> Management Fees | BG35: =SUM(BI35:BT35) -> 12000 | BH35: =SUMPRODUCT((BI$6:BT$6<=BH$6)*(BI35:BT35)) -> 3000 | BI35: 1000 | BJ35: 1000 | BK35: 1000 | BL35: 1000 | BM35: 1000 | BN35: 1000 | BO35: 1000 | BP35: 1000 | BQ35: 1000 | BR35: 1000 | BS35: 1000 | BT35: 1000 | BW35: =$C35 -> Management Fees | BY35: =SUM(BZ35:CC35) -> 86211.3 | BZ35: =SUM(G35:I35) -> 86211.3 | CA35: =SUM(J35:L35) -> 0 | CB35: =SUM(M35:O35) -> 0 | CC35: =SUM(P35:R35) -> 0 | CD35: =SUM(CE35:CH35) -> 415297 | CE35: =SUM(Y35:AA35) -> 97332 | CF35: =SUM(AB35:AD35) -> 103637 | CG35: =SUM(AE35:AG35) -> 107325 | CH35: =SUM(AH35:AJ35) -> 107003 | CI35: =SUM(CJ35:CM35) -> 0 | CJ35: =SUM(AQ35:AS35) -> 0 | CK35: =SUM(AT35:AV35) -> 0 | CL35: =SUM(AW35:AY35) -> 0 | CM35: =SUM(AZ35:BB35) -> 0 | CP35: =$C35 -> Management Fees | CR35: =E35-W35 -> -329085.7 | CS35: =F35-X35 -> -11120.7 | CT35: =G35-Y35 -> -655.7 | CU35: =H35-Z35 -> -4195 | CV35: =I35-AA35 -> -6270 | CW35: =J35-AB35 -> -32293 | CX35: =K35-AC35 -> -34971 | CY35: =L35-AD35 -> -36373 | ... DE35: =R35-AJ35 -> -36746 | DH35: =$C35 -> Management Fees | DJ35: =IFERROR(((E35-W35)/ABS(W35))+1,"") -> 0.20758951 | DK35: =IFERROR(((F35-X35)/ABS(X35))+1,"") -> 0.88574467 | DL35: =IFERROR(((G35-Y35)/ABS(Y35))+1,"") -> 0.97935258 | DM35: =IFERROR(((H35-Z35)/ABS(Z35))+1,"") -> 0.86707016 | DN35: =IFERROR(((I35-AA35)/ABS(AA35))+1,"") -> 0.8156804 | DO35: =IFERROR(((J35-AB35)/ABS(AB35))+1,"") -> 0 | DP35: =IFERROR(((K35-AC35)/ABS(AC35))+1,"") -> 0 | DQ35: =IFERROR(((L35-AD35)/ABS(AD35))+1,"") -> 0 | ... DW35: =IFERROR(((R35-AJ35)/ABS(AJ35))+1,"") -> 0
C36: Property TAX | E36: =SUM(G36:R36) -> 237866 | F36: =SUMPRODUCT((G$6:R$6<=F$6)*(G36:R36)) -> 237866 | G36: =SUM('⑶ IS(Fixed)'!G101) -> 79290 | H36: =SUM('⑶ IS(Fixed)'!H101) -> 79288 | I36: =SUM('⑶ IS(Fixed)'!I101) -> 79288 | J36: =SUM('⑶ IS(Fixed)'!J101) -> 0 | K36: =SUM('⑶ IS(Fixed)'!K101) -> 0 | L36: =SUM('⑶ IS(Fixed)'!L101) -> 0 | M36: =SUM('⑶ IS(Fixed)'!M101) -> 0 | N36: =SUM('⑶ IS(Fixed)'!N101) -> 0 | ... R36: =SUM('⑶ IS(Fixed)'!R101) -> 0 | U36: =$C36 -> Property TAX | W36: =SUM(Y36:AJ36) -> 1255524 | X36: =SUMPRODUCT((Y$6:AJ$6<=X$6)*(Y36:AJ36)) -> 313881 | Y36: =SUM('⑶ IS(Fixed)'!Y101) -> 104627 | Z36: =SUM('⑶ IS(Fixed)'!Z101) -> 104627 | AA36: =SUM('⑶ IS(Fixed)'!AA101) -> 104627 | AB36: =SUM('⑶ IS(Fixed)'!AB101) -> 104627 | AC36: =SUM('⑶ IS(Fixed)'!AC101) -> 104627 | AD36: =SUM('⑶ IS(Fixed)'!AD101) -> 104627 | AE36: =SUM('⑶ IS(Fixed)'!AE101) -> 104627 | AF36: =SUM('⑶ IS(Fixed)'!AF101) -> 104627 | ... AJ36: =SUM('⑶ IS(Fixed)'!AJ101) -> 104627 | AM36: =$C36 -> Property TAX | AO36: =SUM(AQ36:BB36) -> 1207236 | AP36: =SUMPRODUCT((AQ$6:BB$6<=AP$6)*(AQ36:BB36)) -> 283341 | AQ36: =SUM('⑶ IS(Fixed)'!AQ101) -> 94447 | AR36: =SUM('⑶ IS(Fixed)'!AR101) -> 94447 | AS36: =SUM('⑶ IS(Fixed)'!AS101) -> 94447 | AT36: =SUM('⑶ IS(Fixed)'!AT101) -> 102655 | AU36: =SUM('⑶ IS(Fixed)'!AU101) -> 102655 | AV36: =SUM('⑶ IS(Fixed)'!AV101) -> 102655 | AW36: =SUM('⑶ IS(Fixed)'!AW101) -> 102655 | AX36: =SUM('⑶ IS(Fixed)'!AX101) -> 102655 | ... BB36: =SUM('⑶ IS(Fixed)'!BB101) -> 102655 | BE36: =$C36 -> Property TAX | BG36: =SUM(BI36:BT36) -> 982876 | BH36: =SUMPRODUCT((BI$6:BT$6<=BH$6)*(BI36:BT36)) -> 230577 | BI36: 76859 | BJ36: 76859 | BK36: 76859 | BL36: 76857 | BM36: 76859 | BN36: 76859 | BO36: 86954 | BP36: 86954 | BQ36: 86954 | BR36: 86954 | BS36: 86954 | BT36: 86954 | BW36: =$C36 -> Property TAX | BY36: =SUM(BZ36:CC36) -> 237866 | BZ36: =SUM(G36:I36) -> 237866 | CA36: =SUM(J36:L36) -> 0 | CB36: =SUM(M36:O36) -> 0 | CC36: =SUM(P36:R36) -> 0 | CD36: =SUM(CE36:CH36) -> 1255524 | CE36: =SUM(Y36:AA36) -> 313881 | CF36: =SUM(AB36:AD36) -> 313881 | CG36: =SUM(AE36:AG36) -> 313881 | CH36: =SUM(AH36:AJ36) -> 313881 | CI36: =SUM(CJ36:CM36) -> 1207236 | CJ36: =SUM(AQ36:AS36) -> 283341 | CK36: =SUM(AT36:AV36) -> 307965 | CL36: =SUM(AW36:AY36) -> 307965 | CM36: =SUM(AZ36:BB36) -> 307965 | CP36: =$C36 -> Property TAX | CR36: =E36-W36 -> -1017658 | CS36: =F36-X36 -> -76015 | CT36: =G36-Y36 -> -25337 | CU36: =H36-Z36 -> -25339 | CV36: =I36-AA36 -> -25339 | CW36: =J36-AB36 -> -104627 | CX36: =K36-AC36 -> -104627 | CY36: =L36-AD36 -> -104627 | ... DE36: =R36-AJ36 -> -104627 | DH36: =$C36 -> Property TAX | DJ36: =IFERROR(((E36-W36)/ABS(W36))+1,"") -> 0.18945556 | DK36: =IFERROR(((F36-X36)/ABS(X36))+1,"") -> 0.75782223 | DL36: =IFERROR(((G36-Y36)/ABS(Y36))+1,"") -> 0.75783498 | DM36: =IFERROR(((H36-Z36)/ABS(Z36))+1,"") -> 0.75781586 | DN36: =IFERROR(((I36-AA36)/ABS(AA36))+1,"") -> 0.75781586 | DO36: =IFERROR(((J36-AB36)/ABS(AB36))+1,"") -> 0 | DP36: =IFERROR(((K36-AC36)/ABS(AC36))+1,"") -> 0 | DQ36: =IFERROR(((L36-AD36)/ABS(AD36))+1,"") -> 0 | ... DW36: =IFERROR(((R36-AJ36)/ABS(AJ36))+1,"") -> 0
C37: Insurance expenses | E37: =SUM(G37:R37) -> 154143 | F37: =SUMPRODUCT((G$6:R$6<=F$6)*(G37:R37)) -> 154143 | G37: =SUM('⑶ IS(Fixed)'!G73) -> 51381 | H37: =SUM('⑶ IS(Fixed)'!H73) -> 51381 | I37: =SUM('⑶ IS(Fixed)'!I73) -> 51381 | J37: =SUM('⑶ IS(Fixed)'!J73) -> 0 | K37: =SUM('⑶ IS(Fixed)'!K73) -> 0 | L37: =SUM('⑶ IS(Fixed)'!L73) -> 0 | M37: =SUM('⑶ IS(Fixed)'!M73) -> 0 | N37: =SUM('⑶ IS(Fixed)'!N73) -> 0 | ... R37: =SUM('⑶ IS(Fixed)'!R73) -> 0 | U37: =$C37 -> Insurance expenses | W37: =SUM(Y37:AJ37) -> 630441 | X37: =SUMPRODUCT((Y$6:AJ$6<=X$6)*(Y37:AJ37)) -> 154143 | Y37: =SUM('⑶ IS(Fixed)'!Y73) -> 51381 | Z37: =SUM('⑶ IS(Fixed)'!Z73) -> 51381 | AA37: =SUM('⑶ IS(Fixed)'!AA73) -> 51381 | AB37: =SUM('⑶ IS(Fixed)'!AB73) -> 52922 | AC37: =SUM('⑶ IS(Fixed)'!AC73) -> 52922 | AD37: =SUM('⑶ IS(Fixed)'!AD73) -> 52922 | AE37: =SUM('⑶ IS(Fixed)'!AE73) -> 52922 | AF37: =SUM('⑶ IS(Fixed)'!AF73) -> 52922 | ... AJ37: =SUM('⑶ IS(Fixed)'!AJ73) -> 52922 | AM37: =$C37 -> Insurance expenses | AO37: =SUM(AQ37:BB37) -> 601152 | AP37: =SUMPRODUCT((AQ$6:BB$6<=AP$6)*(AQ37:BB37)) -> 138723 | AQ37: =SUM('⑶ IS(Fixed)'!AQ73) -> 46241 | AR37: =SUM('⑶ IS(Fixed)'!AR73) -> 46241 | AS37: =SUM('⑶ IS(Fixed)'!AS73) -> 46241 | AT37: =SUM('⑶ IS(Fixed)'!AT73) -> 51381 | AU37: =SUM('⑶ IS(Fixed)'!AU73) -> 51381 | AV37: =SUM('⑶ IS(Fixed)'!AV73) -> 51381 | AW37: =SUM('⑶ IS(Fixed)'!AW73) -> 51381 | AX37: =SUM('⑶ IS(Fixed)'!AX73) -> 51381 | ... BB37: =SUM('⑶ IS(Fixed)'!BB73) -> 51381 | BE37: =$C37 -> Insurance expenses | BG37: =SUM(BI37:BT37) -> 367171 | BH37: =SUMPRODUCT((BI$6:BT$6<=BH$6)*(BI37:BT37)) -> 72476 | BI37: 19866 | BJ37: 19866 | BK37: 32744 | BL37: 32743 | BM37: 32744 | BN37: 32744 | BO37: 32744 | BP37: 32744 | BQ37: 32744 | BR37: 32744 | BS37: 32744 | BT37: 32744 | BW37: =$C37 -> Insurance expenses | BY37: =SUM(BZ37:CC37) -> 154143 | BZ37: =SUM(G37:I37) -> 154143 | CA37: =SUM(J37:L37) -> 0 | CB37: =SUM(M37:O37) -> 0 | CC37: =SUM(P37:R37) -> 0 | CD37: =SUM(CE37:CH37) -> 630441 | CE37: =SUM(Y37:AA37) -> 154143 | CF37: =SUM(AB37:AD37) -> 158766 | CG37: =SUM(AE37:AG37) -> 158766 | CH37: =SUM(AH37:AJ37) -> 158766 | CI37: =SUM(CJ37:CM37) -> 601152 | CJ37: =SUM(AQ37:AS37) -> 138723 | CK37: =SUM(AT37:AV37) -> 154143 | CL37: =SUM(AW37:AY37) -> 154143 | CM37: =SUM(AZ37:BB37) -> 154143 | CP37: =$C37 -> Insurance expenses | CR37: =E37-W37 -> -476298 | CS37: =F37-X37 -> 0 | CT37: =G37-Y37 -> 0 | CU37: =H37-Z37 -> 0 | CV37: =I37-AA37 -> 0 | CW37: =J37-AB37 -> -52922 | CX37: =K37-AC37 -> -52922 | CY37: =L37-AD37 -> -52922 | ... DE37: =R37-AJ37 -> -52922 | DH37: =$C37 -> Insurance expenses | DJ37: =IFERROR(((E37-W37)/ABS(W37))+1,"") -> 0.24450028 | DK37: =IFERROR(((F37-X37)/ABS(X37))+1,"") -> 1 | DL37: =IFERROR(((G37-Y37)/ABS(Y37))+1,"") -> 1 | DM37: =IFERROR(((H37-Z37)/ABS(Z37))+1,"") -> 1 | DN37: =IFERROR(((I37-AA37)/ABS(AA37))+1,"") -> 1 | DO37: =IFERROR(((J37-AB37)/ABS(AB37))+1,"") -> 0 | DP37: =IFERROR(((K37-AC37)/ABS(AC37))+1,"") -> 0 | DQ37: =IFERROR(((L37-AD37)/ABS(AD37))+1,"") -> 0 | ... DW37: =IFERROR(((R37-AJ37)/ABS(AJ37))+1,"") -> 0
C38: Others | E38: =SUM(G38:R38) -> 0 | F38: =SUMPRODUCT((G$6:R$6<=F$6)*(G38:R38)) -> 0 | U38: =$C38 -> Others | W38: =SUM(Y38:AJ38) -> 0 | X38: =SUMPRODUCT((Y$6:AJ$6<=X$6)*(Y38:AJ38)) -> 0 | AM38: =$C38 -> Others | AO38: =SUM(AQ38:BB38) -> 0 | AP38: =SUMPRODUCT((AQ$6:BB$6<=AP$6)*(AQ38:BB38)) -> 0 | BE38: =$C38 -> Others | BG38: =SUM(BI38:BT38) -> 0 | BH38: =SUMPRODUCT((BI$6:BT$6<=BH$6)*(BI38:BT38)) -> 0 | BI38: 0 | BJ38: 0 | BK38: 0 | BL38: 0 | BM38: 0 | BN38: 0 | BO38: 0 | BP38: 0 | BQ38: 0 | BR38: 0 | BS38: 0 | BT38: 0 | BW38: =$C38 -> Others | BY38: =SUM(BZ38:CC38) -> 0 | BZ38: =SUM(G38:I38) -> 0 | CA38: =SUM(J38:L38) -> 0 | CB38: =SUM(M38:O38) -> 0 | CC38: =SUM(P38:R38) -> 0 | CD38: =SUM(CE38:CH38) -> 0 | CE38: =SUM(Y38:AA38) -> 0 | CF38: =SUM(AB38:AD38) -> 0 | CG38: =SUM(AE38:AG38) -> 0 | CH38: =SUM(AH38:AJ38) -> 0 | CI38: =SUM(CJ38:CM38) -> 0 | CJ38: =SUM(AQ38:AS38) -> 0 | CK38: =SUM(AT38:AV38) -> 0 | CL38: =SUM(AW38:AY38) -> 0 | CM38: =SUM(AZ38:BB38) -> 0 | CP38: =$C38 -> Others | CR38: =E38-W38 -> 0 | CS38: =F38-X38 -> 0 | CT38: =G38-Y38 -> 0 | CU38: =H38-Z38 -> 0 | CV38: =I38-AA38 -> 0 | CW38: =J38-AB38 -> 0 | CX38: =K38-AC38 -> 0 | CY38: =L38-AD38 -> 0 | ... DE38: =R38-AJ38 -> 0 | DH38: =$C38 -> Others | DJ38: =IFERROR(((E38-W38)/ABS(W38))+1,"") | DK38: =IFERROR(((F38-X38)/ABS(X38))+1,"") | DL38: =IFERROR(((G38-Y38)/ABS(Y38))+1,"") | DM38: =IFERROR(((H38-Z38)/ABS(Z38))+1,"") | DN38: =IFERROR(((I38-AA38)/ABS(AA38))+1,"") | DO38: =IFERROR(((J38-AB38)/ABS(AB38))+1,"") | DP38: =IFERROR(((K38-AC38)/ABS(AC38))+1,"") | DQ38: =IFERROR(((L38-AD38)/ABS(AD38))+1,"") | ... DW38: =IFERROR(((R38-AJ38)/ABS(AJ38))+1,"")
B39: Net Operating Income | E39: =SUM(G39:R39) -> 16916.43 | F39: =SUMPRODUCT((G$6:R$6<=F$6)*(G39:R39)) -> 16916.43 | G39: =G33-G34 -> 76493.65 | H39: =H33-H34 -> -15698.88 | I39: =I33-I34 -> -43878.34 | J39: =J33-J34 -> 0 | K39: =K33-K34 -> 0 | L39: =L33-L34 -> 0 | M39: =M33-M34 -> 0 | N39: =N33-N34 -> 0 | ... R39: =R33-R34 -> 0 | T39: =$B39 -> Net Operating Income | W39: =SUM(Y39:AJ39) -> 3329404.9 | X39: =SUMPRODUCT((Y$6:AJ$6<=X$6)*(Y39:AJ39)) -> 554895.16 | Y39: =Y33-Y34 -> 152514.38 | Z39: =Z33-Z34 -> 219922.79 | AA39: =AA33-AA34 -> 182457.99 | AB39: =AB33-AB34 -> 173660.87 | AC39: =AC33-AC34 -> 296331.23 | AD39: =AD33-AD34 -> 369970.22 | AE39: =AE33-AE34 -> 416056.32 | AF39: =AF33-AF34 -> 284631.69 | ... AJ39: =AJ33-AJ34 -> 341784.72 | AL39: =$B39 -> Net Operating Income | AO39: =SUM(AQ39:BB39) -> 2916165.1 | AP39: =SUMPRODUCT((AQ$6:BB$6<=AP$6)*(AQ39:BB39)) -> 850648.51 | AQ39: =AQ33-AQ34 -> 476678.1 | AR39: =AR33-AR34 -> 149972.74 | AS39: =AS33-AS34 -> 223997.68 | AT39: =AT33-AT34 -> 271366 | AU39: =AU33-AU34 -> 303237.41 | AV39: =AV33-AV34 -> 356808.79 | AW39: =AW33-AW34 -> 474584.15 | AX39: =AX33-AX34 -> 299919.97 | ... BB39: =BB33-BB34 -> 83642.467 | BD39: =$B39 -> Net Operating Income | BG39: =SUM(BI39:BT39) -> 4372629 | BH39: =SUMPRODUCT((BI$6:BT$6<=BH$6)*(BI39:BT39)) -> 1245718 | BI39: =BI33-BI34 -> 458639 | BJ39: =BJ33-BJ34 -> 454501 | BK39: =BK33-BK34 -> 332578 | BL39: =BL33-BL34 -> 253325 | BM39: =BM33-BM34 -> 364076 | BN39: =BN33-BN34 -> 446606 | BO39: =BO33-BO34 -> 615338 | BP39: =BP33-BP34 -> 432603 | ... BT39: =BT33-BT34 -> 387997.72 | BV39: =$B39 -> Net Operating Income | BY39: =SUM(BZ39:CC39) -> 16916.43 | BZ39: =BZ33-BZ34 -> 16916.43 | CA39: =CA33-CA34 -> 0 | CB39: =CB33-CB34 -> 0 | CC39: =CC33-CC34 -> 0 | CD39: =SUM(CE39:CH39) -> 3329404.9 | CE39: =CE33-CE34 -> 554895.16 | CF39: =CF33-CF34 -> 839962.31 | CG39: =CG33-CG34 -> 1021881.6 | CH39: =CH33-CH34 -> 912665.87 | CI39: =SUM(CJ39:CM39) -> 2916165.1 | CJ39: =CJ33-CJ34 -> 850648.51 | CK39: =CK33-CK34 -> 931412.2 | CL39: =CL33-CL34 -> 984559.75 | CM39: =CM33-CM34 -> 149544.68 | CO39: =$B39 -> Net Operating Income | CR39: =E39-W39 -> -3312488.5 | CS39: =F39-X39 -> -537978.73 | CT39: =G39-Y39 -> -76020.734 | CU39: =H39-Z39 -> -235621.67 | CV39: =I39-AA39 -> -226336.33 | CW39: =J39-AB39 -> -173660.87 | CX39: =K39-AC39 -> -296331.23 | CY39: =L39-AD39 -> -369970.22 | ... DE39: =R39-AJ39 -> -341784.72 | DG39: =$B39 -> Net Operating Income | DJ39: =IFERROR(((E39-W39)/ABS(W39))+1,"") -> 0.005080917 | DK39: =IFERROR(((F39-X39)/ABS(X39))+1,"") -> 0.030485813 | DL39: =IFERROR(((G39-Y39)/ABS(Y39))+1,"") -> 0.5015504 | DM39: =IFERROR(((H39-Z39)/ABS(Z39))+1,"") -> -0.071383599 | DN39: =IFERROR(((I39-AA39)/ABS(AA39))+1,"") -> -0.24048462 | DO39: =IFERROR(((J39-AB39)/ABS(AB39))+1,"") -> 0 | DP39: =IFERROR(((K39-AC39)/ABS(AC39))+1,"") -> 0 | DQ39: =IFERROR(((L39-AD39)/ABS(AD39))+1,"") -> 0 | ... DW39: =IFERROR(((R39-AJ39)/ABS(AJ39))+1,"") -> 0
B40: Depreciation & Amortization | E40: =SUM(G40:R40) -> 150896.75 | F40: =SUMPRODUCT((G$6:R$6<=F$6)*(G40:R40)) -> 150896.75 | G40: =SUM('⑶ IS(Fixed)'!G51:G53) -> 50340 | H40: =SUM('⑶ IS(Fixed)'!H51:H53) -> 50301 | I40: =SUM('⑶ IS(Fixed)'!I51:I53) -> 50255.75 | J40: =SUM('⑶ IS(Fixed)'!J51:J53) -> 0 | K40: =SUM('⑶ IS(Fixed)'!K51:K53) -> 0 | L40: =SUM('⑶ IS(Fixed)'!L51:L53) -> 0 | M40: =SUM('⑶ IS(Fixed)'!M51:M53) -> 0 | N40: =SUM('⑶ IS(Fixed)'!N51:N53) -> 0 | ... R40: =SUM('⑶ IS(Fixed)'!R51:R53) -> 0 | T40: =$B40 -> Depreciation & Amortization | W40: =SUM(Y40:AJ40) -> 645720 | X40: =SUMPRODUCT((Y$6:AJ$6<=X$6)*(Y40:AJ40)) -> 161430 | Y40: =SUM('⑶ IS(Fixed)'!Y51:Y53) -> 53810 | Z40: =SUM('⑶ IS(Fixed)'!Z51:Z53) -> 53810 | AA40: =SUM('⑶ IS(Fixed)'!AA51:AA53) -> 53810 | AB40: =SUM('⑶ IS(Fixed)'!AB51:AB53) -> 53810 | AC40: =SUM('⑶ IS(Fixed)'!AC51:AC53) -> 53810 | AD40: =SUM('⑶ IS(Fixed)'!AD51:AD53) -> 53810 | AE40: =SUM('⑶ IS(Fixed)'!AE51:AE53) -> 53810 | AF40: =SUM('⑶ IS(Fixed)'!AF51:AF53) -> 53810 | ... AJ40: =SUM('⑶ IS(Fixed)'!AJ51:AJ53) -> 53810 | AL40: =$B40 -> Depreciation & Amortization | AO40: =SUM(AQ40:BB40) -> 619518.63 | AP40: =SUMPRODUCT((AQ$6:BB$6<=AP$6)*(AQ40:BB40)) -> 158586 | AQ40: =SUM('⑶ IS(Fixed)'!AQ51:AQ53) -> 55852 | AR40: =SUM('⑶ IS(Fixed)'!AR51:AR53) -> 51367 | AS40: =SUM('⑶ IS(Fixed)'!AS51:AS53) -> 51367 | AT40: =SUM('⑶ IS(Fixed)'!AT51:AT53) -> 51367 | AU40: =SUM('⑶ IS(Fixed)'!AU51:AU53) -> 51367 | AV40: =SUM('⑶ IS(Fixed)'!AV51:AV53) -> 51367 | AW40: =SUM('⑶ IS(Fixed)'!AW51:AW53) -> 51367 | AX40: =SUM('⑶ IS(Fixed)'!AX51:AX53) -> 51367 | ... BB40: =SUM('⑶ IS(Fixed)'!BB51:BB53) -> 50525.76 | BD40: =$B40 -> Depreciation & Amortization | BG40: =SUM(BI40:BT40) -> 702749 | BH40: =SUMPRODUCT((BI$6:BT$6<=BH$6)*(BI40:BT40)) -> 175486 | BI40: 58543 | BJ40: 58468 | BK40: 58475 | BL40: 58458 | BM40: 58770 | BN40: 58718 | BO40: 58700 | BP40: 58545 | BQ40: 58613 | BR40: 58627 | BS40: 58505 | BT40: 58327 | BV40: =$B40 -> Depreciation & Amortization | BY40: =SUM(BZ40:CC40) -> 150896.75 | BZ40: =SUM(G40:I40) -> 150896.75 | CA40: =SUM(J40:L40) -> 0 | CB40: =SUM(M40:O40) -> 0 | CC40: =SUM(P40:R40) -> 0 | CD40: =SUM(CE40:CH40) -> 645720 | CE40: =SUM(Y40:AA40) -> 161430 | CF40: =SUM(AB40:AD40) -> 161430 | CG40: =SUM(AE40:AG40) -> 161430 | CH40: =SUM(AH40:AJ40) -> 161430 | CI40: =SUM(CJ40:CM40) -> 619518.63 | CJ40: =SUM(AQ40:AS40) -> 158586 | CK40: =SUM(AT40:AV40) -> 154101 | CL40: =SUM(AW40:AY40) -> 154101 | CM40: =SUM(AZ40:BB40) -> 152730.63 | CO40: =$B40 -> Depreciation & Amortization | CR40: =E40-W40 -> -494823.25 | CS40: =F40-X40 -> -10533.25 | CT40: =G40-Y40 -> -3470 | CU40: =H40-Z40 -> -3509 | CV40: =I40-AA40 -> -3554.25 | CW40: =J40-AB40 -> -53810 | CX40: =K40-AC40 -> -53810 | CY40: =L40-AD40 -> -53810 | ... DE40: =R40-AJ40 -> -53810 | DG40: =$B40 -> Depreciation & Amortization | DJ40: =IFERROR(((E40-W40)/ABS(W40))+1,"") -> 0.23368759 | DK40: =IFERROR(((F40-X40)/ABS(X40))+1,"") -> 0.93475036 | DL40: =IFERROR(((G40-Y40)/ABS(Y40))+1,"") -> 0.93551385 | DM40: =IFERROR(((H40-Z40)/ABS(Z40))+1,"") -> 0.93478907 | DN40: =IFERROR(((I40-AA40)/ABS(AA40))+1,"") -> 0.93394815 | DO40: =IFERROR(((J40-AB40)/ABS(AB40))+1,"") -> 0 | DP40: =IFERROR(((K40-AC40)/ABS(AC40))+1,"") -> 0 | DQ40: =IFERROR(((L40-AD40)/ABS(AD40))+1,"") -> 0 | ... DW40: =IFERROR(((R40-AJ40)/ABS(AJ40))+1,"") -> 0
B41: Income before income tax | E41: =SUM(G41:R41) -> -133980.32 | F41: =SUMPRODUCT((G$6:R$6<=F$6)*(G41:R41)) -> -133980.32 | G41: =G39-G40 -> 26153.65 | H41: =H39-H40 -> -65999.88 | I41: =I39-I40 -> -94134.09 | J41: =J39-J40 -> 0 | K41: =K39-K40 -> 0 | L41: =L39-L40 -> 0 | M41: =M39-M40 -> 0 | N41: =N39-N40 -> 0 | ... R41: =R39-R40 -> 0 | T41: =$B41 -> Income before income tax | W41: =SUM(Y41:AJ41) -> 2683684.9 | X41: =SUMPRODUCT((Y$6:AJ$6<=X$6)*(Y41:AJ41)) -> 393465.16 | Y41: =Y39-Y40 -> 98704.384 | Z41: =Z39-Z40 -> 166112.79 | AA41: =AA39-AA40 -> 128647.99 | AB41: =AB39-AB40 -> 119850.87 | AC41: =AC39-AC40 -> 242521.23 | AD41: =AD39-AD40 -> 316160.22 | AE41: =AE39-AE40 -> 362246.32 | AF41: =AF39-AF40 -> 230821.69 | ... AJ41: =AJ39-AJ40 -> 287974.72 | AL41: =$B41 -> Income before income tax | AO41: =SUM(AQ41:BB41) -> 2296646.5 | AP41: =SUMPRODUCT((AQ$6:BB$6<=AP$6)*(AQ41:BB41)) -> 692062.51 | AQ41: =AQ39-AQ40 -> 420826.1 | AR41: =AR39-AR40 -> 98605.737 | AS41: =AS39-AS40 -> 172630.68 | AT41: =AT39-AT40 -> 219999 | AU41: =AU39-AU40 -> 251870.41 | AV41: =AV39-AV40 -> 305441.79 | AW41: =AW39-AW40 -> 423217.15 | AX41: =AX39-AX40 -> 248552.97 | ... BB41: =BB39-BB40 -> 33116.707 | BD41: =$B41 -> Income before income tax | BG41: =SUM(BI41:BT41) -> 3669880 | BH41: =SUMPRODUCT((BI$6:BT$6<=BH$6)*(BI41:BT41)) -> 1070232 | BI41: =BI39-BI40 -> 400096 | BJ41: =BJ39-BJ40 -> 396033 | BK41: =BK39-BK40 -> 274103 | BL41: =BL39-BL40 -> 194867 | BM41: =BM39-BM40 -> 305306 | BN41: =BN39-BN40 -> 387888 | BO41: =BO39-BO40 -> 556638 | BP41: =BP39-BP40 -> 374058 | ... BT41: =BT39-BT40 -> 329670.72 | BV41: =$B41 -> Income before income tax | BY41: =SUM(BZ41:CC41) -> -133980.32 | BZ41: =BZ39-BZ40 -> -133980.32 | CA41: =CA39-CA40 -> 0 | CB41: =CB39-CB40 -> 0 | CC41: =CC39-CC40 -> 0 | CD41: =SUM(CE41:CH41) -> 2683684.9 | CE41: =CE39-CE40 -> 393465.16 | CF41: =CF39-CF40 -> 678532.31 | CG41: =CG39-CG40 -> 860451.58 | CH41: =CH39-CH40 -> 751235.87 | CI41: =SUM(CJ41:CM41) -> 2296646.5 | CJ41: =CJ39-CJ40 -> 692062.51 | CK41: =CK39-CK40 -> 777311.2 | CL41: =CL39-CL40 -> 830458.75 | CM41: =CM39-CM40 -> -3185.953 | CO41: =$B41 -> Income before income tax | CR41: =E41-W41 -> -2817665.2 | CS41: =F41-X41 -> -527445.48 | CT41: =G41-Y41 -> -72550.734 | CU41: =H41-Z41 -> -232112.67 | CV41: =I41-AA41 -> -222782.08 | CW41: =J41-AB41 -> -119850.87 | CX41: =K41-AC41 -> -242521.23 | CY41: =L41-AD41 -> -316160.22 | ... DE41: =R41-AJ41 -> -287974.72 | DG41: =$B41 -> Income before income tax | DJ41: =IFERROR(((E41-W41)/ABS(W41))+1,"") -> -0.049924013 | DK41: =IFERROR(((F41-X41)/ABS(X41))+1,"") -> -0.34051381 | DL41: =IFERROR(((G41-Y41)/ABS(Y41))+1,"") -> 0.26496949 | DM41: =IFERROR(((H41-Z41)/ABS(Z41))+1,"") -> -0.39731968 | DN41: =IFERROR(((I41-AA41)/ABS(AA41))+1,"") -> -0.73171832 | DO41: =IFERROR(((J41-AB41)/ABS(AB41))+1,"") -> 0 | DP41: =IFERROR(((K41-AC41)/ABS(AC41))+1,"") -> 0 | DQ41: =IFERROR(((L41-AD41)/ABS(AD41))+1,"") -> 0 | ... DW41: =IFERROR(((R41-AJ41)/ABS(AJ41))+1,"") -> 0

Sheet 3) IS(Total)
A1: ='1) Rooms'!$A$1 -> ＃ WHR Monthly Closing | R1: ='1) Rooms'!$R$1 -> Business Performance in 2026 | S1: =$A$1 -> ＃ WHR Monthly Closing | AJ1: =$R$1 -> Business Performance in 2026 | AK1: =$A$1 -> ＃ WHR Monthly Closing | BB1: =$R$1 -> Business Performance in 2026 | BC1: =$A$1 -> ＃ WHR Monthly Closing | BT1: =$R$1 -> Business Performance in 2026 | BU1: =$A$1 -> ＃ WHR Monthly Closing | CM1: =$R$1 -> Business Performance in 2026 | CN1: =$A$1 -> ＃ WHR Monthly Closing | DE1: =$R$1 -> Business Performance in 2026 | DF1: =$A$1 -> ＃ WHR Monthly Closing | DW1: =$R$1 -> Business Performance in 2026
A3: 1. 2026년 실적 | S3: 2. 2026년 목표 | AK3: 3. 2025년 실적 | BC3: 4. 2024년 실적 | BU3: 5. 분기별 | CN3: 6. 목표 대비 증감 | DF3: 7. 목표 대비 달성률
A4: 1) 손익계산서 | R4: * Unit : USD | S4: =$A$4 -> 1) 손익계산서 | AJ4: =$R$4 -> * Unit : USD | AK4: =$A$4 -> 1) 손익계산서 | BB4: =$R$4 -> * Unit : USD | BC4: =$A$4 -> 1) 손익계산서 | BT4: =$R$4 -> * Unit : USD | BU4: =$A$4 -> 1) 손익계산서 | CM4: =$R$4 -> * Unit : USD | CN4: =$A$4 -> 1) 손익계산서 | DE4: =$R$4 -> * Unit : USD | DF4: =$A$4 -> 1) 손익계산서
A5: Rooms | E5: Total | F5: Actual 2026 | W5: Total | X5: Budget 2026 | AO5: Total | AP5: Actual 2025 | BG5: Total | BH5: Actual 2024 | BY5: Actual 2026 | CD5: Budget 2026 | CI5: Actual 2025 | CR5: Total | CS5: Actual VS. Budget 2026 | DJ5: Total | DK5: Actual VS. Budget 2026(%)
F6: ='1) Rooms'!$AP$6 -> 3 | G6: ='1) Rooms'!G$6 -> 1 | H6: ='1) Rooms'!H$6 -> 2 | I6: ='1) Rooms'!I$6 -> 3 | J6: ='1) Rooms'!J$6 -> 4 | K6: ='1) Rooms'!K$6 -> 5 | L6: ='1) Rooms'!L$6 -> 6 | M6: ='1) Rooms'!M$6 -> 7 | N6: ='1) Rooms'!N$6 -> 8 | ... R6: ='1) Rooms'!R$6 -> 12 | X6: =$F$6 -> 3 | Y6: =$G$6 -> 1 | Z6: =$H$6 -> 2 | AA6: =$I$6 -> 3 | AB6: =$J$6 -> 4 | AC6: =$K$6 -> 5 | AD6: =$L$6 -> 6 | AE6: =$M$6 -> 7 | AF6: =$N$6 -> 8 | AG6: =$O$6 -> 9 | AH6: =$P$6 -> 10 | AI6: =$Q$6 -> 11 | AJ6: =$R$6 -> 12 | AP6: =$F$6 -> 3 | AQ6: =$G$6 -> 1 | AR6: =$H$6 -> 2 | AS6: =$I$6 -> 3 | AT6: =$J$6 -> 4 | AU6: =$K$6 -> 5 | AV6: =$L$6 -> 6 | AW6: =$M$6 -> 7 | AX6: =$N$6 -> 8 | AY6: =$O$6 -> 9 | AZ6: =$P$6 -> 10 | BA6: =$Q$6 -> 11 | BB6: =$R$6 -> 12 | BH6: =$F$6 -> 3 | BI6: =$G$6 -> 1 | BJ6: =$H$6 -> 2 | BK6: =$I$6 -> 3 | BL6: =$J$6 -> 4 | BM6: =$K$6 -> 5 | BN6: =$L$6 -> 6 | BO6: =$M$6 -> 7 | BP6: =$N$6 -> 8 | BQ6: =$O$6 -> 9 | BR6: =$P$6 -> 10 | BS6: =$Q$6 -> 11 | BT6: =$R$6 -> 12 | BY6: Total | BZ6: 1 | CA6: 2 | CB6: =BK$6 -> 3 | CC6: =BL$6 -> 4 | CD6: Total | CE6: 1 | CF6: 2 | CG6: 3 | CH6: 4 | CI6: Total | CJ6: 1 | CK6: 2 | CL6: 3 | CM6: 4 | CS6: =$F$6 -> 3 | CT6: =$G$6 -> 1 | CU6: =$H$6 -> 2 | CV6: =$I$6 -> 3 | CW6: =$J$6 -> 4 | CX6: =$K$6 -> 5 | CY6: =$L$6 -> 6 | CZ6: =$M$6 -> 7 | DA6: =$N$6 -> 8 | DB6: =$O$6 -> 9 | DC6: =$P$6 -> 10 | DD6: =$Q$6 -> 11 | DE6: =$R$6 -> 12 | DK6: =$F$6 -> 3 | DL6: =$G$6 -> 1 | DM6: =$H$6 -> 2 | DN6: =$I$6 -> 3 | DO6: =$J$6 -> 4 | DP6: =$K$6 -> 5 | DQ6: =$L$6 -> 6 | DR6: =$M$6 -> 7 | DS6: =$N$6 -> 8 | DT6: =$O$6 -> 9 | DU6: =$P$6 -> 10 | DV6: =$Q$6 -> 11 | DW6: =$R$6 -> 12
B7: Revenues | E7: =SUM(G7:R7) -> 4310538.8 | F7: =SUMPRODUCT((G$6:R$6<=F$6)*(G7:R7)) -> 4310538.8 | G7: =SUM(G8:G17) -> 1555066 | H7: =SUM(H8:H17) -> 1368148.1 | I7: =SUM(I8:I17) -> 1387324.7 | J7: =SUM(J8:J17) -> 0 | K7: =SUM(K8:K17) -> 0 | L7: =SUM(L8:L17) -> 0 | M7: =SUM(M8:M17) -> 0 | N7: =SUM(N8:N17) -> 0 | ... R7: =SUM(R8:R17) -> 0 | T7: =$B7 -> Revenues | W7: =SUM(Y7:AJ7) -> 20764818 | X7: =SUMPRODUCT((Y$6:AJ$6<=X$6)*(Y7:AJ7)) -> 4866593 | Y7: =SUM(Y8:Y17) -> 1587873 | Z7: =SUM(Z8:Z17) -> 1577895 | AA7: =SUM(AA8:AA17) -> 1700825 | AB7: =SUM(AB8:AB17) -> 1614662 | AC7: =SUM(AC8:AC17) -> 1748556 | AD7: =SUM(AD8:AD17) -> 1818668 | AE7: =SUM(AE8:AE17) -> 1875135 | AF7: =SUM(AF8:AF17) -> 1742289 | ... AJ7: =SUM(AJ8:AJ17) -> 1837282 | AL7: =$B7 -> Revenues | AO7: =SUM(AQ7:BB7) -> 19305126 | AP7: =SUMPRODUCT((AQ$6:BB$6<=AP$6)*(AQ7:BB7)) -> 4820598.7 | AQ7: =SUM(AQ8:AQ17) -> 1690312 | AR7: =SUM(AR8:AR17) -> 1513097.7 | AS7: =SUM(AS8:AS17) -> 1617189 | AT7: =SUM(AT8:AT17) -> 1565955.7 | AU7: =SUM(AU8:AU17) -> 1681619.4 | AV7: =SUM(AV8:AV17) -> 1633697 | AW7: =SUM(AW8:AW17) -> 1797674 | AX7: =SUM(AX8:AX17) -> 1724903.3 | ... BB7: =SUM(BB8:BB17) -> 1775702.2 | BD7: =$B7 -> Revenues | BG7: =SUM(BI7:BT7) -> 19418346 | BH7: =SUMPRODUCT((BI$6:BT$6<=BH$6)*(BI7:BT7)) -> 4984752 | BI7: =SUM(BI8:BI17) -> 1722276 | BJ7: =SUM(BJ8:BJ17) -> 1638619 | BK7: =SUM(BK8:BK17) -> 1623857 | BL7: =SUM(BL8:BL17) -> 1482290 | BM7: =SUM(BM8:BM17) -> 1574893 | BN7: =SUM(BN8:BN17) -> 1693245 | BO7: =SUM(BO8:BO17) -> 1840939 | BP7: =SUM(BP8:BP17) -> 1652620 | ... BT7: =SUM(BT8:BT17) -> 1743605.9 | BV7: =$B7 -> Revenues | BY7: =SUM(BZ7:CC7) -> 4310538.8 | BZ7: =SUM(G7:I7) -> 4310538.8 | CA7: =SUM(J7:L7) -> 0 | CB7: =SUM(M7:O7) -> 0 | CC7: =SUM(P7:R7) -> 0 | CD7: =SUM(CE7:CH7) -> 20764818 | CE7: =SUM(Y7:AA7) -> 4866593 | CF7: =SUM(AB7:AD7) -> 5181886 | CG7: =SUM(AE7:AG7) -> 5366212 | CH7: =SUM(AH7:AJ7) -> 5350127 | CI7: =SUM(CJ7:CM7) -> 19305126 | CJ7: =SUM(AQ7:AS7) -> 4820598.7 | CK7: =SUM(AT7:AV7) -> 4881272.1 | CL7: =SUM(AW7:AY7) -> 5049222.8 | CM7: =SUM(AZ7:BB7) -> 4554032.9 | CO7: =$B7 -> Revenues | CR7: =E7-W7 -> -16454279 | CS7: =F7-X7 -> -556054.21 | CT7: =G7-Y7 -> -32807 | CU7: =H7-Z7 -> -209746.88 | CV7: =I7-AA7 -> -313500.33 | CW7: =J7-AB7 -> -1614662 | CX7: =K7-AC7 -> -1748556 | CY7: =L7-AD7 -> -1818668 | ... DE7: =R7-AJ7 -> -1837282 | DG7: =$B7 -> Revenues | DJ7: =IFERROR(((E7-W7)/ABS(W7))+1,"") -> 0.20758857 | DK7: =IFERROR(((F7-X7)/ABS(X7))+1,"") -> 0.88574056 | DL7: =IFERROR(((G7-Y7)/ABS(Y7))+1,"") -> 0.97933903 | DM7: =IFERROR(((H7-Z7)/ABS(Z7))+1,"") -> 0.86707171 | DN7: =IFERROR(((I7-AA7)/ABS(AA7))+1,"") -> 0.81567749 | DO7: =IFERROR(((J7-AB7)/ABS(AB7))+1,"") -> 0 | DP7: =IFERROR(((K7-AC7)/ABS(AC7))+1,"") -> 0 | DQ7: =IFERROR(((L7-AD7)/ABS(AD7))+1,"") -> 0 | ... DW7: =IFERROR(((R7-AJ7)/ABS(AJ7))+1,"") -> 0
C8: Rooms | E8: =SUM(G8:R8) -> 3021745.7 | F8: =SUMPRODUCT((G$6:R$6<=F$6)*(G8:R8)) -> 3021745.7 | G8: ='⑴ IS(Subtotal-Dert.)'!G8 -> 1092651 | H8: ='⑴ IS(Subtotal-Dert.)'!H8 -> 955163.12 | I8: ='⑴ IS(Subtotal-Dert.)'!I8 -> 973931.53 | J8: ='⑴ IS(Subtotal-Dert.)'!J8 -> 0 | K8: ='⑴ IS(Subtotal-Dert.)'!K8 -> 0 | L8: ='⑴ IS(Subtotal-Dert.)'!L8 -> 0 | M8: ='⑴ IS(Subtotal-Dert.)'!M8 -> 0 | N8: ='⑴ IS(Subtotal-Dert.)'!N8 -> 0 | ... R8: ='⑴ IS(Subtotal-Dert.)'!R8 -> 0 | U8: =$C8 -> Rooms | W8: =SUM(Y8:AJ8) -> 15059136 | X8: =SUMPRODUCT((Y$6:AJ$6<=X$6)*(Y8:AJ8)) -> 3484775 | Y8: ='⑴ IS(Subtotal-Dert.)'!Y8 -> 1117500 | Z8: ='⑴ IS(Subtotal-Dert.)'!Z8 -> 1140150 | AA8: ='⑴ IS(Subtotal-Dert.)'!AA8 -> 1227125 | AB8: ='⑴ IS(Subtotal-Dert.)'!AB8 -> 1139688 | AC8: ='⑴ IS(Subtotal-Dert.)'!AC8 -> 1264550 | AD8: ='⑴ IS(Subtotal-Dert.)'!AD8 -> 1297355 | AE8: ='⑴ IS(Subtotal-Dert.)'!AE8 -> 1385310 | AF8: ='⑴ IS(Subtotal-Dert.)'!AF8 -> 1278058 | ... AJ8: ='⑴ IS(Subtotal-Dert.)'!AJ8 -> 1397900 | AM8: =$C8 -> Rooms | AO8: =SUM(AQ8:BB8) -> 13883262 | AP8: =SUMPRODUCT((AQ$6:BB$6<=AP$6)*(AQ8:BB8)) -> 3558306.8 | AQ8: ='⑴ IS(Subtotal-Dert.)'!AQ8 -> 1212787.7 | AR8: ='⑴ IS(Subtotal-Dert.)'!AR8 -> 1134012.4 | AS8: ='⑴ IS(Subtotal-Dert.)'!AS8 -> 1211506.7 | AT8: ='⑴ IS(Subtotal-Dert.)'!AT8 -> 1156927.7 | AU8: ='⑴ IS(Subtotal-Dert.)'!AU8 -> 1179641.1 | AV8: ='⑴ IS(Subtotal-Dert.)'!AV8 -> 1214914.9 | AW8: ='⑴ IS(Subtotal-Dert.)'!AW8 -> 1339566.5 | AX8: ='⑴ IS(Subtotal-Dert.)'!AX8 -> 1272731 | ... BB8: ='⑴ IS(Subtotal-Dert.)'!BB8 -> 1221383.3 | BE8: =$C8 -> Rooms | BG8: =SUM(BI8:BT8) -> 14564421 | BH8: =SUMPRODUCT((BI$6:BT$6<=BH$6)*(BI8:BT8)) -> 3694560 | BI8: ='⑴ IS(Subtotal-Dert.)'!BI8 -> 1288486 | BJ8: ='⑴ IS(Subtotal-Dert.)'!BJ8 -> 1227343 | BK8: ='⑴ IS(Subtotal-Dert.)'!BK8 -> 1178731 | BL8: ='⑴ IS(Subtotal-Dert.)'!BL8 -> 1097294 | BM8: ='⑴ IS(Subtotal-Dert.)'!BM8 -> 1177323 | BN8: ='⑴ IS(Subtotal-Dert.)'!BN8 -> 1291824 | BO8: ='⑴ IS(Subtotal-Dert.)'!BO8 -> 1427372 | BP8: ='⑴ IS(Subtotal-Dert.)'!BP8 -> 1265827 | ... BT8: ='⑴ IS(Subtotal-Dert.)'!BT8 -> 1330894.7 | BW8: =$C8 -> Rooms | BY8: =SUM(BZ8:CC8) -> 3021745.7 | BZ8: =SUM(G8:I8) -> 3021745.7 | CA8: =SUM(J8:L8) -> 0 | CB8: =SUM(M8:O8) -> 0 | CC8: =SUM(P8:R8) -> 0 | CD8: =SUM(CE8:CH8) -> 15059136 | CE8: =SUM(Y8:AA8) -> 3484775 | CF8: =SUM(AB8:AD8) -> 3701593 | CG8: =SUM(AE8:AG8) -> 3947668 | CH8: =SUM(AH8:AJ8) -> 3925100 | CI8: =SUM(CJ8:CM8) -> 13883262 | CJ8: =SUM(AQ8:AS8) -> 3558306.8 | CK8: =SUM(AT8:AV8) -> 3551483.6 | CL8: =SUM(AW8:AY8) -> 3670824.1 | CM8: =SUM(AZ8:BB8) -> 3102647.5 | CP8: =$C8 -> Rooms | CR8: =E8-W8 -> -12037390 | CS8: =F8-X8 -> -463029.35 | CT8: =G8-Y8 -> -24849 | CU8: =H8-Z8 -> -184986.88 | CV8: =I8-AA8 -> -253193.47 | CW8: =J8-AB8 -> -1139688 | CX8: =K8-AC8 -> -1264550 | CY8: =L8-AD8 -> -1297355 | ... DE8: =R8-AJ8 -> -1397900 | DH8: =$C8 -> Rooms | DJ8: =IFERROR(((E8-W8)/ABS(W8))+1,"") -> 0.20065863 | DK8: =IFERROR(((F8-X8)/ABS(X8))+1,"") -> 0.86712791 | DL8: =IFERROR(((G8-Y8)/ABS(Y8))+1,"") -> 0.97776376 | DM8: =IFERROR(((H8-Z8)/ABS(Z8))+1,"") -> 0.83775216 | DN8: =IFERROR(((I8-AA8)/ABS(AA8))+1,"") -> 0.79366937 | DO8: =IFERROR(((J8-AB8)/ABS(AB8))+1,"") -> 0 | DP8: =IFERROR(((K8-AC8)/ABS(AC8))+1,"") -> 0 | DQ8: =IFERROR(((L8-AD8)/ABS(AD8))+1,"") -> 0 | ... DW8: =IFERROR(((R8-AJ8)/ABS(AJ8))+1,"") -> 0
C9: Food and beverage | E9: =SUM(G9:R9) -> 452624.44 | F9: =SUMPRODUCT((G$6:R$6<=F$6)*(G9:R9)) -> 452624.44 | G9: ='⑴ IS(Subtotal-Dert.)'!G9 -> 143277 | H9: ='⑴ IS(Subtotal-Dert.)'!H9 -> 151934 | I9: ='⑴ IS(Subtotal-Dert.)'!I9 -> 157413.44 | J9: ='⑴ IS(Subtotal-Dert.)'!J9 -> 0 | K9: ='⑴ IS(Subtotal-Dert.)'!K9 -> 0 | L9: ='⑴ IS(Subtotal-Dert.)'!L9 -> 0 | M9: ='⑴ IS(Subtotal-Dert.)'!M9 -> 0 | N9: ='⑴ IS(Subtotal-Dert.)'!N9 -> 0 | ... R9: ='⑴ IS(Subtotal-Dert.)'!R9 -> 0 | U9: =$C9 -> Food and beverage | W9: =SUM(Y9:AJ9) -> 2236006 | X9: =SUMPRODUCT((Y$6:AJ$6<=X$6)*(Y9:AJ9)) -> 539034 | Y9: ='⑴ IS(Subtotal-Dert.)'!Y9 -> 177257 | Z9: ='⑴ IS(Subtotal-Dert.)'!Z9 -> 176864 | AA9: ='⑴ IS(Subtotal-Dert.)'!AA9 -> 184913 | AB9: ='⑴ IS(Subtotal-Dert.)'!AB9 -> 185136 | AC9: ='⑴ IS(Subtotal-Dert.)'!AC9 -> 185328 | AD9: ='⑴ IS(Subtotal-Dert.)'!AD9 -> 191207 | AE9: ='⑴ IS(Subtotal-Dert.)'!AE9 -> 189535 | AF9: ='⑴ IS(Subtotal-Dert.)'!AF9 -> 173361 | ... AJ9: ='⑴ IS(Subtotal-Dert.)'!AJ9 -> 194035 | AM9: =$C9 -> Food and beverage | AO9: =SUM(AQ9:BB9) -> 2280998.7 | AP9: =SUMPRODUCT((AQ$6:BB$6<=AP$6)*(AQ9:BB9)) -> 520035.91 | AQ9: ='⑴ IS(Subtotal-Dert.)'!AQ9 -> 183550.31 | AR9: ='⑴ IS(Subtotal-Dert.)'!AR9 -> 162416.29 | AS9: ='⑴ IS(Subtotal-Dert.)'!AS9 -> 174069.31 | AT9: ='⑴ IS(Subtotal-Dert.)'!AT9 -> 163899.72 | AU9: ='⑴ IS(Subtotal-Dert.)'!AU9 -> 189888.48 | AV9: ='⑴ IS(Subtotal-Dert.)'!AV9 -> 176917.5 | AW9: ='⑴ IS(Subtotal-Dert.)'!AW9 -> 214127.23 | AX9: ='⑴ IS(Subtotal-Dert.)'!AX9 -> 208175.6 | ... BB9: ='⑴ IS(Subtotal-Dert.)'!BB9 -> 222965.11 | BE9: =$C9 -> Food and beverage | BG9: =SUM(BI9:BT9) -> 2088939.6 | BH9: =SUMPRODUCT((BI$6:BT$6<=BH$6)*(BI9:BT9)) -> 479593 | BI9: ='⑴ IS(Subtotal-Dert.)'!BI9 -> 153484 | BJ9: ='⑴ IS(Subtotal-Dert.)'!BJ9 -> 153391 | BK9: ='⑴ IS(Subtotal-Dert.)'!BK9 -> 172718 | BL9: ='⑴ IS(Subtotal-Dert.)'!BL9 -> 153572 | BM9: ='⑴ IS(Subtotal-Dert.)'!BM9 -> 176148 | BN9: ='⑴ IS(Subtotal-Dert.)'!BN9 -> 181929 | BO9: ='⑴ IS(Subtotal-Dert.)'!BO9 -> 180166 | BP9: ='⑴ IS(Subtotal-Dert.)'!BP9 -> 179352 | ... BT9: ='⑴ IS(Subtotal-Dert.)'!BT9 -> 195678.8 | BW9: =$C9 -> Food and beverage | BY9: =SUM(BZ9:CC9) -> 452624.44 | BZ9: =SUM(G9:I9) -> 452624.44 | CA9: =SUM(J9:L9) -> 0 | CB9: =SUM(M9:O9) -> 0 | CC9: =SUM(P9:R9) -> 0 | CD9: =SUM(CE9:CH9) -> 2236006 | CE9: =SUM(Y9:AA9) -> 539034 | CF9: =SUM(AB9:AD9) -> 561671 | CG9: =SUM(AE9:AG9) -> 540875 | CH9: =SUM(AH9:AJ9) -> 594426 | CI9: =SUM(CJ9:CM9) -> 2280998.7 | CJ9: =SUM(AQ9:AS9) -> 520035.91 | CK9: =SUM(AT9:AV9) -> 530705.7 | CL9: =SUM(AW9:AY9) -> 645078.06 | CM9: =SUM(AZ9:BB9) -> 585179.02 | CP9: =$C9 -> Food and beverage | CR9: =E9-W9 -> -1783381.6 | CS9: =F9-X9 -> -86409.56 | CT9: =G9-Y9 -> -33980 | CU9: =H9-Z9 -> -24930 | CV9: =I9-AA9 -> -27499.56 | CW9: =J9-AB9 -> -185136 | CX9: =K9-AC9 -> -185328 | CY9: =L9-AD9 -> -191207 | ... DE9: =R9-AJ9 -> -194035 | DH9: =$C9 -> Food and beverage | DJ9: =IFERROR(((E9-W9)/ABS(W9))+1,"") -> 0.20242541 | DK9: =IFERROR(((F9-X9)/ABS(X9))+1,"") -> 0.83969553 | DL9: =IFERROR(((G9-Y9)/ABS(Y9))+1,"") -> 0.80830094 | DM9: =IFERROR(((H9-Z9)/ABS(Z9))+1,"") -> 0.85904424 | DN9: =IFERROR(((I9-AA9)/ABS(AA9))+1,"") -> 0.85128379 | DO9: =IFERROR(((J9-AB9)/ABS(AB9))+1,"") -> 0 | DP9: =IFERROR(((K9-AC9)/ABS(AC9))+1,"") -> 0 | DQ9: =IFERROR(((L9-AD9)/ABS(AD9))+1,"") -> 0 | ... DW9: =IFERROR(((R9-AJ9)/ABS(AJ9))+1,"") -> 0
C10: Comunications | E10: =SUM(G10:R10) -> 0 | F10: =SUMPRODUCT((G$6:R$6<=F$6)*(G10:R10)) -> 0 | G10: ='⑴ IS(Subtotal-Dert.)'!G10 -> 0 | H10: ='⑴ IS(Subtotal-Dert.)'!H10 -> 0 | I10: ='⑴ IS(Subtotal-Dert.)'!I10 -> 0 | J10: ='⑴ IS(Subtotal-Dert.)'!J10 -> 0 | K10: ='⑴ IS(Subtotal-Dert.)'!K10 -> 0 | L10: ='⑴ IS(Subtotal-Dert.)'!L10 -> 0 | M10: ='⑴ IS(Subtotal-Dert.)'!M10 -> 0 | N10: ='⑴ IS(Subtotal-Dert.)'!N10 -> 0 | ... R10: ='⑴ IS(Subtotal-Dert.)'!R10 -> 0 | U10: =$C10 -> Comunications | W10: =SUM(Y10:AJ10) -> 0 | X10: =SUMPRODUCT((Y$6:AJ$6<=X$6)*(Y10:AJ10)) -> 0 | Y10: ='⑴ IS(Subtotal-Dert.)'!Y10 -> 0 | Z10: ='⑴ IS(Subtotal-Dert.)'!Z10 -> 0 | AA10: ='⑴ IS(Subtotal-Dert.)'!AA10 -> 0 | AB10: ='⑴ IS(Subtotal-Dert.)'!AB10 -> 0 | AC10: ='⑴ IS(Subtotal-Dert.)'!AC10 -> 0 | AD10: ='⑴ IS(Subtotal-Dert.)'!AD10 -> 0 | AE10: ='⑴ IS(Subtotal-Dert.)'!AE10 -> 0 | AF10: ='⑴ IS(Subtotal-Dert.)'!AF10 -> 0 | ... AJ10: ='⑴ IS(Subtotal-Dert.)'!AJ10 -> 0 | AM10: =$C10 -> Comunications | AO10: =SUM(AQ10:BB10) -> 299 | AP10: =SUMPRODUCT((AQ$6:BB$6<=AP$6)*(AQ10:BB10)) -> 191 | AQ10: ='⑴ IS(Subtotal-Dert.)'!AQ10 -> 147 | AR10: ='⑴ IS(Subtotal-Dert.)'!AR10 -> 0 | AS10: ='⑴ IS(Subtotal-Dert.)'!AS10 -> 44 | AT10: ='⑴ IS(Subtotal-Dert.)'!AT10 -> 40 | AU10: ='⑴ IS(Subtotal-Dert.)'!AU10 -> 0 | AV10: ='⑴ IS(Subtotal-Dert.)'!AV10 -> 68 | AW10: ='⑴ IS(Subtotal-Dert.)'!AW10 -> 0 | AX10: ='⑴ IS(Subtotal-Dert.)'!AX10 -> 0 | ... BB10: ='⑴ IS(Subtotal-Dert.)'!BB10 -> 0 | BE10: =$C10 -> Comunications | BG10: =SUM(BI10:BT10) -> 961 | BH10: =SUMPRODUCT((BI$6:BT$6<=BH$6)*(BI10:BT10)) -> 49 | BI10: ='⑴ IS(Subtotal-Dert.)'!BI10 -> 6 | BJ10: ='⑴ IS(Subtotal-Dert.)'!BJ10 -> 8 | BK10: ='⑴ IS(Subtotal-Dert.)'!BK10 -> 35 | BL10: ='⑴ IS(Subtotal-Dert.)'!BL10 -> 162 | BM10: ='⑴ IS(Subtotal-Dert.)'!BM10 -> 0 | BN10: ='⑴ IS(Subtotal-Dert.)'!BN10 -> 495 | BO10: ='⑴ IS(Subtotal-Dert.)'!BO10 -> 58 | BP10: ='⑴ IS(Subtotal-Dert.)'!BP10 -> 54 | ... BT10: ='⑴ IS(Subtotal-Dert.)'!BT10 -> 0 | BW10: =$C10 -> Comunications | BY10: =SUM(BZ10:CC10) -> 0 | BZ10: =SUM(G10:I10) -> 0 | CA10: =SUM(J10:L10) -> 0 | CB10: =SUM(M10:O10) -> 0 | CC10: =SUM(P10:R10) -> 0 | CD10: =SUM(CE10:CH10) -> 0 | CE10: =SUM(Y10:AA10) -> 0 | CF10: =SUM(AB10:AD10) -> 0 | CG10: =SUM(AE10:AG10) -> 0 | CH10: =SUM(AH10:AJ10) -> 0 | CI10: =SUM(CJ10:CM10) -> 299 | CJ10: =SUM(AQ10:AS10) -> 191 | CK10: =SUM(AT10:AV10) -> 108 | CL10: =SUM(AW10:AY10) -> 0 | CM10: =SUM(AZ10:BB10) -> 0 | CP10: =$C10 -> Comunications | CR10: =E10-W10 -> 0 | CS10: =F10-X10 -> 0 | CT10: =G10-Y10 -> 0 | CU10: =H10-Z10 -> 0 | CV10: =I10-AA10 -> 0 | CW10: =J10-AB10 -> 0 | CX10: =K10-AC10 -> 0 | CY10: =L10-AD10 -> 0 | ... DE10: =R10-AJ10 -> 0 | DH10: =$C10 -> Comunications | DJ10: =IFERROR(((E10-W10)/ABS(W10))+1,"") | DK10: =IFERROR(((F10-X10)/ABS(X10))+1,"") | DL10: =IFERROR(((G10-Y10)/ABS(Y10))+1,"") | DM10: =IFERROR(((H10-Z10)/ABS(Z10))+1,"") | DN10: =IFERROR(((I10-AA10)/ABS(AA10))+1,"") | DO10: =IFERROR(((J10-AB10)/ABS(AB10))+1,"") | DP10: =IFERROR(((K10-AC10)/ABS(AC10))+1,"") | DQ10: =IFERROR(((L10-AD10)/ABS(AD10))+1,"") | ... DW10: =IFERROR(((R10-AJ10)/ABS(AJ10))+1,"")
C11: Parking | E11: =SUM(G11:R11) -> 177883.01 | F11: =SUMPRODUCT((G$6:R$6<=F$6)*(G11:R11)) -> 177883.01 | G11: ='⑴ IS(Subtotal-Dert.)'!G11 -> 64204 | H11: ='⑴ IS(Subtotal-Dert.)'!H11 -> 51471 | I11: ='⑴ IS(Subtotal-Dert.)'!I11 -> 62208.01 | J11: ='⑴ IS(Subtotal-Dert.)'!J11 -> 0 | K11: ='⑴ IS(Subtotal-Dert.)'!K11 -> 0 | L11: ='⑴ IS(Subtotal-Dert.)'!L11 -> 0 | M11: ='⑴ IS(Subtotal-Dert.)'!M11 -> 0 | N11: ='⑴ IS(Subtotal-Dert.)'!N11 -> 0 | ... R11: ='⑴ IS(Subtotal-Dert.)'!R11 -> 0 | U11: =$C11 -> Parking | W11: =SUM(Y11:AJ11) -> 976214 | X11: =SUMPRODUCT((Y$6:AJ$6<=X$6)*(Y11:AJ11)) -> 234768 | Y11: ='⑴ IS(Subtotal-Dert.)'!Y11 -> 85368 | Z11: ='⑴ IS(Subtotal-Dert.)'!Z11 -> 67000 | AA11: ='⑴ IS(Subtotal-Dert.)'!AA11 -> 82400 | AB11: ='⑴ IS(Subtotal-Dert.)'!AB11 -> 83184 | AC11: ='⑴ IS(Subtotal-Dert.)'!AC11 -> 86096 | AD11: ='⑴ IS(Subtotal-Dert.)'!AD11 -> 86600 | AE11: ='⑴ IS(Subtotal-Dert.)'!AE11 -> 92200 | AF11: ='⑴ IS(Subtotal-Dert.)'!AF11 -> 87496 | ... AJ11: ='⑴ IS(Subtotal-Dert.)'!AJ11 -> 66762 | AM11: =$C11 -> Parking | AO11: =SUM(AQ11:BB11) -> 944489.61 | AP11: =SUMPRODUCT((AQ$6:BB$6<=AP$6)*(AQ11:BB11)) -> 211825.31 | AQ11: ='⑴ IS(Subtotal-Dert.)'!AQ11 -> 81862.54 | AR11: ='⑴ IS(Subtotal-Dert.)'!AR11 -> 65661.57 | AS11: ='⑴ IS(Subtotal-Dert.)'!AS11 -> 64301.2 | AT11: ='⑴ IS(Subtotal-Dert.)'!AT11 -> 60137.47 | AU11: ='⑴ IS(Subtotal-Dert.)'!AU11 -> 145880.28 | AV11: ='⑴ IS(Subtotal-Dert.)'!AV11 -> 81213.36 | AW11: ='⑴ IS(Subtotal-Dert.)'!AW11 -> 88077.57 | AX11: ='⑴ IS(Subtotal-Dert.)'!AX11 -> 79978.93 | ... BB11: ='⑴ IS(Subtotal-Dert.)'!BB11 -> 75157.47 | BE11: =$C11 -> Parking | BG11: =SUM(BI11:BT11) -> 790540.92 | BH11: =SUMPRODUCT((BI$6:BT$6<=BH$6)*(BI11:BT11)) -> 203919 | BI11: ='⑴ IS(Subtotal-Dert.)'!BI11 -> 68053 | BJ11: ='⑴ IS(Subtotal-Dert.)'!BJ11 -> 64829 | BK11: ='⑴ IS(Subtotal-Dert.)'!BK11 -> 71037 | BL11: ='⑴ IS(Subtotal-Dert.)'!BL11 -> 66006 | BM11: ='⑴ IS(Subtotal-Dert.)'!BM11 -> 67517 | BN11: ='⑴ IS(Subtotal-Dert.)'!BN11 -> 70167 | BO11: ='⑴ IS(Subtotal-Dert.)'!BO11 -> 74562 | BP11: ='⑴ IS(Subtotal-Dert.)'!BP11 -> 68617 | ... BT11: ='⑴ IS(Subtotal-Dert.)'!BT11 -> 65144.82 | BW11: =$C11 -> Parking | BY11: =SUM(BZ11:CC11) -> 177883.01 | BZ11: =SUM(G11:I11) -> 177883.01 | CA11: =SUM(J11:L11) -> 0 | CB11: =SUM(M11:O11) -> 0 | CC11: =SUM(P11:R11) -> 0 | CD11: =SUM(CE11:CH11) -> 976214 | CE11: =SUM(Y11:AA11) -> 234768 | CF11: =SUM(AB11:AD11) -> 255880 | CG11: =SUM(AE11:AG11) -> 257504 | CH11: =SUM(AH11:AJ11) -> 228062 | CI11: =SUM(CJ11:CM11) -> 944489.61 | CJ11: =SUM(AQ11:AS11) -> 211825.31 | CK11: =SUM(AT11:AV11) -> 287231.11 | CL11: =SUM(AW11:AY11) -> 240250.1 | CM11: =SUM(AZ11:BB11) -> 205183.09 | CP11: =$C11 -> Parking | CR11: =E11-W11 -> -798330.99 | CS11: =F11-X11 -> -56884.99 | CT11: =G11-Y11 -> -21164 | CU11: =H11-Z11 -> -15529 | CV11: =I11-AA11 -> -20191.99 | CW11: =J11-AB11 -> -83184 | CX11: =K11-AC11 -> -86096 | CY11: =L11-AD11 -> -86600 | ... DE11: =R11-AJ11 -> -66762 | DH11: =$C11 -> Parking | DJ11: =IFERROR(((E11-W11)/ABS(W11))+1,"") -> 0.18221723 | DK11: =IFERROR(((F11-X11)/ABS(X11))+1,"") -> 0.757697 | DL11: =IFERROR(((G11-Y11)/ABS(Y11))+1,"") -> 0.75208509 | DM11: =IFERROR(((H11-Z11)/ABS(Z11))+1,"") -> 0.76822388 | DN11: =IFERROR(((I11-AA11)/ABS(AA11))+1,"") -> 0.75495158 | DO11: =IFERROR(((J11-AB11)/ABS(AB11))+1,"") -> 0 | DP11: =IFERROR(((K11-AC11)/ABS(AC11))+1,"") -> 0 | DQ11: =IFERROR(((L11-AD11)/ABS(AD11))+1,"") -> 0 | ... DW11: =IFERROR(((R11-AJ11)/ABS(AJ11))+1,"") -> 0
C12: Other operated | E12: =SUM(G12:R12) -> 499376.01 | F12: =SUMPRODUCT((G$6:R$6<=F$6)*(G12:R12)) -> 499376.01 | G12: ='⑴ IS(Subtotal-Dert.)'!G12 -> 199082 | H12: ='⑴ IS(Subtotal-Dert.)'!H12 -> 156188 | I12: ='⑴ IS(Subtotal-Dert.)'!I12 -> 144106.01 | J12: ='⑴ IS(Subtotal-Dert.)'!J12 -> 0 | K12: ='⑴ IS(Subtotal-Dert.)'!K12 -> 0 | L12: ='⑴ IS(Subtotal-Dert.)'!L12 -> 0 | M12: ='⑴ IS(Subtotal-Dert.)'!M12 -> 0 | N12: ='⑴ IS(Subtotal-Dert.)'!N12 -> 0 | ... R12: ='⑴ IS(Subtotal-Dert.)'!R12 -> 0 | U12: =$C12 -> Other operated | W12: =SUM(Y12:AJ12) -> 1869462 | X12: =SUMPRODUCT((Y$6:AJ$6<=X$6)*(Y12:AJ12)) -> 452016 | Y12: ='⑴ IS(Subtotal-Dert.)'!Y12 -> 155748 | Z12: ='⑴ IS(Subtotal-Dert.)'!Z12 -> 141881 | AA12: ='⑴ IS(Subtotal-Dert.)'!AA12 -> 154387 | AB12: ='⑴ IS(Subtotal-Dert.)'!AB12 -> 154654 | AC12: ='⑴ IS(Subtotal-Dert.)'!AC12 -> 160582 | AD12: ='⑴ IS(Subtotal-Dert.)'!AD12 -> 191506 | AE12: ='⑴ IS(Subtotal-Dert.)'!AE12 -> 156090 | AF12: ='⑴ IS(Subtotal-Dert.)'!AF12 -> 151374 | ... AJ12: ='⑴ IS(Subtotal-Dert.)'!AJ12 -> 126585 | AM12: =$C12 -> Other operated | AO12: =SUM(AQ12:BB12) -> 1557235.3 | AP12: =SUMPRODUCT((AQ$6:BB$6<=AP$6)*(AQ12:BB12)) -> 380093.12 | AQ12: ='⑴ IS(Subtotal-Dert.)'!AQ12 -> 162088.54 | AR12: ='⑴ IS(Subtotal-Dert.)'!AR12 -> 99660.1 | AS12: ='⑴ IS(Subtotal-Dert.)'!AS12 -> 118344.48 | AT12: ='⑴ IS(Subtotal-Dert.)'!AT12 -> 135193.66 | AU12: ='⑴ IS(Subtotal-Dert.)'!AU12 -> 113920.2 | AV12: ='⑴ IS(Subtotal-Dert.)'!AV12 -> 106163.92 | AW12: ='⑴ IS(Subtotal-Dert.)'!AW12 -> 99607.76 | AX12: ='⑴ IS(Subtotal-Dert.)'!AX12 -> 107769.38 | ... BB12: ='⑴ IS(Subtotal-Dert.)'!BB12 -> 203836.33 | BE12: =$C12 -> Other operated | BG12: =SUM(BI12:BT12) -> 1320842.7 | BH12: =SUMPRODUCT((BI$6:BT$6<=BH$6)*(BI12:BT12)) -> 376618 | BI12: ='⑴ IS(Subtotal-Dert.)'!BI12 -> 133903 | BJ12: ='⑴ IS(Subtotal-Dert.)'!BJ12 -> 117453 | BK12: ='⑴ IS(Subtotal-Dert.)'!BK12 -> 125262 | BL12: ='⑴ IS(Subtotal-Dert.)'!BL12 -> 120653 | BM12: ='⑴ IS(Subtotal-Dert.)'!BM12 -> 107714 | BN12: ='⑴ IS(Subtotal-Dert.)'!BN12 -> 102762 | BO12: ='⑴ IS(Subtotal-Dert.)'!BO12 -> 109551 | BP12: ='⑴ IS(Subtotal-Dert.)'!BP12 -> 86926 | ... BT12: ='⑴ IS(Subtotal-Dert.)'!BT12 -> 114551.72 | BW12: =$C12 -> Other operated | BY12: =SUM(BZ12:CC12) -> 499376.01 | BZ12: =SUM(G12:I12) -> 499376.01 | CA12: =SUM(J12:L12) -> 0 | CB12: =SUM(M12:O12) -> 0 | CC12: =SUM(P12:R12) -> 0 | CD12: =SUM(CE12:CH12) -> 1869462 | CE12: =SUM(Y12:AA12) -> 452016 | CF12: =SUM(AB12:AD12) -> 506742 | CG12: =SUM(AE12:AG12) -> 464165 | CH12: =SUM(AH12:AJ12) -> 446539 | CI12: =SUM(CJ12:CM12) -> 1557235.3 | CJ12: =SUM(AQ12:AS12) -> 380093.12 | CK12: =SUM(AT12:AV12) -> 355277.78 | CL12: =SUM(AW12:AY12) -> 325567.91 | CM12: =SUM(AZ12:BB12) -> 496296.52 | CP12: =$C12 -> Other operated | CR12: =E12-W12 -> -1370086 | CS12: =F12-X12 -> 47360.01 | CT12: =G12-Y12 -> 43334 | CU12: =H12-Z12 -> 14307 | CV12: =I12-AA12 -> -10280.99 | CW12: =J12-AB12 -> -154654 | CX12: =K12-AC12 -> -160582 | CY12: =L12-AD12 -> -191506 | ... DE12: =R12-AJ12 -> -126585 | DH12: =$C12 -> Other operated | DJ12: =IFERROR(((E12-W12)/ABS(W12))+1,"") -> 0.26712285 | DK12: =IFERROR(((F12-X12)/ABS(X12))+1,"") -> 1.1047751 | DL12: =IFERROR(((G12-Y12)/ABS(Y12))+1,"") -> 1.2782315 | DM12: =IFERROR(((H12-Z12)/ABS(Z12))+1,"") -> 1.100838 | DN12: =IFERROR(((I12-AA12)/ABS(AA12))+1,"") -> 0.93340767 | DO12: =IFERROR(((J12-AB12)/ABS(AB12))+1,"") -> 0 | DP12: =IFERROR(((K12-AC12)/ABS(AC12))+1,"") -> 0 | DQ12: =IFERROR(((L12-AD12)/ABS(AD12))+1,"") -> 0 | ... DW12: =IFERROR(((R12-AJ12)/ABS(AJ12))+1,"") -> 0
C13: Rent and other | E13: =SUM(G13:R13) -> 158909.68 | F13: =SUMPRODUCT((G$6:R$6<=F$6)*(G13:R13)) -> 158909.68 | G13: ='⑴ IS(Subtotal-Dert.)'!G13 -> 55852 | H13: ='⑴ IS(Subtotal-Dert.)'!H13 -> 53392 | I13: ='⑴ IS(Subtotal-Dert.)'!I13 -> 49665.68 | J13: ='⑴ IS(Subtotal-Dert.)'!J13 -> 0 | K13: ='⑴ IS(Subtotal-Dert.)'!K13 -> 0 | L13: ='⑴ IS(Subtotal-Dert.)'!L13 -> 0 | M13: ='⑴ IS(Subtotal-Dert.)'!M13 -> 0 | N13: ='⑴ IS(Subtotal-Dert.)'!N13 -> 0 | ... R13: ='⑴ IS(Subtotal-Dert.)'!R13 -> 0 | U13: =$C13 -> Rent and other | W13: =SUM(Y13:AJ13) -> 624000 | X13: =SUMPRODUCT((Y$6:AJ$6<=X$6)*(Y13:AJ13)) -> 156000 | Y13: ='⑴ IS(Subtotal-Dert.)'!Y13 -> 52000 | Z13: ='⑴ IS(Subtotal-Dert.)'!Z13 -> 52000 | AA13: ='⑴ IS(Subtotal-Dert.)'!AA13 -> 52000 | AB13: ='⑴ IS(Subtotal-Dert.)'!AB13 -> 52000 | AC13: ='⑴ IS(Subtotal-Dert.)'!AC13 -> 52000 | AD13: ='⑴ IS(Subtotal-Dert.)'!AD13 -> 52000 | AE13: ='⑴ IS(Subtotal-Dert.)'!AE13 -> 52000 | AF13: ='⑴ IS(Subtotal-Dert.)'!AF13 -> 52000 | ... AJ13: ='⑴ IS(Subtotal-Dert.)'!AJ13 -> 52000 | AM13: =$C13 -> Rent and other | AO13: =SUM(AQ13:BB13) -> 638841.85 | AP13: =SUMPRODUCT((AQ$6:BB$6<=AP$6)*(AQ13:BB13)) -> 150146.53 | AQ13: ='⑴ IS(Subtotal-Dert.)'!AQ13 -> 49875.91 | AR13: ='⑴ IS(Subtotal-Dert.)'!AR13 -> 51347.33 | AS13: ='⑴ IS(Subtotal-Dert.)'!AS13 -> 48923.29 | AT13: ='⑴ IS(Subtotal-Dert.)'!AT13 -> 49757.16 | AU13: ='⑴ IS(Subtotal-Dert.)'!AU13 -> 52289.36 | AV13: ='⑴ IS(Subtotal-Dert.)'!AV13 -> 54419.32 | AW13: ='⑴ IS(Subtotal-Dert.)'!AW13 -> 56294.94 | AX13: ='⑴ IS(Subtotal-Dert.)'!AX13 -> 56248.39 | ... BB13: ='⑴ IS(Subtotal-Dert.)'!BB13 -> 52359.99 | BE13: =$C13 -> Rent and other | BG13: =SUM(BI13:BT13) -> 652641.2 | BH13: =SUMPRODUCT((BI$6:BT$6<=BH$6)*(BI13:BT13)) -> 230013 | BI13: ='⑴ IS(Subtotal-Dert.)'!BI13 -> 78344 | BJ13: ='⑴ IS(Subtotal-Dert.)'!BJ13 -> 75595 | BK13: ='⑴ IS(Subtotal-Dert.)'!BK13 -> 76074 | BL13: ='⑴ IS(Subtotal-Dert.)'!BL13 -> 44603 | BM13: ='⑴ IS(Subtotal-Dert.)'!BM13 -> 46191 | BN13: ='⑴ IS(Subtotal-Dert.)'!BN13 -> 46068 | BO13: ='⑴ IS(Subtotal-Dert.)'!BO13 -> 49230 | BP13: ='⑴ IS(Subtotal-Dert.)'!BP13 -> 51844 | ... BT13: ='⑴ IS(Subtotal-Dert.)'!BT13 -> 37335.85 | BW13: =$C13 -> Rent and other | BY13: =SUM(BZ13:CC13) -> 158909.68 | BZ13: =SUM(G13:I13) -> 158909.68 | CA13: =SUM(J13:L13) -> 0 | CB13: =SUM(M13:O13) -> 0 | CC13: =SUM(P13:R13) -> 0 | CD13: =SUM(CE13:CH13) -> 624000 | CE13: =SUM(Y13:AA13) -> 156000 | CF13: =SUM(AB13:AD13) -> 156000 | CG13: =SUM(AE13:AG13) -> 156000 | CH13: =SUM(AH13:AJ13) -> 156000 | CI13: =SUM(CJ13:CM13) -> 638841.85 | CJ13: =SUM(AQ13:AS13) -> 150146.53 | CK13: =SUM(AT13:AV13) -> 156465.84 | CL13: =SUM(AW13:AY13) -> 167502.7 | CM13: =SUM(AZ13:BB13) -> 164726.78 | CP13: =$C13 -> Rent and other | CR13: =E13-W13 -> -465090.32 | CS13: =F13-X13 -> 2909.68 | CT13: =G13-Y13 -> 3852 | CU13: =H13-Z13 -> 1392 | CV13: =I13-AA13 -> -2334.32 | CW13: =J13-AB13 -> -52000 | CX13: =K13-AC13 -> -52000 | CY13: =L13-AD13 -> -52000 | ... DE13: =R13-AJ13 -> -52000 | DH13: =$C13 -> Rent and other | DJ13: =IFERROR(((E13-W13)/ABS(W13))+1,"") -> 0.25466295 | DK13: =IFERROR(((F13-X13)/ABS(X13))+1,"") -> 1.0186518 | DL13: =IFERROR(((G13-Y13)/ABS(Y13))+1,"") -> 1.0740769 | DM13: =IFERROR(((H13-Z13)/ABS(Z13))+1,"") -> 1.0267692 | DN13: =IFERROR(((I13-AA13)/ABS(AA13))+1,"") -> 0.95510923 | DO13: =IFERROR(((J13-AB13)/ABS(AB13))+1,"") -> 0 | DP13: =IFERROR(((K13-AC13)/ABS(AC13))+1,"") -> 0 | DQ13: =IFERROR(((L13-AD13)/ABS(AD13))+1,"") -> 0 | ... DW13: =IFERROR(((R13-AJ13)/ABS(AJ13))+1,"") -> 0
E14: =SUM(G14:R14) -> 0 | F14: =SUMPRODUCT((G$6:R$6<=F$6)*(G14:R14)) -> 0 | U14: =$C14 -> 0 | W14: =SUM(Y14:AJ14) -> 0 | X14: =SUMPRODUCT((Y$6:AJ$6<=X$6)*(Y14:AJ14)) -> 0 | AM14: =$C14 -> 0 | AO14: =SUM(AQ14:BB14) -> 0 | AP14: =SUMPRODUCT((AQ$6:BB$6<=AP$6)*(AQ14:BB14)) -> 0 | BE14: =$C14 -> 0 | BG14: =SUM(BI14:BT14) -> 0 | BH14: =SUMPRODUCT((BI$6:BT$6<=BH$6)*(BI14:BT14)) -> 0 | BW14: =$C14 -> 0 | BY14: =SUM(BZ14:CC14) -> 0 | BZ14: =SUM(G14:I14) -> 0 | CA14: =SUM(J14:L14) -> 0 | CB14: =SUM(M14:O14) -> 0 | CC14: =SUM(P14:R14) -> 0 | CD14: =SUM(CE14:CH14) -> 0 | CE14: =SUM(Y14:AA14) -> 0 | CF14: =SUM(AB14:AD14) -> 0 | CG14: =SUM(AE14:AG14) -> 0 | CH14: =SUM(AH14:AJ14) -> 0 | CI14: =SUM(CJ14:CM14) -> 0 | CJ14: =SUM(AQ14:AS14) -> 0 | CK14: =SUM(AT14:AV14) -> 0 | CL14: =SUM(AW14:AY14) -> 0 | CM14: =SUM(AZ14:BB14) -> 0 | CP14: =$C14 -> 0 | CR14: =E14-W14 -> 0 | CS14: =F14-X14 -> 0 | CT14: =G14-Y14 -> 0 | CU14: =H14-Z14 -> 0 | CV14: =I14-AA14 -> 0 | CW14: =J14-AB14 -> 0 | CX14: =K14-AC14 -> 0 | CY14: =L14-AD14 -> 0 | ... DE14: =R14-AJ14 -> 0 | DH14: =$C14 -> 0 | DJ14: =IFERROR(((E14-W14)/ABS(W14))+1,"") | DK14: =IFERROR(((F14-X14)/ABS(X14))+1,"") | DL14: =IFERROR(((G14-Y14)/ABS(Y14))+1,"") | DM14: =IFERROR(((H14-Z14)/ABS(Z14))+1,"") | DN14: =IFERROR(((I14-AA14)/ABS(AA14))+1,"") | DO14: =IFERROR(((J14-AB14)/ABS(AB14))+1,"") | DP14: =IFERROR(((K14-AC14)/ABS(AC14))+1,"") | DQ14: =IFERROR(((L14-AD14)/ABS(AD14))+1,"") | ... DW14: =IFERROR(((R14-AJ14)/ABS(AJ14))+1,"")
E15: =SUM(G15:R15) -> 0 | F15: =SUMPRODUCT((G$6:R$6<=F$6)*(G15:R15)) -> 0 | U15: =$C15 -> 0 | W15: =SUM(Y15:AJ15) -> 0 | X15: =SUMPRODUCT((Y$6:AJ$6<=X$6)*(Y15:AJ15)) -> 0 | AM15: =$C15 -> 0 | AO15: =SUM(AQ15:BB15) -> 0 | AP15: =SUMPRODUCT((AQ$6:BB$6<=AP$6)*(AQ15:BB15)) -> 0 | BE15: =$C15 -> 0 | BG15: =SUM(BI15:BT15) -> 0 | BH15: =SUMPRODUCT((BI$6:BT$6<=BH$6)*(BI15:BT15)) -> 0 | BW15: =$C15 -> 0 | BY15: =SUM(BZ15:CC15) -> 0 | BZ15: =SUM(G15:I15) -> 0 | CA15: =SUM(J15:L15) -> 0 | CB15: =SUM(M15:O15) -> 0 | CC15: =SUM(P15:R15) -> 0 | CD15: =SUM(CE15:CH15) -> 0 | CE15: =SUM(Y15:AA15) -> 0 | CF15: =SUM(AB15:AD15) -> 0 | CG15: =SUM(AE15:AG15) -> 0 | CH15: =SUM(AH15:AJ15) -> 0 | CI15: =SUM(CJ15:CM15) -> 0 | CJ15: =SUM(AQ15:AS15) -> 0 | CK15: =SUM(AT15:AV15) -> 0 | CL15: =SUM(AW15:AY15) -> 0 | CM15: =SUM(AZ15:BB15) -> 0 | CP15: =$C15 -> 0 | CR15: =E15-W15 -> 0 | CS15: =F15-X15 -> 0 | CT15: =G15-Y15 -> 0 | CU15: =H15-Z15 -> 0 | CV15: =I15-AA15 -> 0 | CW15: =J15-AB15 -> 0 | CX15: =K15-AC15 -> 0 | CY15: =L15-AD15 -> 0 | ... DE15: =R15-AJ15 -> 0 | DH15: =$C15 -> 0 | DJ15: =IFERROR(((E15-W15)/ABS(W15))+1,"") | DK15: =IFERROR(((F15-X15)/ABS(X15))+1,"") | DL15: =IFERROR(((G15-Y15)/ABS(Y15))+1,"") | DM15: =IFERROR(((H15-Z15)/ABS(Z15))+1,"") | DN15: =IFERROR(((I15-AA15)/ABS(AA15))+1,"") | DO15: =IFERROR(((J15-AB15)/ABS(AB15))+1,"") | DP15: =IFERROR(((K15-AC15)/ABS(AC15))+1,"") | DQ15: =IFERROR(((L15-AD15)/ABS(AD15))+1,"") | ... DW15: =IFERROR(((R15-AJ15)/ABS(AJ15))+1,"")
E16: =SUM(G16:R16) -> 0 | F16: =SUMPRODUCT((G$6:R$6<=F$6)*(G16:R16)) -> 0 | U16: =$C16 -> 0 | W16: =SUM(Y16:AJ16) -> 0 | X16: =SUMPRODUCT((Y$6:AJ$6<=X$6)*(Y16:AJ16)) -> 0 | AM16: =$C16 -> 0 | AO16: =SUM(AQ16:BB16) -> 0 | AP16: =SUMPRODUCT((AQ$6:BB$6<=AP$6)*(AQ16:BB16)) -> 0 | BE16: =$C16 -> 0 | BG16: =SUM(BI16:BT16) -> 0 | BH16: =SUMPRODUCT((BI$6:BT$6<=BH$6)*(BI16:BT16)) -> 0 | BW16: =$C16 -> 0 | BY16: =SUM(BZ16:CC16) -> 0 | BZ16: =SUM(G16:I16) -> 0 | CA16: =SUM(J16:L16) -> 0 | CB16: =SUM(M16:O16) -> 0 | CC16: =SUM(P16:R16) -> 0 | CD16: =SUM(CE16:CH16) -> 0 | CE16: =SUM(Y16:AA16) -> 0 | CF16: =SUM(AB16:AD16) -> 0 | CG16: =SUM(AE16:AG16) -> 0 | CH16: =SUM(AH16:AJ16) -> 0 | CI16: =SUM(CJ16:CM16) -> 0 | CJ16: =SUM(AQ16:AS16) -> 0 | CK16: =SUM(AT16:AV16) -> 0 | CL16: =SUM(AW16:AY16) -> 0 | CM16: =SUM(AZ16:BB16) -> 0 | CP16: =$C16 -> 0 | CR16: =E16-W16 -> 0 | CS16: =F16-X16 -> 0 | CT16: =G16-Y16 -> 0 | CU16: =H16-Z16 -> 0 | CV16: =I16-AA16 -> 0 | CW16: =J16-AB16 -> 0 | CX16: =K16-AC16 -> 0 | CY16: =L16-AD16 -> 0 | ... DE16: =R16-AJ16 -> 0 | DH16: =$C16 -> 0 | DJ16: =IFERROR(((E16-W16)/ABS(W16))+1,"") | DK16: =IFERROR(((F16-X16)/ABS(X16))+1,"") | DL16: =IFERROR(((G16-Y16)/ABS(Y16))+1,"") | DM16: =IFERROR(((H16-Z16)/ABS(Z16))+1,"") | DN16: =IFERROR(((I16-AA16)/ABS(AA16))+1,"") | DO16: =IFERROR(((J16-AB16)/ABS(AB16))+1,"") | DP16: =IFERROR(((K16-AC16)/ABS(AC16))+1,"") | DQ16: =IFERROR(((L16-AD16)/ABS(AD16))+1,"") | ... DW16: =IFERROR(((R16-AJ16)/ABS(AJ16))+1,"")
E17: =SUM(G17:R17) -> 0 | F17: =SUMPRODUCT((G$6:R$6<=F$6)*(G17:R17)) -> 0 | U17: =$C17 -> 0 | W17: =SUM(Y17:AJ17) -> 0 | X17: =SUMPRODUCT((Y$6:AJ$6<=X$6)*(Y17:AJ17)) -> 0 | AM17: =$C17 -> 0 | AO17: =SUM(AQ17:BB17) -> 0 | AP17: =SUMPRODUCT((AQ$6:BB$6<=AP$6)*(AQ17:BB17)) -> 0 | BE17: =$C17 -> 0 | BG17: =SUM(BI17:BT17) -> 0 | BH17: =SUMPRODUCT((BI$6:BT$6<=BH$6)*(BI17:BT17)) -> 0 | BW17: =$C17 -> 0 | BY17: =SUM(BZ17:CC17) -> 0 | BZ17: =SUM(G17:I17) -> 0 | CA17: =SUM(J17:L17) -> 0 | CB17: =SUM(M17:O17) -> 0 | CC17: =SUM(P17:R17) -> 0 | CD17: =SUM(CE17:CH17) -> 0 | CE17: =SUM(Y17:AA17) -> 0 | CF17: =SUM(AB17:AD17) -> 0 | CG17: =SUM(AE17:AG17) -> 0 | CH17: =SUM(AH17:AJ17) -> 0 | CI17: =SUM(CJ17:CM17) -> 0 | CJ17: =SUM(AQ17:AS17) -> 0 | CK17: =SUM(AT17:AV17) -> 0 | CL17: =SUM(AW17:AY17) -> 0 | CM17: =SUM(AZ17:BB17) -> 0 | CP17: =$C17 -> 0 | CR17: =E17-W17 -> 0 | CS17: =F17-X17 -> 0 | CT17: =G17-Y17 -> 0 | CU17: =H17-Z17 -> 0 | CV17: =I17-AA17 -> 0 | CW17: =J17-AB17 -> 0 | CX17: =K17-AC17 -> 0 | CY17: =L17-AD17 -> 0 | ... DE17: =R17-AJ17 -> 0 | DH17: =$C17 -> 0 | DJ17: =IFERROR(((E17-W17)/ABS(W17))+1,"") | DK17: =IFERROR(((F17-X17)/ABS(X17))+1,"") | DL17: =IFERROR(((G17-Y17)/ABS(Y17))+1,"") | DM17: =IFERROR(((H17-Z17)/ABS(Z17))+1,"") | DN17: =IFERROR(((I17-AA17)/ABS(AA17))+1,"") | DO17: =IFERROR(((J17-AB17)/ABS(AB17))+1,"") | DP17: =IFERROR(((K17-AC17)/ABS(AC17))+1,"") | DQ17: =IFERROR(((L17-AD17)/ABS(AD17))+1,"") | ... DW17: =IFERROR(((R17-AJ17)/ABS(AJ17))+1,"")
A18: =IFERROR(CONCATENATE(VLOOKUP($C18,[86]Code!$G:$H,2,0),"-",VLOOKUP($A$5,[86]Code!$B:$D,3,0)),"N/A") -> N/A | B18: Total expenses | E18: =SUM(G18:R18) -> 3815402.1 | F18: =SUMPRODUCT((G$6:R$6<=F$6)*(G18:R18)) -> 3815402.1 | G18: =SUM(G19,G24,G28) -> 1316800.1 | H18: =SUM(H19,H24,H28) -> 1225815 | I18: =SUM(I19,I24,I28) -> 1272787 | J18: =SUM(J19,J24,J28) -> 0 | K18: =SUM(K19,K24,K28) -> 0 | L18: =SUM(L19,L24,L28) -> 0 | M18: =SUM(M19,M24,M28) -> 0 | N18: =SUM(N19,N24,N28) -> 0 | ... R18: =SUM(R19,R24,R28) -> 0 | T18: =$B18 -> Total expenses | W18: =SUM(Y18:AJ18) -> 15134151 | X18: =SUMPRODUCT((Y$6:AJ$6<=X$6)*(Y18:AJ18)) -> 3746341.8 | Y18: =SUM(Y19,Y24,Y28) -> 1247593.6 | Z18: =SUM(Z19,Z24,Z28) -> 1170406.2 | AA18: =SUM(AA19,AA24,AA28) -> 1328342 | AB18: =SUM(AB19,AB24,AB28) -> 1251159.1 | AC18: =SUM(AC19,AC24,AC28) -> 1259704.8 | AD18: =SUM(AD19,AD24,AD28) -> 1254775.8 | AE18: =SUM(AE19,AE24,AE28) -> 1264026.7 | AF18: =SUM(AF19,AF24,AF28) -> 1265262.3 | ... AJ18: =SUM(AJ19,AJ24,AJ28) -> 1301202.3 | AL18: =$B18 -> Total expenses | AO18: =SUM(AQ18:BB18) -> 14580573 | AP18: =SUMPRODUCT((AQ$6:BB$6<=AP$6)*(AQ18:BB18)) -> 3547886.1 | AQ18: =SUM(AQ19,AQ24,AQ28) -> 1072945.9 | AR18: =SUM(AR19,AR24,AR28) -> 1222436.9 | AS18: =SUM(AS19,AS24,AS28) -> 1252503.3 | AT18: =SUM(AT19,AT24,AT28) -> 1140553.7 | AU18: =SUM(AU19,AU24,AU28) -> 1224346 | AV18: =SUM(AV19,AV24,AV28) -> 1122852.2 | AW18: =SUM(AW19,AW24,AW28) -> 1169053.8 | AX18: =SUM(AX19,AX24,AX28) -> 1270947.4 | ... BB18: =SUM(BB19,BB24,BB28) -> 1538023.7 | BD18: =$B18 -> Total expenses | BG18: =SUM(BI18:BT18) -> 14409648 | BH18: =SUMPRODUCT((BI$6:BT$6<=BH$6)*(BI18:BT18)) -> 3572190 | BI18: =SUM(BI19,BI24,BI28) -> 1226698 | BJ18: =SUM(BJ19,BJ24,BJ28) -> 1191770 | BK18: =SUM(BK19,BK24,BK28) -> 1153722 | BL18: =SUM(BL19,BL24,BL28) -> 1147825 | BM18: =SUM(BM19,BM24,BM28) -> 1239468 | BN18: =SUM(BN19,BN24,BN28) -> 1242310 | BO18: =SUM(BO19,BO24,BO28) -> 1265721 | BP18: =SUM(BP19,BP24,BP28) -> 1213180 | ... BT18: =SUM(BT19,BT24,BT28) -> 1238567 | BV18: =$B18 -> Total expenses | BY18: =SUM(BZ18:CC18) -> 3815402.1 | BZ18: =SUM(G18:I18) -> 3815402.1 | CA18: =SUM(J18:L18) -> 0 | CB18: =SUM(M18:O18) -> 0 | CC18: =SUM(P18:R18) -> 0 | CD18: =SUM(CE18:CH18) -> 15134151 | CE18: =SUM(Y18:AA18) -> 3746341.8 | CF18: =SUM(AB18:AD18) -> 3765639.7 | CG18: =SUM(AE18:AG18) -> 3764358.4 | CH18: =SUM(AH18:AJ18) -> 3857811.1 | CI18: =SUM(CJ18:CM18) -> 14580573 | CJ18: =SUM(AQ18:AS18) -> 3547886.1 | CK18: =SUM(AT18:AV18) -> 3487751.9 | CL18: =SUM(AW18:AY18) -> 3602555.1 | CM18: =SUM(AZ18:BB18) -> 3942380.3 | CO18: =$B18 -> Total expenses | CR18: =E18-W18 -> -11318749 | CS18: =F18-X18 -> 69060.218 | CT18: =G18-Y18 -> 69206.434 | CU18: =H18-Z18 -> 55408.787 | CV18: =I18-AA18 -> -55555.002 | CW18: =J18-AB18 -> -1251159.1 | CX18: =K18-AC18 -> -1259704.8 | CY18: =L18-AD18 -> -1254775.8 | ... DE18: =R18-AJ18 -> -1301202.3 | DG18: =$B18 -> Total expenses | DJ18: =IFERROR(((E18-W18)/ABS(W18))+1,"") -> 0.25210546 | DK18: =IFERROR(((F18-X18)/ABS(X18))+1,"") -> 1.018434 | DL18: =IFERROR(((G18-Y18)/ABS(Y18))+1,"") -> 1.0554719 | DM18: =IFERROR(((H18-Z18)/ABS(Z18))+1,"") -> 1.0473415 | DN18: =IFERROR(((I18-AA18)/ABS(AA18))+1,"") -> 0.95817719 | DO18: =IFERROR(((J18-AB18)/ABS(AB18))+1,"") -> 0 | DP18: =IFERROR(((K18-AC18)/ABS(AC18))+1,"") -> 0 | DQ18: =IFERROR(((L18-AD18)/ABS(AD18))+1,"") -> 0 | ... DW18: =IFERROR(((R18-AJ18)/ABS(AJ18))+1,"") -> 0
C19: Subtotal Cost of Sales | E19: =SUM(G19:R19) -> 128914.91 | F19: =SUMPRODUCT((G$6:R$6<=F$6)*(G19:R19)) -> 128914.91 | G19: =SUM(G20:G23) -> 49628 | H19: =SUM(H20:H23) -> 39680 | I19: =SUM(I20:I23) -> 39606.91 | J19: =SUM(J20:J23) -> 0 | K19: =SUM(K20:K23) -> 0 | L19: =SUM(L20:L23) -> 0 | M19: =SUM(M20:M23) -> 0 | N19: =SUM(N20:N23) -> 0 | ... R19: =SUM(R20:R23) -> 0 | U19: =$C19 -> Subtotal Cost of Sales | W19: =SUM(Y19:AJ19) -> 714720 | X19: =SUMPRODUCT((Y$6:AJ$6<=X$6)*(Y19:AJ19)) -> 172490 | Y19: =SUM(Y20:Y23) -> 56722 | Z19: =SUM(Z20:Z23) -> 56596 | AA19: =SUM(AA20:AA23) -> 59172 | AB19: =SUM(AB20:AB23) -> 59244 | AC19: =SUM(AC20:AC23) -> 59305 | AD19: =SUM(AD20:AD23) -> 60386 | AE19: =SUM(AE20:AE23) -> 60651 | AF19: =SUM(AF20:AF23) -> 55476 | ... AJ19: =SUM(AJ20:AJ23) -> 62091 | AM19: =$C19 -> Subtotal Cost of Sales | AO19: =SUM(AQ19:BB19) -> 692212.33 | AP19: =SUMPRODUCT((AQ$6:BB$6<=AP$6)*(AQ19:BB19)) -> 167230.94 | AQ19: =SUM(AQ20:AQ23) -> 55719.95 | AR19: =SUM(AR20:AR23) -> 52442.7 | AS19: =SUM(AS20:AS23) -> 59068.29 | AT19: =SUM(AT20:AT23) -> 64170.96 | AU19: =SUM(AU20:AU23) -> 56011.18 | AV19: =SUM(AV20:AV23) -> 51216.19 | AW19: =SUM(AW20:AW23) -> 63749.97 | AX19: =SUM(AX20:AX23) -> 57226.67 | ... BB19: =SUM(BB20:BB23) -> 52559.82 | BE19: =$C19 -> Subtotal Cost of Sales | BG19: =SUM(BI19:BT19) -> 618828.27 | BH19: =SUMPRODUCT((BI$6:BT$6<=BH$6)*(BI19:BT19)) -> 148414 | BI19: =SUM(BI20:BI23) -> 49379 | BJ19: =SUM(BJ20:BJ23) -> 50536 | BK19: =SUM(BK20:BK23) -> 48499 | BL19: =SUM(BL20:BL23) -> 46323 | BM19: =SUM(BM20:BM23) -> 43180 | BN19: =SUM(BN20:BN23) -> 60442 | BO19: =SUM(BO20:BO23) -> 60631 | BP19: =SUM(BP20:BP23) -> 55152 | ... BT19: =SUM(BT20:BT23) -> 49066.48 | BW19: =$C19 -> Subtotal Cost of Sales | BY19: =SUM(BZ19:CC19) -> 128914.91 | BZ19: =SUM(G19:I19) -> 128914.91 | CA19: =SUM(J19:L19) -> 0 | CB19: =SUM(M19:O19) -> 0 | CC19: =SUM(P19:R19) -> 0 | CD19: =SUM(CE19:CH19) -> 714720 | CE19: =SUM(Y19:AA19) -> 172490 | CF19: =SUM(AB19:AD19) -> 178935 | CG19: =SUM(AE19:AG19) -> 173080 | CH19: =SUM(AH19:AJ19) -> 190215 | CI19: =SUM(CJ19:CM19) -> 692212.33 | CJ19: =SUM(AQ19:AS19) -> 167230.94 | CK19: =SUM(AT19:AV19) -> 171398.33 | CL19: =SUM(AW19:AY19) -> 180902.31 | CM19: =SUM(AZ19:BB19) -> 172680.75 | CP19: =$C19 -> Subtotal Cost of Sales | CR19: =E19-W19 -> -585805.09 | CS19: =F19-X19 -> -43575.09 | CT19: =G19-Y19 -> -7094 | CU19: =H19-Z19 -> -16916 | CV19: =I19-AA19 -> -19565.09 | CW19: =J19-AB19 -> -59244 | CX19: =K19-AC19 -> -59305 | CY19: =L19-AD19 -> -60386 | ... DE19: =R19-AJ19 -> -62091 | DH19: =$C19 -> Subtotal Cost of Sales | DJ19: =IFERROR(((E19-W19)/ABS(W19))+1,"") -> 0.18037121 | DK19: =IFERROR(((F19-X19)/ABS(X19))+1,"") -> 0.74737614 | DL19: =IFERROR(((G19-Y19)/ABS(Y19))+1,"") -> 0.87493389 | DM19: =IFERROR(((H19-Z19)/ABS(Z19))+1,"") -> 0.70110962 | DN19: =IFERROR(((I19-AA19)/ABS(AA19))+1,"") -> 0.66935223 | DO19: =IFERROR(((J19-AB19)/ABS(AB19))+1,"") -> 0 | DP19: =IFERROR(((K19-AC19)/ABS(AC19))+1,"") -> 0 | DQ19: =IFERROR(((L19-AD19)/ABS(AD19))+1,"") -> 0 | ... DW19: =IFERROR(((R19-AJ19)/ABS(AJ19))+1,"") -> 0
